Workbook
Name _Fill: #REF!
Name _Fill: #REF!
Name _Key2: #REF!
Name _Key2: #REF!
Name _Sort: #REF!
Name _Table2_In2: #REF!
Name _Table2_Out: #REF!
Name cap: #REF!
Name d: #REF!
Name dfasfasf: #REF!
Name increase: #REF!
Name increase1: #REF!
Name MasterCheck: #REF!
Name newsf: #REF!
Name rate: #REF!
Name RentRollProperty: #REF!
Name salesprice: #REF!
Name salesprice: #REF!
Name SnapshotAnnexRow: #REF!
Name SnapshotAutofilter1: #REF!
Name SnapshotProperty: #REF!
Name SnapshotSqFtRentedPercent: #REF!
Name SnapshotUnitRentedPercent: #REF!
Name transpose07occ: #REF!
Name transpose08occ: #REF!
Name transpose09occ: #REF!
Name UnitMixProperty: #REF!

Sheet How to

Sheet Summary
H1: Year | I1: Year | J1: Year | K1: Year | L1: Year
G2: In-Place | H2: 1 | I2: =H2+1 -> 2 | J2: =I2+1 -> 3 | K2: =J2+1 -> 4 | L2: =K2+1 -> 5
B3: Assumptions | E3: Average Rates
B4: Starting Rate | C4: =Projection!I30 -> 17.789291 | F4: Occupancy | G4: =$C$24/$C$23 -> 0 | H4: =AVERAGEIF(Monthly!$2:$2,Summary!H$2,Monthly!$6:$6) -> 0.18741743 | I4: =AVERAGEIF(Monthly!$2:$2,Summary!I$2,Monthly!$6:$6) -> 0.52877606 | J4: =AVERAGEIF(Monthly!$2:$2,Summary!J$2,Monthly!$6:$6) -> 0.81630358 | K4: =AVERAGEIF(Monthly!$2:$2,Summary!K$2,Monthly!$6:$6) -> 0.92 | L4: =AVERAGEIF(Monthly!$2:$2,Summary!L$2,Monthly!$6:$6) -> 0.91760417
F5: Rental Rate | G5: =$C$4 -> 17.789291 | H5: =AVERAGEIF(Monthly!$2:$2,Summary!H$2,Monthly!$10:$10) -> 18.918678 | I5: =AVERAGEIF(Monthly!$2:$2,Summary!I$2,Monthly!$10:$10) -> 19.607006 | J5: =AVERAGEIF(Monthly!$2:$2,Summary!J$2,Monthly!$10:$10) -> 20.320378 | K5: =AVERAGEIF(Monthly!$2:$2,Summary!K$2,Monthly!$10:$10) -> 21.059704 | L5: =AVERAGEIF(Monthly!$2:$2,Summary!L$2,Monthly!$10:$10) -> 21.812382
B6: Rate Growth | F6: Avg. Rental Rate | H6: =AVERAGEIF(Monthly!$2:$2,Summary!H$2,Monthly!$23:$23) -> 19.265521 | I6: =AVERAGEIF(Monthly!$2:$2,Summary!I$2,Monthly!$23:$23) -> 19.966468 | J6: =AVERAGEIF(Monthly!$2:$2,Summary!J$2,Monthly!$23:$23) -> 20.413654 | K6: =AVERAGEIF(Monthly!$2:$2,Summary!K$2,Monthly!$23:$23) -> 20.553838 | L6: =AVERAGEIF(Monthly!$2:$2,Summary!L$2,Monthly!$23:$23) -> 21.313117
B7: 1 | C7: =Inputs!I19 -> 0.04 | F7: Implied Full-Price Rate | H7: =AVERAGEIF(Monthly!$2:$2,Summary!H$2,Monthly!$12:$12) -> 0 | I7: =AVERAGEIF(Monthly!$2:$2,Summary!I$2,Monthly!$12:$12) -> 0 | J7: =AVERAGEIF(Monthly!$2:$2,Summary!J$2,Monthly!$12:$12) -> 0 | K7: =AVERAGEIF(Monthly!$2:$2,Summary!K$2,Monthly!$12:$12) -> 0 | L7: =AVERAGEIF(Monthly!$2:$2,Summary!L$2,Monthly!$12:$12) -> 0
B8: 2 | C8: =Inputs!I20 -> 0.04 | F8: Implied Internet Rate | H8: =AVERAGEIF(Monthly!$2:$2,Summary!H$2,Monthly!$13:$13) -> 0 | I8: =AVERAGEIF(Monthly!$2:$2,Summary!I$2,Monthly!$13:$13) -> 0 | J8: =AVERAGEIF(Monthly!$2:$2,Summary!J$2,Monthly!$13:$13) -> 0 | K8: =AVERAGEIF(Monthly!$2:$2,Summary!K$2,Monthly!$13:$13) -> 0 | L8: =AVERAGEIF(Monthly!$2:$2,Summary!L$2,Monthly!$13:$13) -> 0
B9: 3 | C9: =Inputs!I21 -> 0.04
B10: 4 | C10: =Inputs!I22 -> 0.04 | F10: In-Place Rate | G10: =IFERROR($C$25/$C$24*12,0) -> 0 | H10: =H24/(H4*$C$23) -> 19.859233 | I10: =I24/(I4*$C$23) -> 20.810242 | J10: =J24/(J4*$C$23) -> 21.794342 | K10: =K24/(K4*$C$23) -> 22.648495 | L10: =L24/(L4*$C$23) -> 31.686167
B11: 5 | C11: =Inputs!I23 -> 0.04 | F11: Achieved Rate | H11: =H27/(H4*$C$23) -> 15.346934 | I11: =I27/(I4*$C$23) -> 17.945767 | J11: =J27/(J4*$C$23) -> 19.927324 | K11: =K27/(K4*$C$23) -> 21.735555 | L11: =L27/(L4*$C$23) -> 30.474012
B13: Property Age | C13: =Inputs!C10 -> 1 | E13: Ending Rates
F14: Occupancy | G14: =$C$24/$C$23 -> 0 | H14: =SUMIFS(Monthly!$6:$6,Monthly!$3:$3,12*Summary!H$2,Monthly!$2:$2,Summary!H$2) -> 0.33 | I14: =SUMIFS(Monthly!$6:$6,Monthly!$3:$3,12*Summary!I$2,Monthly!$2:$2,Summary!I$2) -> 0.68 | J14: =SUMIFS(Monthly!$6:$6,Monthly!$3:$3,12*Summary!J$2,Monthly!$2:$2,Summary!J$2) -> 0.92 | K14: =SUMIFS(Monthly!$6:$6,Monthly!$3:$3,12*Summary!K$2,Monthly!$2:$2,Summary!K$2) -> 0.90766667 | L14: =SUMIFS(Monthly!$6:$6,Monthly!$3:$3,12*Summary!L$2,Monthly!$2:$2,Summary!L$2) -> 0.90766667
B15: Writeoff % | C15: =Inputs!J37 -> -0.01 | F15: Net Effective Rate | G15: =Monthly!C10 -> 17.789291 | H15: =SUMIFS(Monthly!$10:$10,Monthly!$3:$3,12*Summary!H$2,Monthly!$2:$2,Summary!H$2) -> 18.436528 | I15: =SUMIFS(Monthly!$10:$10,Monthly!$3:$3,12*Summary!I$2,Monthly!$2:$2,Summary!I$2) -> 19.107314 | J15: =SUMIFS(Monthly!$10:$10,Monthly!$3:$3,12*Summary!J$2,Monthly!$2:$2,Summary!J$2) -> 19.802505 | K15: =SUMIFS(Monthly!$10:$10,Monthly!$3:$3,12*Summary!K$2,Monthly!$2:$2,Summary!K$2) -> 20.522989 | L15: =SUMIFS(Monthly!$10:$10,Monthly!$3:$3,12*Summary!L$2,Monthly!$2:$2,Summary!L$2) -> 21.269687
F16: Implied Avg. Rental Rate | H16: =SUMIFS(Monthly!$23:$23,Monthly!$3:$3,12*Summary!H$2,Monthly!$2:$2,Summary!H$2) -> 18.774531 | I16: =SUMIFS(Monthly!$23:$23,Monthly!$3:$3,12*Summary!I$2,Monthly!$2:$2,Summary!I$2) -> 19.457614 | J16: =SUMIFS(Monthly!$23:$23,Monthly!$3:$3,12*Summary!J$2,Monthly!$2:$2,Summary!J$2) -> 19.333655 | K16: =SUMIFS(Monthly!$23:$23,Monthly!$3:$3,12*Summary!K$2,Monthly!$2:$2,Summary!K$2) -> 20.148214 | L16: =SUMIFS(Monthly!$23:$23,Monthly!$3:$3,12*Summary!L$2,Monthly!$2:$2,Summary!L$2) -> 20.881276
B17: Cust. Choice | C17: FALSE | F17: Implied Full-Price Rate | G17: =Monthly!C12 -> 0 | H17: =SUMIFS(Monthly!$12:$12,Monthly!$3:$3,12*Summary!H$2,Monthly!$2:$2,Summary!H$2) -> 0 | I17: =SUMIFS(Monthly!$12:$12,Monthly!$3:$3,12*Summary!I$2,Monthly!$2:$2,Summary!I$2) -> 0 | J17: =SUMIFS(Monthly!$12:$12,Monthly!$3:$3,12*Summary!J$2,Monthly!$2:$2,Summary!J$2) -> 0 | K17: =SUMIFS(Monthly!$12:$12,Monthly!$3:$3,12*Summary!K$2,Monthly!$2:$2,Summary!K$2) -> 0 | L17: =SUMIFS(Monthly!$12:$12,Monthly!$3:$3,12*Summary!L$2,Monthly!$2:$2,Summary!L$2) -> 0
B18: Cust Choice % | C18: 0.25 | F18: Implied Internet Rate | G18: =Monthly!C13 -> 0 | H18: =SUMIFS(Monthly!$13:$13,Monthly!$3:$3,12*Summary!H$2,Monthly!$2:$2,Summary!H$2) -> 0 | I18: =SUMIFS(Monthly!$13:$13,Monthly!$3:$3,12*Summary!I$2,Monthly!$2:$2,Summary!I$2) -> 0 | J18: =SUMIFS(Monthly!$13:$13,Monthly!$3:$3,12*Summary!J$2,Monthly!$2:$2,Summary!J$2) -> 0 | K18: =SUMIFS(Monthly!$13:$13,Monthly!$3:$3,12*Summary!K$2,Monthly!$2:$2,Summary!K$2) -> 0 | L18: =SUMIFS(Monthly!$13:$13,Monthly!$3:$3,12*Summary!L$2,Monthly!$2:$2,Summary!L$2) -> 0
B19: Non-FMF Disc | C19: -0.005
B20: Churn Adj. | C20: 0 | F20: In-Place Rate | G20: =IFERROR($C$25/$C$24*12,0) -> 0 | H20: =SUMIFS(Monthly!$40:$40,Monthly!$3:$3,12*Summary!H$2,Monthly!$2:$2,Summary!H$2) -> 20.160365 | I20: =SUMIFS(Monthly!$40:$40,Monthly!$3:$3,12*Summary!I$2,Monthly!$2:$2,Summary!I$2) -> 21.209467 | J20: =SUMIFS(Monthly!$40:$40,Monthly!$3:$3,12*Summary!J$2,Monthly!$2:$2,Summary!J$2) -> 22.05744 | K20: =SUMIFS(Monthly!$40:$40,Monthly!$3:$3,12*Summary!K$2,Monthly!$2:$2,Summary!K$2) -> 23.088462 | L20: =SUMIFS(Monthly!$40:$40,Monthly!$3:$3,12*Summary!L$2,Monthly!$2:$2,Summary!L$2) -> 24.114293
F21: Achieved Rate | H21: =SUMIFS(Monthly!$41:$41,Monthly!$3:$3,12*Summary!H$2,Monthly!$2:$2,Summary!H$2) -> 17.46595 | I21: =SUMIFS(Monthly!$41:$41,Monthly!$3:$3,12*Summary!I$2,Monthly!$2:$2,Summary!I$2) -> 18.996297 | J21: =SUMIFS(Monthly!$41:$41,Monthly!$3:$3,12*Summary!J$2,Monthly!$2:$2,Summary!J$2) -> 21.002753 | K21: =SUMIFS(Monthly!$41:$41,Monthly!$3:$3,12*Summary!K$2,Monthly!$2:$2,Summary!K$2) -> 22.181987 | L21: =SUMIFS(Monthly!$41:$41,Monthly!$3:$3,12*Summary!L$2,Monthly!$2:$2,Summary!L$2) -> 23.213143
B22: In-Place Metrics
B23: Total SF | C23: =Inputs!C13-Inputs!C23 -> 105807 | E23: Net Rental Income Buildup
B24: Occ SF | C24: =Inputs!C18 -> 0 | F24: Rental Income | H24: =SUMIF(Monthly!$2:$2,Summary!H$2,Monthly!34:34) -> 393810.09 | I24: =SUMIF(Monthly!$2:$2,Summary!I$2,Monthly!34:34) -> 1164295.8 | J24: =SUMIF(Monthly!$2:$2,Summary!J$2,Monthly!34:34) -> 1882391.1 | K24: =SUMIF(Monthly!$2:$2,Summary!K$2,Monthly!34:34) -> 2204659.7 | L24: =SUMIF(Monthly!$2:$2,Summary!L$2,Monthly!34:34) -> 3076376.5
B25: Proj Rent | C25: =Inputs!C20 -> 0 | F25: Discounts | H25: =SUMIF(Monthly!$2:$2,Summary!H$2,Monthly!35:35) -> -85541.134 | I25: =SUMIF(Monthly!$2:$2,Summary!I$2,Monthly!35:35) -> -148619.28 | J25: =SUMIF(Monthly!$2:$2,Summary!J$2,Monthly!35:35) -> -142431.67 | K25: =SUMIF(Monthly!$2:$2,Summary!K$2,Monthly!35:35) -> -66821.14 | L25: =SUMIF(Monthly!$2:$2,Summary!L$2,Monthly!35:35) -> -86923.078
F26: Write-Offs | H26: =SUMIF(Monthly!$2:$2,Summary!H$2,Monthly!36:36) -> -3938.1009 | I26: =SUMIF(Monthly!$2:$2,Summary!I$2,Monthly!36:36) -> -11642.958 | J26: =SUMIF(Monthly!$2:$2,Summary!J$2,Monthly!36:36) -> -18823.911 | K26: =SUMIF(Monthly!$2:$2,Summary!K$2,Monthly!36:36) -> -22046.597 | L26: =SUMIF(Monthly!$2:$2,Summary!L$2,Monthly!36:36) -> -30763.765
F27: Net Rental Income | H27: =SUMIF(Monthly!$2:$2,Summary!H$2,Monthly!37:37) -> 304330.86 | I27: =SUMIF(Monthly!$2:$2,Summary!I$2,Monthly!37:37) -> 1004033.5 | J27: =SUMIF(Monthly!$2:$2,Summary!J$2,Monthly!37:37) -> 1721135.5 | K27: =SUMIF(Monthly!$2:$2,Summary!K$2,Monthly!37:37) -> 2115792 | L27: =SUMIF(Monthly!$2:$2,Summary!L$2,Monthly!37:37) -> 2958689.6
F29: Ending In-Place Rate Growth | H29: =IFERROR(H20/G20-1,0) -> 0 | I29: =IFERROR(I20/H20-1,0) -> 0.052037838 | J29: =IFERROR(J20/I20-1,0) -> 0.039980844 | K29: =IFERROR(K20/J20-1,0) -> 0.04674261 | L29: =IFERROR(L20/K20-1,0) -> 0.044430467
F30: Full Year In-Place Rate Growth | H30: =IFERROR(H10/G10-1,0) -> 0 | I30: =IFERROR(I10/H10-1,0) -> 0.047887498 | J30: =IFERROR(J10/I10-1,0) -> 0.047289218 | K30: =IFERROR(K10/J10-1,0) -> 0.039191484 | L30: =IFERROR(L10/K10-1,0) -> 0.39904075
F31: Ann'l Achieved RPSF Growth | H31: =IFERROR(H11/G11-1,0) -> 0 | I31: =IFERROR(I11/H11-1,0) -> 0.16933893 | J31: =IFERROR(J11/I11-1,0) -> 0.11041915 | K31: =IFERROR(K11/J11-1,0) -> 0.090741335 | L31: =IFERROR(L11/K11-1,0) -> 0.40203512
F32: Disc % of Rental Income | H32: =H25/H24 -> -0.21721418 | I32: =I25/I24 -> -0.12764736 | J32: =J25/J24 -> -0.075665289 | K32: =K25/K24 -> -0.030309049 | L32: =L25/L24 -> -0.02825502

Sheet Inputs
B2: Basic Info | E2: Rental Income Assumptions | L2: Expense Assumptions | T2: Expense Calcluations for Model | X2: Market | Y2: GM Pay | Z2: SM Pay
B3: Address | C3: 250 Dolson Avenue | E3: Occupancy Inputs | L3: Payroll Expense | O3: Comp Data | P3: Override | Q3: Model | R3: Year 1 Total | U3: Hours | V3: Avg Rate | X3: Major Metro | Y3: 30.05 | Z3: 25.38
B4: City | C4: Middletown | E4: Current Occupancy | G4: 0 | I4: =(Inputs!C18-Inputs!C24)/(Inputs!C13-Inputs!C23) -> 0 | M4: # of Full-Time Employees | O4: =ROUNDDOWN($U$8/40,0) -> 1 | P4: 0 | Q4: =IF(P4=0,O4,P4) -> 1 | T4: Total Store Hours | U4: =IF(Inputs!$C$14<300,64,64+(INT(Inputs!$C$14/100-2)*8)) -> 96 | X4: National | Y4: 24.55 | Z4: 20.43
B5: State | C5: New York | H5: Rented SF | I5: Ending Occ % | J5: Avg Occ | L5: 6112 | M5: Medical Expense | N5: per FTE | P5: 822 | Q5: =IF(P5=0,O5,P5) -> 822 | R5: =Projection!$BW$85 -> 9864 | T5: Gen. Mgr | U5: 40 | V5: =Y9 -> 28.846154 | X5: Secondary | Y5: 19.82 | Z5: 16
B6: Zip | C6: 10940 | F6: =IF(G6<$I$12,"Occ @ End of Year:","Average Occ") -> Occ @ End of Year: | G6: 1 | H6: =Projection!U25 -> 34916.31 | I6: 0.33 | J6: =HLOOKUP($E19,Projection!$BW$7:$CC$24,18,FALSE) -> 0.18741743 | L6: 6130 | M6: Payroll Taxes | N6: % of Sal. | O6: =IFERROR(SUMIF('Expense Comp Data'!$B:$B,Inputs!$L6,'Expense Comp Data'!$I:$I)/SUMIF('Expense Comp Data'!$B:$B,6100,'Expense Comp Data'!$I:$I),"No Comps") -> No Comps | P6: 0.01 | Q6: =IF(P6=0,O6,P6) -> 0.01 | R6: =Projection!BW87 -> 601.33846 | T6: Manager | U6: 0 | V6: =Z9 -> 21.634615
B7: New Development? | C7: TRUE | F7: =IF(G7<$I$12,"Occ @ End of Year:","Average Occ") -> Occ @ End of Year: | G7: 2 | H7: =Projection!AG25 -> 71948.76 | I7: 0.68 | J7: =HLOOKUP($E20,Projection!$BW$7:$CC$24,18,FALSE) -> 0.52877606 | L7: 6283 | M7: Workers Comp. | N7: % of Sal. | O7: =IFERROR(SUMIF('Expense Comp Data'!$B:$B,Inputs!$L7,'Expense Comp Data'!$I:$I)/SUMIF('Expense Comp Data'!$B:$B,6100,'Expense Comp Data'!$I:$I),"No Comps") -> No Comps | P7: 0.01 | Q7: =IF(P7=0,O7,P7) -> 0.01 | R7: =Projection!BW89 -> 595.38462 | T7: Maint. | U7: 0 | X7: Market | Y7: GM Pay | Z7: SM Pay | AA7: Maintenance Pay
B8: Projection Start Date (EOM) | C8: 46053 | F8: =IF(G8<$I$12,"Occ @ End of Year:","Average Occ") -> Occ @ End of Year: | G8: 3 | H8: =Projection!AS25 -> 97342.44 | I8: 0.92 | J8: =HLOOKUP($E21,Projection!$BW$7:$CC$24,18,FALSE) -> 0.81630358 | R8: =Projection!BW90 -> 71789.954 | T8: Total | U8: =SUM(U5:U7) -> 40 | V8: =SUMPRODUCT($V$5:$V$7,$U$5:$U$7)/$U$8 -> 28.846154 | X8: Annual Salary | Y8: 60000 | Z8: 45000 | AA8: 50000
B9: 1 Year Budget/Upload Start | C9: =C8 -> 46053 | F9: =IF(G9<$I$12,"Occ @ End of Year:","Average Occ") -> Average Occ | G9: 4 | H9: =Projection!BE25 -> 96037.487 | I9: 0.92 | J9: =HLOOKUP($E22,Projection!$BW$7:$CC$24,18,FALSE) -> 0.92 | L9: Utility Expense | O9: Comp Data | P9: Override | Q9: Model | R9: Year 1 | X9: Hourly Rate | Y9: =Y8/2080 -> 28.846154 | Z9: =Z8/2080 -> 21.634615 | AA9: =AA8/2080 -> 24.038462
B10: Property Age (Years) | C10: 1 | F10: =IF(G10<$I$12,"Occ @ End of Year:","Average Occ") -> Average Occ | G10: 5 | H10: =Projection!BU25 -> 96883.943 | I10: 0.92 | J10: =HLOOKUP($E23,Projection!$BW$7:$CC$24,18,FALSE) -> 0.92 | L10: 6150 | M10: Rubbish Removal | N10: psf | O10: =IFERROR(SUMIF('Expense Comp Data'!$B:$B,Inputs!$L10,'Expense Comp Data'!$I:$I)/SUMIF('Expense Comp Data'!$B:$B,"SqFoot_Total",'Expense Comp Data'!$I:$I),"No Comps") -> No Comps | P10: 0.11 | Q10: =IF(P10=0,O10,P10) -> 0.11 | R10: =Projection!BW93 -> 11638.77 | T10: Year 1 Output | U10: Payroll | V10: =Projection!BW84 -> 59538.462
L11: 6158 | M11: Exterminating | N11: psf | O11: =IFERROR(SUMIF('Expense Comp Data'!$B:$B,Inputs!$L11,'Expense Comp Data'!$I:$I)/SUMIF('Expense Comp Data'!$B:$B,"SqFoot_Total",'Expense Comp Data'!$I:$I),"No Comps") -> No Comps | P11: 0.05 | Q11: =IF(P11=0,O11,P11) -> 0.05 | R11: =Projection!BW94 -> 5290.35
B12: Current Property Info | E12: 1st Fully Stable Year | I12: 4 | L12: 6184 | M12: Electric | N12: psf | O12: =IFERROR(SUMIF('Expense Comp Data'!$B:$B,Inputs!$L12,'Expense Comp Data'!$I:$I)/SUMIF('Expense Comp Data'!$B:$B,"SqFoot_Total",'Expense Comp Data'!$I:$I),"No Comps") -> No Comps | P12: 0.28 | Q12: =IF(P12=0,O12,P12) -> 0.28 | R12: =Projection!BW95 -> 29625.96 | T12: Historical Utility Expense Calculator
B13: Total Square Feet | C13: 105807 | E13: Stable Average Occupancy | I13: 0.92 | L13: 6185 | M13: Telephone | N13: psf | O13: =IFERROR(SUMIF('Expense Comp Data'!$B:$B,Inputs!$L13,'Expense Comp Data'!$I:$I)/SUMIF('Expense Comp Data'!$B:$B,"SqFoot_Total",'Expense Comp Data'!$I:$I),"No Comps") -> No Comps | P13: 0.05 | Q13: =IF(P13=0,O13,P13) -> 0.05 | R13: =Projection!BW96 -> 5290.35 | T13: Ann'l Expense | U13: Growth | V13: PSF
B14: Total Units | C14: 684 | L14: 6186 | M14: Water/Sewer | N14: psf | O14: =IFERROR(SUMIF('Expense Comp Data'!$B:$B,Inputs!$L14,'Expense Comp Data'!$I:$I)/SUMIF('Expense Comp Data'!$B:$B,"SqFoot_Total",'Expense Comp Data'!$I:$I),"No Comps") -> No Comps | P14: 0.12 | Q14: =IF(P14=0,O14,P14) -> 0.12 | R14: =Projection!BW97 -> 12696.84 | T14: 0 | U14: 0.025 | V14: =($T14*(1+U14))/Projection!$F$3 -> 0
A15: Owned | B15: Climated Controlled SF | C15: =C13 -> 105807 | E15: Rate Inputs | H15: IP Rate | I15: Rate Input | J15: Output | L15: 6187 | M15: Gas & Utilities | N15: psf | O15: =IFERROR(SUMIF('Expense Comp Data'!$B:$B,Inputs!$L15,'Expense Comp Data'!$I:$I)/SUMIF('Expense Comp Data'!$B:$B,"SqFoot_Total",'Expense Comp Data'!$I:$I),"No Comps") -> No Comps | P15: 0.1 | Q15: =IF(P15=0,O15,P15) -> 0.1 | R15: =Projection!BW98 -> 10580.7 | T15: 0 | U15: 0.025 | V15: =($T15*(1+U15))/Projection!$F$3 -> 0
A16: Managed | B16: Climate Controlled % | C16: =IFERROR(C15/C13, 0) -> 1 | E16: Starting Rates | H16: =IFERROR((C20-C30)/(C18-C24)*12,0) -> 0 | I16: =(('Rate Calculation'!R38*12)*0)+(1.55*12) -> 18.6 | J16: =I16 -> 18.6 | L16: 6200 | M16: Security Expense | N16: psf | O16: =IFERROR(SUMIF('Expense Comp Data'!$B:$B,Inputs!$L16,'Expense Comp Data'!$I:$I)/SUMIF('Expense Comp Data'!$B:$B,"SqFoot_Total",'Expense Comp Data'!$I:$I),"No Comps") -> No Comps | P16: 1e-12 | Q16: =IF(P16=0,O16,P16) -> 1e-12 | R16: =Projection!BW99 -> 1.05807e-07 | T16: 0 | U16: 0.025 | V16: =($T16*(1+U16))/Projection!$F$3 -> 0
A17: JV | B17: Starting Point | L17: 6205 | M17: Fire Alarm Monitoring | N17: psf | O17: =IFERROR(SUMIF('Expense Comp Data'!$B:$B,Inputs!$L17,'Expense Comp Data'!$I:$I)/SUMIF('Expense Comp Data'!$B:$B,"SqFoot_Total",'Expense Comp Data'!$I:$I),"No Comps") -> No Comps | P17: 0.01 | Q17: =IF(P17=0,O17,P17) -> 0.01 | R17: =Projection!BW100 -> 1058.07 | T17: 0 | U17: 0.025 | V17: =($T17*(1+U17))/Projection!$F$3 -> 0
B18: Occupied SF | C18: 0 | H18: IP Rate | I18: Rate Growth | J18: Avg Rate | M18: Total | R18: =Projection!BW101 -> 76181.04 | T18: 0 | U18: 0.025 | V18: =($T18*(1+U18))/Projection!$F$3 -> 0
B19: Occupied Units | C19: 0 | E19: 1 | H19: =Projection!BW34 -> 19.859233 | I19: 0.04 | J19: =Projection!BW30 -> 18.918678 | T19: 0 | U19: 0.025 | V19: =($T19*(1+U19))/Projection!$F$3 -> 0
B20: Projected Rent | C20: 0 | E20: 2 | H20: =Projection!BX34 -> 20.810242 | I20: 0.04 | J20: =Projection!BX30 -> 19.607006 | L20: R&M Expense | O20: Comp Data | P20: Override | Q20: Model | R20: Year 1 | T20: 0 | U20: 0.025 | V20: =($T20*(1+U20))/Projection!$F$3 -> 0
B21: Insurance Pen. | C21: 0 | E21: 3 | H21: =Projection!BY34 -> 21.794342 | I21: 0.04 | J21: =Projection!BY30 -> 20.320378 | L21: 6189 | M21: R&M Roof | N21: psf | O21: =IFERROR(SUMIF('Expense Comp Data'!$B:$B,Inputs!$L21,'Expense Comp Data'!$I:$I)/SUMIF('Expense Comp Data'!$B:$B,"SqFoot_Total",'Expense Comp Data'!$I:$I),"No Comps") -> No Comps | P21: =IF($V$29=0,0,Modeling!E36) -> 0.00945 | Q21: =IF(P21=0,O21,P21) -> 0.00945 | R21: =Projection!BW104 -> 299.96284 | T21: 0 | U21: 0.025 | V21: =($T21*(1+U21))/Projection!$F$3 -> 0
B22: Non-Storage Income | E22: 4 | H22: =Projection!BZ34 -> 22.648495 | I22: 0.04 | J22: =Projection!BZ30 -> 21.059704 | L22: 6192 | M22: Repairs & Maintenance | N22: psf | O22: =IFERROR(SUMIF('Expense Comp Data'!$B:$B,Inputs!$L22,'Expense Comp Data'!$I:$I)/SUMIF('Expense Comp Data'!$B:$B,"SqFoot_Total",'Expense Comp Data'!$I:$I),"No Comps") -> No Comps | P22: =IF($V$29=0,0,Modeling!E37) -> 0.0126 | Q22: =IF(P22=0,O22,P22) -> 0.0126 | R22: =Projection!BW105 -> 399.95046
B23: Non-Storage Total SF (Covered parking) | C23: 0 | E23: 5 | H23: =Projection!CA34 -> 23.666244 | I23: 0.04 | J23: =Projection!CA30 -> 21.82593 | L23: 6193 | M23: R&M Elevator | N23: psf | O23: =IFERROR(SUMIF('Expense Comp Data'!$B:$B,Inputs!$L23,'Expense Comp Data'!$I:$I)/SUMIF('Expense Comp Data'!$B:$B,"SqFoot_Total",'Expense Comp Data'!$I:$I),"No Comps") -> No Comps | P23: =IF(C62=FALSE,0,IF($V$29=0,0,Modeling!E38)) -> 0.0588 | Q23: =IF(P23=0,O23,P23) -> 0.0588 | R23: =Projection!BW106 -> 1866.4355 | T23: Dev Store Ref. Table | U23: ---------------------------------------------------->
B24: Non-Storage Occ SF (Covered parking) | C24: 0 | L24: 6194 | M24: R&M Doors | N24: psf | O24: =IFERROR(SUMIF('Expense Comp Data'!$B:$B,Inputs!$L24,'Expense Comp Data'!$I:$I)/SUMIF('Expense Comp Data'!$B:$B,"SqFoot_Total",'Expense Comp Data'!$I:$I),"No Comps") -> No Comps | P24: =IF($V$29=0,0,Modeling!E39) -> 0.01155 | Q24: =IF(P24=0,O24,P24) -> 0.01155 | R24: =Projection!BW107 -> 366.62125 | T24: R&M Phase-in Input
B25: Non-Covered Parking Total SF (removed from total) | C25: 0 | E25: Avg. Rate Increases % | I25: 0.12 | L25: 6195 | M25: R&M Gates | N25: psf | O25: =IFERROR(SUMIF('Expense Comp Data'!$B:$B,Inputs!$L25,'Expense Comp Data'!$I:$I)/SUMIF('Expense Comp Data'!$B:$B,"SqFoot_Total",'Expense Comp Data'!$I:$I),"No Comps") -> No Comps | P25: =IF($V$29=0,0,Modeling!E40) -> 0.013125 | Q25: =IF(P25=0,O25,P25) -> 0.013125 | R25: =Projection!BW108 -> 416.61506 | T25: Year 1 | V25: 0.3
B26: Non-Covered Parking Occ SF (removed from total) | C26: 0 | L26: 6196 | M26: R&M Golf Carts | N26: psf | O26: =IFERROR(SUMIF('Expense Comp Data'!$B:$B,Inputs!$L26,'Expense Comp Data'!$I:$I)/SUMIF('Expense Comp Data'!$B:$B,"SqFoot_Total",'Expense Comp Data'!$I:$I),"No Comps") -> No Comps | P26: =IF(C63=FALSE,0,IF($V$29=0,0,Modeling!E41)) -> 0 | Q26: =IF(P26=0,O26,P26) -> No Comps | R26: =Projection!BW109 -> 0 | T26: Year 2 | V26: 0.6
B27: Non-Storage Total Units | C27: 0 | E27: Non-Storage Income | L27: 6197 | M27: R&M Parking Lot | N27: psf | O27: =IFERROR(SUMIF('Expense Comp Data'!$B:$B,Inputs!$L27,'Expense Comp Data'!$I:$I)/SUMIF('Expense Comp Data'!$B:$B,"SqFoot_Total",'Expense Comp Data'!$I:$I),"No Comps") -> No Comps | P27: =IF($V$29=0,0,Modeling!E42) -> 0.0021 | Q27: =IF(P27=0,O27,P27) -> 0.0021 | R27: =Projection!BW110 -> 66.65841 | T27: Year 3 | V27: 1
B28: Non-Storage Occ Units | C28: 0 | E28: Modeling Methodology | I28: None | L28: 6198 | M28: R&M Cameras | N28: psf | O28: =IFERROR(SUMIF('Expense Comp Data'!$B:$B,Inputs!$L28,'Expense Comp Data'!$I:$I)/SUMIF('Expense Comp Data'!$B:$B,"SqFoot_Total",'Expense Comp Data'!$I:$I),"No Comps") -> No Comps | P28: =IF($V$29=0,0,Modeling!E43) -> 0.00525 | Q28: =IF(P28=0,O28,P28) -> 0.00525 | R28: =Projection!BW111 -> 166.64602
B29: Non-Storage GPI | C29: 0 | E29: Simple Annual Growth Rate | I29: 0.03 | L29: 6199 | M29: R&M HVAC | N29: psf | O29: =IFERROR(SUMIF('Expense Comp Data'!$B:$B,Inputs!$L29,'Expense Comp Data'!$I:$I)/SUMIF('Expense Comp Data'!$B:$B,"SqFoot_Total",'Expense Comp Data'!$I:$I),"No Comps") -> No Comps | P29: =IF($V$29=0,0,Modeling!E44) -> 0.0441 | Q29: =IF(P29=0,O29,P29) -> 0.0441 | R29: =Projection!BW112 -> 1399.8266 | T29: Input Stable R&M Total | V29: =0.21*C13 -> 22219.47
B30: Non-Storage Proj Rent | C30: 0 | E30: Leaseup: Starting Non-Storage GPI | I30: =C29 -> 0 | L30: 6201 | M30: R&M Fire Protection | N30: psf | O30: =IFERROR(SUMIF('Expense Comp Data'!$B:$B,Inputs!$L30,'Expense Comp Data'!$I:$I)/SUMIF('Expense Comp Data'!$B:$B,"SqFoot_Total",'Expense Comp Data'!$I:$I),"No Comps") -> No Comps | P30: =IF($V$29=0,0,Modeling!E45) -> 0.0231 | Q30: =IF(P30=0,O30,P30) -> 0.0231 | R30: =Projection!BW113 -> 733.24251
E31: Leaseup: # of Months to Stabilization | I31: 0 | L31: 6203 | M31: R&M Lighting/Electrical | N31: psf | O31: =IFERROR(SUMIF('Expense Comp Data'!$B:$B,Inputs!$L31,'Expense Comp Data'!$I:$I)/SUMIF('Expense Comp Data'!$B:$B,"SqFoot_Total",'Expense Comp Data'!$I:$I),"No Comps") -> No Comps | P31: =IF($V$29=0,0,Modeling!E46) -> 0.0168 | Q31: =IF(P31=0,O31,P31) -> 0.0168 | R31: =Projection!BW114 -> 533.26728 | U31: CC | V31: NON
B32: LT Growth Assumptions | E32: Leaseup: Fully-Stable Mtly Non-Storage Rental Income | I32: =I30*I10 -> 0 | L32: 6204 | M32: R&M Plumbing | N32: psf | O32: =IFERROR(SUMIF('Expense Comp Data'!$B:$B,Inputs!$L32,'Expense Comp Data'!$I:$I)/SUMIF('Expense Comp Data'!$B:$B,"SqFoot_Total",'Expense Comp Data'!$I:$I),"No Comps") -> No Comps | P32: =IF($V$29=0,0,Modeling!E47) -> 0.006825 | Q32: =IF(P32=0,O32,P32) -> 0.006825 | R32: =Projection!BW115 -> 216.63983 | T32: Rate
L33: 6206 | M33: R&M Exterior Bldg Repair | N33: psf | O33: =IFERROR(SUMIF('Expense Comp Data'!$B:$B,Inputs!$L33,'Expense Comp Data'!$I:$I)/SUMIF('Expense Comp Data'!$B:$B,"SqFoot_Total",'Expense Comp Data'!$I:$I),"No Comps") -> No Comps | P33: =IF($V$29=0,0,Modeling!E48) -> 0.0063 | Q33: =IF(P33=0,O33,P33) -> 0.0063 | R33: =Projection!BW116 -> 199.97523 | T33: CC% | U33: =$C$16 -> 1 | V33: =1-U33 -> 0
B34: LT Revenue Growth | C34: 0.04 | E34: Other Revenue Assumptions | L34: 6321 | M34: R&M Apartments | N34: psf | O34: =IFERROR(SUMIF('Expense Comp Data'!$B:$B,Inputs!$L34,'Expense Comp Data'!$I:$I)/SUMIF('Expense Comp Data'!$B:$B,"SqFoot_Total",'Expense Comp Data'!$I:$I),"No Comps") -> No Comps | P34: =IF(C64=FALSE,0,IF($V$29=0,O34,Modeling!E49)) -> 0 | Q34: =IF(P34=0,O34,P34) -> No Comps | R34: =Projection!BW117 -> 0 | T34: Blended | U34: =(U32*U33)+(V32*V33) -> 0
B35: Ann'l Expense Growth | C35: 0.025 | E35: Net Rental Income | H35: Comp | I35: Override | J35: Model | M35: Total | R35: =Projection!BW118 -> 6665.841
B36: Ann'l RE Tax Growth | C36: 0.01 | E36: 4700 | F36: Stable Discounts | G36: % of RI | H36: =IFERROR(SUMIF('Expense Comp Data'!$B:$B,Inputs!$E36,'Expense Comp Data'!$I:$I)/SUMIF('Expense Comp Data'!$B:$B,"ProjectedRent",'Expense Comp Data'!$I:$I),"No Comps") -> No Comps | I36: -0.025
B37: Management Contract | E37: WriteOffSum | F37: Write-offs | G37: % of RI | H37: =IFERROR(SUMIF('Expense Comp Data'!$B:$B,Inputs!$E37,'Expense Comp Data'!$I:$I)/SUMIF('Expense Comp Data'!$B:$B,"ProjectedRent",'Expense Comp Data'!$I:$I),"No Comps") -> No Comps | I37: -0.01 | J37: =MIN(IF(I37=0,H37,I37),-0.6%) -> -0.01 | L37: Other Operating Expense | O37: Comp Data | P37: Override | Q37: Model | R37: Year 1
B38: Sales Center | L38: 6122 | M38: Training | N38: per month | P38: 15 | Q38: =IF(P38=0,O38,P38) -> 15 | R38: =Projection!BW121 -> 180
B39: Management Fee Min | E39: Fee Income | H39: Comp | I39: Override | J39: Model | L39: 6152 | M39: Uniforms | N39: per EE | O39: =SUMIF('Expense Comp Data'!$B:$B,Inputs!$L39,'Expense Comp Data'!$I:$I)/12 -> 0 | P39: 175 | Q39: =IF(P39=0,O39,P39) -> 175 | R39: =Projection!BW122 -> 175
B40: Management Fee % | E40: 4281 | F40: Admin Fees | G40: per rental | H40: =IFERROR(SUMIF('Expense Comp Data'!$B:$B,$E40,'Expense Comp Data'!$I:$I)/SUMIF('Expense Comp Data'!$B:$B,"Rentals",'Expense Comp Data'!$I:$I),"No Comps") -> No Comps | I40: 15 | J40: =IF(I40=0,H40,I40) -> 15 | L40: 6162 | M40: Supplies | N40: per month | O40: =SUMIF('Expense Comp Data'!$B:$B,Inputs!$L40,'Expense Comp Data'!$I:$I)/12 -> 0 | P40: 0 | Q40: =IF(P40=0,O40,P40) -> 0 | R40: =Projection!BW125 -> 0
B41: 3PM Owner Insurance % | C41: 0.5 | E41: 4282 | F41: Late Fees | G41: % of RI | H41: =IFERROR(SUMIF('Expense Comp Data'!$B:$B,$E41,'Expense Comp Data'!$I:$I)/SUMIF('Expense Comp Data'!$B:$B,"ProjectedRent",'Expense Comp Data'!$I:$I),"No Comps") -> No Comps | I41: 0.001 | J41: =IF(I41=0,H41,I41) -> 0.001 | L41: 6163 | M41: Help Desk | N41: per month | P41: 43 | Q41: =IF(P41=0,O41,P41) -> 43 | R41: =Projection!BW126 -> 516 | T41: New Property Start-Up Costs
E42: 4283 | F42: Other Fee Rev. | G42: % of RI | H42: =IFERROR(SUMIF('Expense Comp Data'!$B:$B,$E42,'Expense Comp Data'!$I:$I)/SUMIF('Expense Comp Data'!$B:$B,"ProjectedRent",'Expense Comp Data'!$I:$I),"No Comps") -> No Comps | I42: 0.001 | J42: =IF(I42=0,H42,I42) -> 0.001 | L42: 6166 | M42: Truck Expense | N42: per month | O42: =SUMIF('Expense Comp Data'!$B:$B,Inputs!$L42,'Expense Comp Data'!$I:$I)/12 -> 0 | P42: 0 | Q42: =IF(P42=0,O42,P42) -> 0 | R42: =Projection!BW127 -> 0 | V42: Inputs | W42: Recommended
B43: Acquisition & Financing Assumptions | E43: 4286 | F43: Convenience Fee | G43: % of RI | H43: =IFERROR(SUMIF('Expense Comp Data'!$B:$B,$E43,'Expense Comp Data'!$I:$I)/SUMIF('Expense Comp Data'!$B:$B,"ProjectedRent",'Expense Comp Data'!$I:$I),"No Comps") -> No Comps | I43: 0.001 | J43: =IF(I43=0,H43,I43) -> 0.001 | L43: 6168 | M43: Dues & Subscriptions | N43: per month | O43: =IFERROR(SUMIF('Expense Comp Data'!$B:$B,Inputs!$L43,'Expense Comp Data'!$I:$I)/SUMIF('Expense Comp Data'!$B:$B,"SqFoot_Total",'Expense Comp Data'!$I:$I),VALUE(0)) -> 0 | P43: 12 | Q43: =IF(P43=0,O43,P43) -> 12 | R43: =Projection!BW128 -> 135 | T43: Training | W43: 0
E44: 7102 | F44: Fee Write Off | G44: % of RI | H44: =IFERROR(SUMIF('Expense Comp Data'!$B:$B,$E44,'Expense Comp Data'!$I:$I)/SUMIF('Expense Comp Data'!$B:$B,"ProjectedRent",'Expense Comp Data'!$I:$I),"No Comps") -> No Comps | I44: 0.001 | J44: =IF(I44=0,H44,I44) -> 0.001 | L44: 6170 | M44: Landscaping | N44: psf | O44: =IFERROR(SUMIF('Expense Comp Data'!$B:$B,Inputs!$L44,'Expense Comp Data'!$I:$I)/SUMIF('Expense Comp Data'!$B:$B,"SqFoot_Total",'Expense Comp Data'!$I:$I),VALUE(0)) -> 0 | P44: 0.14 | Q44: =IF(P44=0,O44,P44) -> 0.14 | R44: =Projection!BW129 -> 14812.98 | T44: Uniforms | W44: 250
B45: Purchase Price | C45: 14903660 | E45: 4285 | F45: Fees Waived | G45: % of RI | H45: =IFERROR(SUMIF('Expense Comp Data'!$B:$B,$E45,'Expense Comp Data'!$I:$I)/SUMIF('Expense Comp Data'!$B:$B,"ProjectedRent",'Expense Comp Data'!$I:$I),"No Comps") -> No Comps | I45: 0.001 | J45: =IF(I45=0,H45,I45) -> 0.001 | L45: 6174 | M45: Signs | N45: per month | O45: =SUMIF('Expense Comp Data'!$B:$B,Inputs!$L45,'Expense Comp Data'!$I:$I)/12 -> 0 | P45: 1e-07 | Q45: =IF(P45=0,O45,P45) -> 1e-07 | R45: =Projection!BW130 -> 1.2e-06 | T45: Supplies | W45: 1200
B46: Loan Amount | C46: =C45*0.65 -> 9687379 | E46: 4287 | F46: Fees Waived - Admin | G46: % of RI | H46: =IFERROR(SUMIF('Expense Comp Data'!$B:$B,$E46,'Expense Comp Data'!$I:$I)/SUMIF('Expense Comp Data'!$B:$B,"ProjectedRent",'Expense Comp Data'!$I:$I),"No Comps") -> No Comps | I46: 0.001 | J46: =IF(I46=0,H46,I46) -> 0.001 | L46: 6176 | M46: Auto Expense | N46: per month | O46: =SUMIF('Expense Comp Data'!$B:$B,Inputs!$L46,'Expense Comp Data'!$I:$I)/12 -> 0 | P46: 0 | Q46: =IF(P46=0,O46,P46) -> 0 | R46: =Projection!BW131 -> 0 | T46: Sale Items | W46: 1800
B47: Interest Rate | C47: 0.075 | E47: 4288 | F47: Fees Waived - Late Fee | G47: % of RI | H47: =IFERROR(SUMIF('Expense Comp Data'!$B:$B,$E47,'Expense Comp Data'!$I:$I)/SUMIF('Expense Comp Data'!$B:$B,"ProjectedRent",'Expense Comp Data'!$I:$I),"No Comps") -> No Comps | I47: 0.001 | J47: =IF(I47=0,H47,I47) -> 0.001 | L47: 6182 | M47: Fees/Licenses | N47: per month | O47: =SUMIF('Expense Comp Data'!$B:$B,Inputs!$L47,'Expense Comp Data'!$I:$I)/12 -> 0 | P47: 17 | Q47: =IF(P47=0,O47,P47) -> 17 | R47: =Projection!BW132 -> 204 | T47: Computer Expense | W47: 5000
B48: Loan Term (Years) | C48: 25 | E48: 4255 | F48: CC Chargebacks | G48: % of RI | H48: =IFERROR(SUMIF('Expense Comp Data'!$B:$B,$E48,'Expense Comp Data'!$I:$I)/SUMIF('Expense Comp Data'!$B:$B,"ProjectedRent",'Expense Comp Data'!$I:$I),"No Comps") -> No Comps | I48: 0.001 | J48: =IF(I48=0,H48,I48) -> 0.001 | L48: 6190 | M48: Postage/UPS | N48: per month | O48: =SUMIF('Expense Comp Data'!$B:$B,Inputs!$L48,'Expense Comp Data'!$I:$I)/12 -> 0 | P48: 0 | Q48: =IF(P48=0,O48,P48) -> 0 | R48: =Projection!BW133 -> 0 | T48: Store Marketing | W48: 10000
B49: Interest Only Period (Months) | C49: 0 | L49: 6212 | M49: Office Supplies | N49: per month | O49: =SUMIF('Expense Comp Data'!$B:$B,Inputs!$L49,'Expense Comp Data'!$I:$I)/12 -> 0 | P49: 0 | Q49: =IF(P49=0,O49,P49) -> 0 | R49: =Projection!BW134 -> 0 | T49: Travel & Lodging | W49: 0
B50: Closing Costs | C50: 50000 | E50: Ancillary Income | H50: Comp | I50: Override | J50: Model | L50: 6224 | M50: Computer Expense | N50: per month | O50: =SUMIF('Expense Comp Data'!$B:$B,Inputs!$L50,'Expense Comp Data'!$I:$I)/12 -> 0 | P50: 64 | Q50: =IF(P50=0,O50,P50) -> 64 | R50: =Projection!BW137 -> 768 | T50: Bank Charges | W50: 0
B51: CapEx Budget | C51: =SUM(I58:I72)*0 -> 0 | E51: Max Insurance Penetration | I51: 0.75 | J51: =IF(I51=0,H51,I51) -> 0.75 | L51: 6225 | M51: CMS Expense | N51: per month | O51: =SUMIF('Expense Comp Data'!$B:$B,Inputs!$L51,'Expense Comp Data'!$I:$I)/12 -> 0 | P51: 189 | Q51: =IF(P51=0,O51,P51) -> 189 | R51: =Projection!BW138 -> 2268 | T51: Signs | W51: 0
B52: Origination Fees | C52: =C46*0.02 -> 193747.58 | E52: 4940 | F52: Penske Truck Rental | G52: per month | I52: 0 | J52: =IF(I52=0,H52,I52) -> 0 | L52: 6226 | M52: Bank Charges | N52: per month | O52: =SUMIF('Expense Comp Data'!$B:$B,Inputs!$L52,'Expense Comp Data'!$I:$I)/12 -> 0 | Q52: =IF(P52=0,O52,P52) -> 0 | R52: =Projection!BW139 -> 0 | T52: Office Supplies | W52: 500
E53: 4962 | F53: Site Truck Rental | G53: per month | I53: 0 | J53: 0 | L53: 6227 | M53: Bank Printing Fees | N53: per month | O53: =SUMIF('Expense Comp Data'!$B:$B,Inputs!$L53,'Expense Comp Data'!$I:$I)/12 -> 0 | P53: 1e-09 | Q53: =IF(P53=0,O53,P53) -> 1e-09 | R53: =Projection!BW140 -> 1.2e-08 | T53: Equipment (New Dev Only) | W53: =IF(D18=0,3000,0) -> 3000
B54: LTV Ratio | C54: =C46/C45 -> 0.65 | E54: 4961 | F54: Merchandise | G54: per rental | H54: =IFERROR(SUMIF('Expense Comp Data'!$B:$B,Inputs!$E54,'Expense Comp Data'!$I:$I)/SUMIF('Expense Comp Data'!$B:$B,"Rentals",'Expense Comp Data'!$I:$I),"No Comps") -> No Comps | I54: 2.5 | J54: =IF(I54=0,H54,I54) -> 2.5 | L54: 6232 | M54: Visa/MC | N54: % of Rev | O54: =IFERROR(SUMIF('Expense Comp Data'!$B:$B,Inputs!$L54,'Expense Comp Data'!$I:$I)/SUMIF('Expense Comp Data'!$B:$B,"SqFoot_Total",'Expense Comp Data'!$I:$I),VALUE(0)) -> 0 | P54: 0.015 | Q54: =IF(P54=0,O54,P54) -> 0.015 | R54: =Projection!BW141 -> 5939.0578
B55: Equity Contribution | C55: =C45-C46+C50+C51+C52 -> 5460028.6 | L55: 6233 | M55: Amer. Exp. | N55: % of Rev | O55: =IFERROR(SUMIF('Expense Comp Data'!$B:$B,Inputs!$L55,'Expense Comp Data'!$I:$I)/SUMIF('Expense Comp Data'!$B:$B,"SqFoot_Total",'Expense Comp Data'!$I:$I),VALUE(0)) -> 0 | P55: 0.008 | Q55: =IF(P55=0,O55,P55) -> 0.008 | R55: =Projection!BW142 -> 3167.4975
B56: Year 1 Cap Rate (6.5% Market Avg) | C56: ='7 Year Projection'!S51 -> 0.0021455037 | E56: Capital Expenditures / Soft Costs | L56: 6261 | M56: Legal Advertising | N56: per month | O56: =SUMIF('Expense Comp Data'!$B:$B,Inputs!$L56,'Expense Comp Data'!$I:$I)/12 -> 0 | P56: 0 | Q56: =IF(P56=0,O56,P56) -> 0 | R56: =Projection!BW145 -> 0
B57: Year 4 Cap Rate | C57: ='7 Year Projection'!V51 -> 0.10770524 | I57: Amount | L57: 6256 | M57: Legal/Auction | N57: per month | O57: =MAX(SUMIF('Expense Comp Data'!$B:$B,Inputs!$L57,'Expense Comp Data'!$I:$I)/12,50) -> 50 | P57: 50 | Q57: =IF(P57=0,O57,P57) -> 50 | R57: =Projection!BW146 -> 600
E58: New Asphalt | L58: 6311 | M58: Free Move Vouchers | N58: $ per rental | O58: =IFERROR(SUMIF('Expense Comp Data'!$B:$B,Inputs!$L58,'Expense Comp Data'!$I:$I)/SUMIF('Expense Comp Data'!$B:$B,"Rentals",'Expense Comp Data'!$I:$I),0) -> 0 | P58: 1e-08 | Q58: =IF(P58=0,O58,P58) -> 1e-08 | R58: =Projection!BW147 -> 3.3357223e-06
B59: Property Characteristics | E59: Roof Replacement | I59: 0 | L59: 6320 | M59: Truck R&M | N59: per month | O59: =SUMIF('Expense Comp Data'!$B:$B,Inputs!$L59,'Expense Comp Data'!$I:$I)/12 -> 0 | P59: =IF(C60=FALSE,0.001,O59) -> 0.001 | Q59: =IF(P59=0,O59,P59) -> 0.001 | R59: =Projection!BW148 -> 0.012
B60: Move-In Truck? | C60: FALSE | E60: Security Upgrades | I60: 0 | M60: Total | R60: =Projection!BW149 -> 13952.567
B61: CC? | C61: =IF(C16>0%,TRUE,FALSE) -> TRUE | E61: Doors | I61: 0
B62: Multi-Story? | C62: TRUE | L62: Marketing Expense | O62: Comp Data | P62: Override | Q62: Model
B63: Golf Cart? | C63: FALSE
B64: Apartment? | C64: FALSE | E64: Estimated Development Cost | I64: =SUM(H76:H77)*0 -> 0 | L64: 6377 | M64: Marketing Expense | N64: Annual | P64: 12000 | Q64: =IF(P64=0,O64,P64) -> 12000 | R64: =Projection!BW153 -> 12000
E65: Land | I65: 0
B66: PSF and % Assumptions | L66: Non-Controllable Expenses | O66: Comp Data | P66: Override | Q66: Model | T66: 1 | U66: 2 | V66: 3 | W66: 4 | X66: 5
B67: Opex: $5.31 – $6.27/sf | C67: ='7 Year Projection'!S38/'7 Year Projection'!U4 -> 3.4277722 | L67: 6270 | M67: Real Estate Taxes | N67: psf | O67: =IFERROR(SUMIF('Expense Comp Data'!$B:$B,Inputs!$L67,'Expense Comp Data'!$I:$I)/SUMIF('Expense Comp Data'!$B:$B,"SqFoot_Total",'Expense Comp Data'!$I:$I),"No Comps") -> No Comps | P67: =T67/C13 -> 1.200991 | Q67: =IF(P67=0,O67,P67) -> 1.200991 | R67: =Projection!BW156 -> 127073.25 | T67: =U67*0.75 -> 127073.25 | U67: 169431
B68: Payroll: $0.73 – $1.28/sf | C68: =R8/C13 -> 0.6784991 | L68: 6172 | M68: Snow Removal | N68: psf | O68: =IFERROR(SUMIF('Expense Comp Data'!$B:$B,Inputs!$L68,'Expense Comp Data'!$I:$I)/SUMIF('Expense Comp Data'!$B:$B,"SqFoot_Total",'Expense Comp Data'!$I:$I),"No Comps") -> No Comps | P68: 0.11 | Q68: =IF(P68=0,O68,P68) -> 0.11 | R68: =Projection!BW161 -> 11638.77
B69: Utilities/Maintenance: $1-1.50/sf | C69: =(R18+R35+R68)/C13 -> 0.893 | M69: Insurance Property Type | P69: Non-Cat | T69: Insurance Rates
B70: Property Taxes: $2.09-2.47/sf | C70: ='7 Year Projection'!S34/'7 Year Projection'!U4 -> 1.200991 | L70: 6280 | M70: Insurance | N70: psf | O70: =IFERROR(SUMIF('Expense Comp Data'!$B:$B,Inputs!$L70,'Expense Comp Data'!$I:$I)/SUMIF('Expense Comp Data'!$B:$B,"SqFoot_Total",'Expense Comp Data'!$I:$I),"No Comps") -> No Comps | P70: 0.27 | Q70: =IF(P70=0,O70,P70) -> 0.27 | R70: =Projection!BW157 -> 28567.89 | T70: Non-Cat | V70: 0.06433558
B71: Insurance: $.27/sf | C71: ='7 Year Projection'!S35/'7 Year Projection'!U4 -> 0.27 | M71: Insurance - Flood/Pollution | N71: per month | P71: 0 | Q71: =IF(P71=0,O71,P71) -> 0 | T71: Tier 1 | V71: 0.10967763
B72: Revenue: $15/sf (Lower for New Dev) | C72: ='7 Year Projection'!S26/C13 -> 3.7420698 | E72: Reserves | M72: Insurance - Input Override | N72: annual | P72: 0 | T72: S. FLA Tier I | V72: 0.11064818
B73: Ancillary Income: 3% (higher if managed) | C73: ='7 Year Projection'!S25/'7 Year Projection'!S26 -> 0.040184265 | T73: California | V73: 0.10732799
B74: Expenses: 21.5% – 35.0% (higher for New Dev) | C74: ='7 Year Projection'!S38/'7 Year Projection'!S26 -> 0.91600968 | L74: Other Expenses | O74: Comp Data | P74: Override | Q74: Model | T74: Other Insurance psf | V74: 0.022274942 | AA74: Year
E75: Avg Cost to Develop (25-70 psf) | G75: 67.82 | H75: =I64/C13 -> 0 | L75: 7500 | M75: Commissions | N75: per month | P75: 0 | Q75: =IF(P75=0,O75,P75) -> 0 | AA75: Annual
E76: CC Cost to Develop | G76: 65 | H76: =G76*C15 -> 6877455 | L76: 7530 | M76: Professional Fees | N76: per month | P76: 0 | Q76: =IF(P76=0,O76,P76) -> 0
E77: NCC Cost to Develop | G77: 35 | H77: =G77*(C13-C15) -> 0 | L77: 7550 | M77: Land Lease | N77: per month | P77: 0 | Q77: =IF(P77=0,O77,P77) -> 0

Sheet Projection
D2: Property Info | O2: =SUM(J4:O4) -> 0
D3: Storage SF: | F3: =Inputs!C13-Inputs!C23 -> 105807 | G3: Total SF w/ Parking: | H3: =F3+(Inputs!C23-Inputs!C25) -> 105807 | BF3: =IF(AND($H44="Leaseup",BF$8<=Inputs!$I$31),(Projection!BF44-Projection!BE44)/Inputs!$I$30*(Inputs!$C$23-Inputs!$C$25),0) -> 0
D4: Units: | F4: =Inputs!C14-Inputs!C27 -> 684 | G4: Total Units w/ Parking: | H4: =F4+Inputs!C27 -> 684 | J4: =IF(AND($H44="Leaseup",J$8<=Inputs!$I$31),(Projection!J44-Projection!I44)/Inputs!$I$30*(Inputs!$C$23-Inputs!$C$25),0) -> 0 | K4: =IF(AND($H44="Leaseup",K$8<=Inputs!$I$31),(Projection!K44-Projection!J44)/Inputs!$I$30*(Inputs!$C$23-Inputs!$C$25),0) -> 0 | L4: =IF(AND($H44="Leaseup",L$8<=Inputs!$I$31),(Projection!L44-Projection!K44)/Inputs!$I$30*(Inputs!$C$23-Inputs!$C$25),0) -> 0 | M4: =IF(AND($H44="Leaseup",M$8<=Inputs!$I$31),(Projection!M44-Projection!L44)/Inputs!$I$30*(Inputs!$C$23-Inputs!$C$25),0) -> 0 | N4: =IF(AND($H44="Leaseup",N$8<=Inputs!$I$31),(Projection!N44-Projection!M44)/Inputs!$I$30*(Inputs!$C$23-Inputs!$C$25),0) -> 0 | O4: =IF(AND($H44="Leaseup",O$8<=Inputs!$I$31),(Projection!O44-Projection!N44)/Inputs!$I$30*(Inputs!$C$23-Inputs!$C$25),0) -> 0 | P4: =IF(AND($H44="Leaseup",P$8<=Inputs!$I$31),(Projection!P44-Projection!O44)/Inputs!$I$30*(Inputs!$C$23-Inputs!$C$25),0) -> 0 | Q4: =IF(AND($H44="Leaseup",Q$8<=Inputs!$I$31),(Projection!Q44-Projection!P44)/Inputs!$I$30*(Inputs!$C$23-Inputs!$C$25),0) -> 0 | ... U4: =IF(AND($H44="Leaseup",U$8<=Inputs!$I$31),(Projection!U44-Projection!T44)/Inputs!$I$30*(Inputs!$C$23-Inputs!$C$25),0) -> 0
D5: Avg Unit SF: | F5: =F3/F4 -> 154.6886
D6: Summary Year | I6: 0 | J6: =IF(Inputs!$C$9>Projection!J9,0,ROUNDDOWN((IF(J9<Inputs!$C$9,0,I8+1)-1)/12,0)+1) -> 1 | K6: =IF(Inputs!$C$9>Projection!K9,0,ROUNDDOWN((IF(K9<Inputs!$C$9,0,J8+1)-1)/12,0)+1) -> 1 | L6: =IF(Inputs!$C$9>Projection!L9,0,ROUNDDOWN((IF(L9<Inputs!$C$9,0,K8+1)-1)/12,0)+1) -> 1 | M6: =IF(Inputs!$C$9>Projection!M9,0,ROUNDDOWN((IF(M9<Inputs!$C$9,0,L8+1)-1)/12,0)+1) -> 1 | N6: =IF(Inputs!$C$9>Projection!N9,0,ROUNDDOWN((IF(N9<Inputs!$C$9,0,M8+1)-1)/12,0)+1) -> 1 | O6: =IF(Inputs!$C$9>Projection!O9,0,ROUNDDOWN((IF(O9<Inputs!$C$9,0,N8+1)-1)/12,0)+1) -> 1 | P6: =IF(Inputs!$C$9>Projection!P9,0,ROUNDDOWN((IF(P9<Inputs!$C$9,0,O8+1)-1)/12,0)+1) -> 1 | Q6: =IF(Inputs!$C$9>Projection!Q9,0,ROUNDDOWN((IF(Q9<Inputs!$C$9,0,P8+1)-1)/12,0)+1) -> 1 | ... BU6: =IF(Inputs!$C$9>Projection!BU9,0,ROUNDDOWN((IF(BU9<Inputs!$C$9,0,BT8+1)-1)/12,0)+1) -> 6
D7: Year: | J7: 1 | K7: 1 | L7: 1 | M7: 1 | N7: 1 | O7: 1 | P7: 1 | Q7: 1 | R7: 1 | S7: 1 | T7: 1 | U7: 1 | V7: 2 | W7: 2 | X7: 2 | Y7: 2 | Z7: 2 | AA7: 2 | AB7: 2 | AC7: 2 | AD7: 2 | AE7: 2 | AF7: 2 | AG7: 2 | AH7: 3 | AI7: 3 | AJ7: 3 | AK7: 3 | AL7: 3 | AM7: 3 | AN7: 3 | AO7: 3 | AP7: 3 | AQ7: 3 | AR7: 3 | AS7: 3 | AT7: 4 | AU7: 4 | AV7: 4 | AW7: 4 | AX7: 4 | AY7: 4 | AZ7: 4 | BA7: 4 | BB7: 4 | BC7: 4 | BD7: 4 | BE7: 4 | BF7: 5 | BG7: 5 | BH7: 5 | BI7: 5 | BJ7: 5 | BK7: 5 | BL7: 5 | BM7: 5 | BN7: 5 | BO7: 5 | BP7: 5 | BQ7: 5 | BR7: 6 | BS7: 6 | BT7: 6 | BU7: 6 | BW7: 1 | BX7: 2 | BY7: 3 | BZ7: 4 | CA7: 5 | CB7: 6 | CC7: 7
D8: Total Projection Month: | J8: =IF(J9<Inputs!$C$9,0,I8+1) -> 1 | K8: =IF(K9<Inputs!$C$9,0,J8+1) -> 2 | L8: =IF(L9<Inputs!$C$9,0,K8+1) -> 3 | M8: =IF(M9<Inputs!$C$9,0,L8+1) -> 4 | N8: =IF(N9<Inputs!$C$9,0,M8+1) -> 5 | O8: =IF(O9<Inputs!$C$9,0,N8+1) -> 6 | P8: =IF(P9<Inputs!$C$9,0,O8+1) -> 7 | Q8: =IF(Q9<Inputs!$C$9,0,P8+1) -> 8 | ... BU8: =IF(BU9<Inputs!$C$9,0,BT8+1) -> 64
A9: =$F$2 -> 0 | H9: Mkt Rate | I9: In-Place | J9: =Inputs!$C$8 -> 46053 | K9: =EOMONTH(J9,1) -> 46081 | L9: =EOMONTH(K9,1) -> 46112 | M9: =EOMONTH(L9,1) -> 46142 | N9: =EOMONTH(M9,1) -> 46173 | O9: =EOMONTH(N9,1) -> 46203 | P9: =EOMONTH(O9,1) -> 46234 | Q9: =EOMONTH(P9,1) -> 46265 | R9: =EOMONTH(Q9,1) -> 46295 | ... BU9: =EOMONTH(BT9,1) -> 47968 | BW9: 1 | BX9: 2 | BY9: 3 | BZ9: 4 | CA9: 5 | CB9: 6 | CC9: 7 | CD9: 8 | CE9: 9 | CF9: 10 | CG9: 11 | CH9: 12 | CI9: 13 | CJ9: 14 | CK9: 15
A10: =$F$2 -> 0
A11: =$F$2 -> 0 | D11: Revenue Forecast | BW11: Revenue Forecast
A12: =$F$2 -> 0 | D12: Occupancy | BW12: =D12 -> Occupancy
A13: =$F$2 -> 0 | F13: Automated Occupancy | I13: =(Inputs!C18-Inputs!C24)/(Inputs!C13-Inputs!C23) -> 0 | J13: =IF(J$7>=Inputs!$I$12,Inputs!$I$13+VLOOKUP(MONTH(J$9),Modeling!$B$4:$G$16,4,FALSE),RentalsVacates!G2+(VLOOKUP(J$7,Inputs!$G$4:$I$10,3,FALSE)-VLOOKUP(J$7-1,Inputs!$G$4:$I$10,3,FALSE))/12*VLOOKUP(MONTH(J$9),Modeling!$B$4:$I$16,8,FALSE)+IF(Inputs!$I$6<60%,VLOOKUP(Projection!J$8,Modeling!$B$4:$K$16,9,FALSE)+VLOOKUP(MONTH(J$9),Modeling!$B$4:$K$16,10,FALSE),0)) -> 0.021821417 | K13: =IF(K$7>=Inputs!$I$12,Inputs!$I$13+VLOOKUP(MONTH(K$9),Modeling!$B$4:$G$16,4,FALSE),RentalsVacates!H2+(VLOOKUP(K$7,Inputs!$G$4:$I$10,3,FALSE)-VLOOKUP(K$7-1,Inputs!$G$4:$I$10,3,FALSE))/12*VLOOKUP(MONTH(K$9),Modeling!$B$4:$I$16,8,FALSE)+IF(Inputs!$I$6<60%,VLOOKUP(Projection!K$8,Modeling!$B$4:$K$16,9,FALSE)+VLOOKUP(MONTH(K$9),Modeling!$B$4:$K$16,10,FALSE),0)) -> 0.043379585 | L13: =IF(L$7>=Inputs!$I$12,Inputs!$I$13+VLOOKUP(MONTH(L$9),Modeling!$B$4:$G$16,4,FALSE),RentalsVacates!I2+(VLOOKUP(L$7,Inputs!$G$4:$I$10,3,FALSE)-VLOOKUP(L$7-1,Inputs!$G$4:$I$10,3,FALSE))/12*VLOOKUP(MONTH(L$9),Modeling!$B$4:$I$16,8,FALSE)+IF(Inputs!$I$6<60%,VLOOKUP(Projection!L$8,Modeling!$B$4:$K$16,9,FALSE)+VLOOKUP(MONTH(L$9),Modeling!$B$4:$K$16,10,FALSE),0)) -> 0.073093854 | M13: =IF(M$7>=Inputs!$I$12,Inputs!$I$13+VLOOKUP(MONTH(M$9),Modeling!$B$4:$G$16,4,FALSE),RentalsVacates!J2+(VLOOKUP(M$7,Inputs!$G$4:$I$10,3,FALSE)-VLOOKUP(M$7-1,Inputs!$G$4:$I$10,3,FALSE))/12*VLOOKUP(MONTH(M$9),Modeling!$B$4:$I$16,8,FALSE)+IF(Inputs!$I$6<60%,VLOOKUP(Projection!M$8,Modeling!$B$4:$K$16,9,FALSE)+VLOOKUP(MONTH(M$9),Modeling!$B$4:$K$16,10,FALSE),0)) -> 0.10328732 | N13: =IF(N$7>=Inputs!$I$12,Inputs!$I$13+VLOOKUP(MONTH(N$9),Modeling!$B$4:$G$16,4,FALSE),RentalsVacates!K2+(VLOOKUP(N$7,Inputs!$G$4:$I$10,3,FALSE)-VLOOKUP(N$7-1,Inputs!$G$4:$I$10,3,FALSE))/12*VLOOKUP(MONTH(N$9),Modeling!$B$4:$I$16,8,FALSE)+IF(Inputs!$I$6<60%,VLOOKUP(Projection!N$8,Modeling!$B$4:$K$16,9,FALSE)+VLOOKUP(MONTH(N$9),Modeling!$B$4:$K$16,10,FALSE),0)) -> 0.14958765 | O13: =IF(O$7>=Inputs!$I$12,Inputs!$I$13+VLOOKUP(MONTH(O$9),Modeling!$B$4:$G$16,4,FALSE),RentalsVacates!L2+(VLOOKUP(O$7,Inputs!$G$4:$I$10,3,FALSE)-VLOOKUP(O$7-1,Inputs!$G$4:$I$10,3,FALSE))/12*VLOOKUP(MONTH(O$9),Modeling!$B$4:$I$16,8,FALSE)+IF(Inputs!$I$6<60%,VLOOKUP(Projection!O$8,Modeling!$B$4:$K$16,9,FALSE)+VLOOKUP(MONTH(O$9),Modeling!$B$4:$K$16,10,FALSE),0)) -> 0.1878091 | P13: =IF(P$7>=Inputs!$I$12,Inputs!$I$13+VLOOKUP(MONTH(P$9),Modeling!$B$4:$G$16,4,FALSE),RentalsVacates!M2+(VLOOKUP(P$7,Inputs!$G$4:$I$10,3,FALSE)-VLOOKUP(P$7-1,Inputs!$G$4:$I$10,3,FALSE))/12*VLOOKUP(MONTH(P$9),Modeling!$B$4:$I$16,8,FALSE)+IF(Inputs!$I$6<60%,VLOOKUP(Projection!P$8,Modeling!$B$4:$K$16,9,FALSE)+VLOOKUP(MONTH(P$9),Modeling!$B$4:$K$16,10,FALSE),0)) -> 0.22122481 | Q13: =IF(Q$7>=Inputs!$I$12,Inputs!$I$13+VLOOKUP(MONTH(Q$9),Modeling!$B$4:$G$16,4,FALSE),RentalsVacates!N2+(VLOOKUP(Q$7,Inputs!$G$4:$I$10,3,FALSE)-VLOOKUP(Q$7-1,Inputs!$G$4:$I$10,3,FALSE))/12*VLOOKUP(MONTH(Q$9),Modeling!$B$4:$I$16,8,FALSE)+IF(Inputs!$I$6<60%,VLOOKUP(Projection!Q$8,Modeling!$B$4:$K$16,9,FALSE)+VLOOKUP(MONTH(Q$9),Modeling!$B$4:$K$16,10,FALSE),0)) -> 0.2464521 | ... U13: =IF(U$7>=Inputs!$I$12,Inputs!$I$13+VLOOKUP(MONTH(U$9),Modeling!$B$4:$G$16,4,FALSE),RentalsVacates!R2+(VLOOKUP(U$7,Inputs!$G$4:$I$10,3,FALSE)-VLOOKUP(U$7-1,Inputs!$G$4:$I$10,3,FALSE))/12*VLOOKUP(MONTH(U$9),Modeling!$B$4:$I$16,8,FALSE)+IF(Inputs!$I$6<60%,VLOOKUP(Projection!U$8,Modeling!$B$4:$K$16,9,FALSE)+VLOOKUP(MONTH(U$9),Modeling!$B$4:$K$16,10,FALSE),0)) -> 0.33 | V13: =IF(V$7>=Inputs!$I$12,Inputs!$I$13+VLOOKUP(MONTH(V$9),Modeling!$B$4:$G$16,4,FALSE),RentalsVacates!S2+(VLOOKUP(V$7,Inputs!$G$4:$I$10,3,FALSE)-VLOOKUP(V$7-1,Inputs!$G$4:$I$10,3,FALSE))/12*VLOOKUP(MONTH(V$9),Modeling!$B$4:$I$16,8,FALSE)+VLOOKUP(MONTH(V$9),Modeling!$B$4:$K$16,10,FALSE)) -> 0.35314393 | W13: =IF(W$7>=Inputs!$I$12,Inputs!$I$13+VLOOKUP(MONTH(W$9),Modeling!$B$4:$G$16,4,FALSE),RentalsVacates!T2+(VLOOKUP(W$7,Inputs!$G$4:$I$10,3,FALSE)-VLOOKUP(W$7-1,Inputs!$G$4:$I$10,3,FALSE))/12*VLOOKUP(MONTH(W$9),Modeling!$B$4:$I$16,8,FALSE)+VLOOKUP(MONTH(W$9),Modeling!$B$4:$K$16,10,FALSE)) -> 0.37600865 | X13: =IF(X$7>=Inputs!$I$12,Inputs!$I$13+VLOOKUP(MONTH(X$9),Modeling!$B$4:$G$16,4,FALSE),RentalsVacates!U2+(VLOOKUP(X$7,Inputs!$G$4:$I$10,3,FALSE)-VLOOKUP(X$7-1,Inputs!$G$4:$I$10,3,FALSE))/12*VLOOKUP(MONTH(X$9),Modeling!$B$4:$I$16,8,FALSE)+VLOOKUP(MONTH(X$9),Modeling!$B$4:$K$16,10,FALSE)) -> 0.40752378 | Y13: =IF(Y$7>=Inputs!$I$12,Inputs!$I$13+VLOOKUP(MONTH(Y$9),Modeling!$B$4:$G$16,4,FALSE),RentalsVacates!V2+(VLOOKUP(Y$7,Inputs!$G$4:$I$10,3,FALSE)-VLOOKUP(Y$7-1,Inputs!$G$4:$I$10,3,FALSE))/12*VLOOKUP(MONTH(Y$9),Modeling!$B$4:$I$16,8,FALSE)+VLOOKUP(MONTH(Y$9),Modeling!$B$4:$K$16,10,FALSE)) -> 0.43954716 | Z13: =IF(Z$7>=Inputs!$I$12,Inputs!$I$13+VLOOKUP(MONTH(Z$9),Modeling!$B$4:$G$16,4,FALSE),RentalsVacates!W2+(VLOOKUP(Z$7,Inputs!$G$4:$I$10,3,FALSE)-VLOOKUP(Z$7-1,Inputs!$G$4:$I$10,3,FALSE))/12*VLOOKUP(MONTH(Z$9),Modeling!$B$4:$I$16,8,FALSE)+VLOOKUP(MONTH(Z$9),Modeling!$B$4:$K$16,10,FALSE)) -> 0.48865357 | AA13: =IF(AA$7>=Inputs!$I$12,Inputs!$I$13+VLOOKUP(MONTH(AA$9),Modeling!$B$4:$G$16,4,FALSE),RentalsVacates!X2+(VLOOKUP(AA$7,Inputs!$G$4:$I$10,3,FALSE)-VLOOKUP(AA$7-1,Inputs!$G$4:$I$10,3,FALSE))/12*VLOOKUP(MONTH(AA$9),Modeling!$B$4:$I$16,8,FALSE)+VLOOKUP(MONTH(AA$9),Modeling!$B$4:$K$16,10,FALSE)) -> 0.52919147 | AB13: =IF(AB$7>=Inputs!$I$12,Inputs!$I$13+VLOOKUP(MONTH(AB$9),Modeling!$B$4:$G$16,4,FALSE),RentalsVacates!Y2+(VLOOKUP(AB$7,Inputs!$G$4:$I$10,3,FALSE)-VLOOKUP(AB$7-1,Inputs!$G$4:$I$10,3,FALSE))/12*VLOOKUP(MONTH(AB$9),Modeling!$B$4:$I$16,8,FALSE)+VLOOKUP(MONTH(AB$9),Modeling!$B$4:$K$16,10,FALSE)) -> 0.56463238 | AC13: =IF(AC$7>=Inputs!$I$12,Inputs!$I$13+VLOOKUP(MONTH(AC$9),Modeling!$B$4:$G$16,4,FALSE),RentalsVacates!Z2+(VLOOKUP(AC$7,Inputs!$G$4:$I$10,3,FALSE)-VLOOKUP(AC$7-1,Inputs!$G$4:$I$10,3,FALSE))/12*VLOOKUP(MONTH(AC$9),Modeling!$B$4:$I$16,8,FALSE)+VLOOKUP(MONTH(AC$9),Modeling!$B$4:$K$16,10,FALSE)) -> 0.59138859 | ... BU13: =IF(BU$7>=Inputs!$I$12,Inputs!$I$13+VLOOKUP(MONTH(BU$9),Modeling!$B$4:$G$16,4,FALSE),RentalsVacates!BR2+(VLOOKUP(BU$7,Inputs!$G$4:$I$10,3,FALSE)-VLOOKUP(BU$7-1,Inputs!$G$4:$I$10,3,FALSE))/12*VLOOKUP(MONTH(BU$9),Modeling!$B$4:$I$16,8,FALSE)+VLOOKUP(MONTH(BU$9),Modeling!$B$4:$K$16,10,FALSE)) -> 0.91566667 | BW13: =AVERAGEIF($J$6:$BU$6,BW$9,$K13:$BU13) -> 0.21502763 | BX13: =AVERAGEIF($J$6:$BU$6,BX$9,$K13:$BU13) -> 0.55733657 | BY13: =AVERAGEIF($J$6:$BU$6,BY$9,$K13:$BU13) -> 0.83395329 | BZ13: =AVERAGEIF($J$6:$BU$6,BZ$9,$K13:$BU13) -> 0.92 | CA13: =AVERAGEIF($J$6:$BU$6,CA$9,$K13:$BU13) -> 0.92 | CB13: =CA13 -> 0.92 | CC13: =CB13 -> 0.92 | CD13: =CC13 -> 0.92 | CE13: =CD13 -> 0.92 | CF13: =CE13 -> 0.92 | CG13: =CF13 -> 0.92 | CH13: =CG13 -> 0.92 | CI13: =CH13 -> 0.92 | ... CK13: =CJ13 -> 0.92
A14: =$F$2 -> 0 | F14: Automated Rentals | J14: =RentalsVacates!H5 -> 14.925849 | K14: =RentalsVacates!I5 -> 14.745787 | L14: =RentalsVacates!J5 -> 21.810253 | M14: =RentalsVacates!K5 -> 23.883929 | N14: =RentalsVacates!L5 -> 36.70985 | O14: =RentalsVacates!M5 -> 34.292549 | P14: =RentalsVacates!N5 -> 33.8332 | Q14: =RentalsVacates!O5 -> 32.233434 | ... BU14: =RentalsVacates!BS5 -> 27.402977 | BW14: =SUMIF($J$6:$BU$6,BW$9,$J14:$BU14) -> 333.57223 | BX14: =SUMIF($J$6:$BU$6,BX$9,$J14:$BU14) -> 551.64635 | BY14: =SUMIF($J$6:$BU$6,BY$9,$J14:$BU14) -> 606.19768 | BZ14: =SUMIF($J$6:$BU$6,BZ$9,$J14:$BU14) -> 443.29988 | CA14: =SUMIF($J$6:$BU$6,CA$9,$J14:$BU14) -> 414.61604 | CB14: =CA14 -> 414.61604 | CC14: =CB14 -> 414.61604 | CD14: =CC14 -> 414.61604 | CE14: =CD14 -> 414.61604 | CF14: =CE14 -> 414.61604 | CG14: =CF14 -> 414.61604 | CH14: =CG14 -> 414.61604 | CI14: =CH14 -> 414.61604 | ... CK14: =CJ14 -> 414.61604
A15: =$F$2 -> 0 | F15: Automated Vacates | J15: =RentalsVacates!H6 -> 0 | K15: =RentalsVacates!I6 -> 0 | L15: =RentalsVacates!J6 -> -1.4856926 | M15: =RentalsVacates!K6 -> -3.2315988 | N15: =RentalsVacates!L6 -> -5.0404209 | O15: =RentalsVacates!M6 -> -8.1490822 | P15: =RentalsVacates!N6 -> -10.976852 | Q15: =RentalsVacates!O6 -> -14.977967 | ... BU15: =RentalsVacates!BS6 -> -23.982977 | BW15: =SUMIF($J$6:$BU$6,BW$9,$J15:$BU15) -> -107.85223 | BX15: =SUMIF($J$6:$BU$6,BX$9,$J15:$BU15) -> -312.24635 | BY15: =SUMIF($J$6:$BU$6,BY$9,$J15:$BU15) -> -442.03768 | BZ15: =SUMIF($J$6:$BU$6,BZ$9,$J15:$BU15) -> -451.73588 | CA15: =SUMIF($J$6:$BU$6,CA$9,$J15:$BU15) -> -414.61604 | CB15: =CA15 -> -414.61604 | CC15: =CB15 -> -414.61604 | CD15: =CC15 -> -414.61604 | CE15: =CD15 -> -414.61604 | CF15: =CE15 -> -414.61604 | CG15: =CF15 -> -414.61604 | CH15: =CG15 -> -414.61604 | CI15: =CH15 -> -414.61604 | ... CK15: =CJ15 -> -414.61604
A16: =$F$2 -> 0 | F16: Vacate Change | J16: 0 | K16: 0 | L16: 0 | M16: 0 | N16: 0 | O16: 0 | P16: 0 | Q16: 0 | R16: 0 | S16: 0 | T16: 0 | U16: 0 | V16: 0 | W16: 0 | X16: 0 | Y16: 0 | Z16: 0 | AA16: 0 | AB16: 0 | AC16: 0 | AD16: 0 | AE16: 0 | AF16: 0 | AG16: 0 | AH16: 0 | AI16: 0 | AJ16: 0 | AK16: 0 | AL16: 0 | AM16: 0 | AN16: 0 | AO16: 0 | AP16: 0 | AQ16: 0 | AR16: 0 | AS16: 0 | AT16: 0 | AU16: 0 | AV16: 0 | AW16: 0 | AX16: 0 | AY16: 0 | AZ16: 0 | BA16: 0 | BB16: 0 | BC16: 0 | BD16: 0 | BE16: 0 | BF16: 0 | BG16: 0 | BH16: 0 | BI16: 0 | BJ16: 0 | BK16: 0 | BL16: 0 | BM16: 0 | BN16: 0 | BO16: 0 | BP16: 0 | BQ16: 0 | BR16: 0 | BS16: 0 | BT16: 0 | BU16: 0
A18: =$F$2 -> 0 | B18: MI | F18: Move In's | J18: =J14 -> 14.925849 | K18: =K14 -> 14.745787 | L18: =L14 -> 21.810253 | M18: =M14 -> 23.883929 | N18: =N14 -> 36.70985 | O18: =O14 -> 34.292549 | P18: =P14 -> 33.8332 | Q18: =Q14 -> 32.233434 | ... BU18: =BU14 -> 27.402977 | BW18: =SUMIF($J$6:$BU$6,BW$9,$J18:$BU18) -> 333.57223 | BX18: =SUMIF($J$6:$BU$6,BX$9,$J18:$BU18) -> 551.64635 | BY18: =SUMIF($J$6:$BU$6,BY$9,$J18:$BU18) -> 606.19768 | BZ18: =SUMIF($J$6:$BU$6,BZ$9,$J18:$BU18) -> 443.29988 | CA18: =SUMIF($J$6:$BU$6,CA$9,$J18:$BU18) -> 414.61604 | CB18: =CA18 -> 414.61604 | CC18: =CB18 -> 414.61604 | CD18: =CC18 -> 414.61604 | CE18: =CD18 -> 414.61604 | CF18: =CE18 -> 414.61604 | CG18: =CF18 -> 414.61604 | CH18: =CG18 -> 414.61604 | CI18: =CH18 -> 414.61604 | ... CK18: =CJ18 -> 414.61604
A19: =$F$2 -> 0 | B19: MO | F19: Move Out's | J19: =Monthly!D26/Projection!$F$5 -> 0 | K19: =Monthly!E26/Projection!$F$5 -> 0 | L19: =Monthly!F26/Projection!$F$5 -> -1.4856926 | M19: =Monthly!G26/Projection!$F$5 -> -3.2315988 | N19: =Monthly!H26/Projection!$F$5 -> -5.0404209 | O19: =Monthly!I26/Projection!$F$5 -> -8.1490822 | P19: =Monthly!J26/Projection!$F$5 -> -10.976852 | Q19: =Monthly!K26/Projection!$F$5 -> -14.977967 | ... BU19: =Monthly!BO26/Projection!$F$5 -> -23.982977 | BW19: =SUMIF($J$6:$BU$6,BW$9,$J19:$BU19) -> -107.85223 | BX19: =SUMIF($J$6:$BU$6,BX$9,$J19:$BU19) -> -312.24635 | BY19: =SUMIF($J$6:$BU$6,BY$9,$J19:$BU19) -> -442.03768 | BZ19: =SUMIF($J$6:$BU$6,BZ$9,$J19:$BU19) -> -451.73588 | CA19: =SUMIF($J$6:$BU$6,CA$9,$J19:$BU19) -> -414.61604 | CB19: =CA19 -> -414.61604 | CC19: =CB19 -> -414.61604 | CD19: =CC19 -> -414.61604 | CE19: =CD19 -> -414.61604 | CF19: =CE19 -> -414.61604 | CG19: =CF19 -> -414.61604 | CH19: =CG19 -> -414.61604 | CI19: =CH19 -> -414.61604 | ... CK19: =CJ19 -> -414.61604
A20: =$F$2 -> 0 | B20: Net | F20: Net Rentals | J20: =J18+J19 -> 14.925849 | K20: =K18+K19 -> 14.745787 | L20: =L18+L19 -> 20.32456 | M20: =M18+M19 -> 20.65233 | N20: =N18+N19 -> 31.669429 | O20: =O18+O19 -> 26.143467 | P20: =P18+P19 -> 22.856348 | Q20: =Q18+Q19 -> 17.255467 | ... BU20: =BU18+BU19 -> 3.42 | BW20: =SUMIF($J$6:$BU$6,BW$9,$J20:$BU20) -> 225.72 | BX20: =SUMIF($J$6:$BU$6,BX$9,$J20:$BU20) -> 239.4 | BY20: =SUMIF($J$6:$BU$6,BY$9,$J20:$BU20) -> 164.16 | BZ20: =SUMIF($J$6:$BU$6,BZ$9,$J20:$BU20) -> -8.436 | CA20: =SUMIF($J$6:$BU$6,CA$9,$J20:$BU20) -> 0 | CB20: =CA20 -> 0 | CC20: =CB20 -> 0 | CD20: =CC20 -> 0 | CE20: =CD20 -> 0 | CF20: =CE20 -> 0 | CG20: =CF20 -> 0 | CH20: =CG20 -> 0 | CI20: =CH20 -> 0 | ... CK20: =CJ20 -> 0
A21: =$F$2 -> 0 | B21: RentEnd | F21: Ending Occupied Units | I21: =(Inputs!C19-Inputs!C28) -> 0 | J21: =I21+J20 -> 14.925849 | K21: =J21+K20 -> 29.671636 | L21: =K21+L20 -> 49.996196 | M21: =L21+M20 -> 70.648527 | N21: =M21+N20 -> 102.31796 | O21: =N21+O20 -> 128.46142 | P21: =O21+P20 -> 151.31777 | Q21: =P21+Q20 -> 168.57324 | ... BU21: =BT21+BU20 -> 626.316 | BW21: =SUMIF($J$6:$BU$6,BW$9,$J21:$BU21)/12 -> 128.19352 | BX21: =SUMIF($J$6:$BU$6,BX$9,$J21:$BU21)/12 -> 361.68282 | BY21: =SUMIF($J$6:$BU$6,BY$9,$J21:$BU21)/12 -> 558.35165 | BZ21: =SUMIF($J$6:$BU$6,BZ$9,$J21:$BU21)/12 -> 629.28 | CA21: =SUMIF($J$6:$BU$6,CA$9,$J21:$BU21)/12 -> 629.28
A22: =$F$2 -> 0 | J22: =J15-J19 -> 0 | K22: =K15-K19 -> 0 | L22: =L15-L19 -> 0 | M22: =M15-M19 -> 0 | N22: =N15-N19 -> 0 | O22: =O15-O19 -> 0 | P22: =P15-P19 -> 0 | Q22: =Q15-Q19 -> 0 | ... BU22: =BU15-BU19 -> 0
A23: =$F$2 -> 0 | B23: StorageSF | F23: Storage Square Feet Rented | I23: =(Inputs!C18-Inputs!C24) -> 0 | J23: =I23+J$20*$F$5 -> 2308.8587 | K23: =J23+K$20*$F$5 -> 4589.8637 | L23: =K23+L$20*$F$5 -> 7733.8414 | M23: =L23+M$20*$F$5 -> 10928.521 | N23: =M23+N$20*$F$5 -> 15827.421 | O23: =N23+O$20*$F$5 -> 19871.517 | P23: =O23+P$20*$F$5 -> 23407.134 | Q23: =P23+Q$20*$F$5 -> 26076.358 | ... BU23: =BT23+BU$20*$F$5 -> 96883.943 | BW23: =SUMIF($J$6:$BU$6,BW$9,$J23:$BU23)/12 -> 19830.076 | BX23: =SUMIF($J$6:$BU$6,BX$9,$J23:$BU23)/12 -> 55948.208 | BY23: =SUMIF($J$6:$BU$6,BY$9,$J23:$BU23)/12 -> 86370.633 | BZ23: =SUMIF($J$6:$BU$6,BZ$9,$J23:$BU23)/12 -> 97342.44 | CA23: =SUMIF($J$6:$BU$6,CA$9,$J23:$BU23)/12 -> 97342.44 | CB23: =CA23 -> 97342.44 | CC23: =CB23 -> 97342.44 | CD23: =CC23 -> 97342.44 | CE23: =CD23 -> 97342.44 | CF23: =CE23 -> 97342.44 | CG23: =CF23 -> 97342.44 | CH23: =CG23 -> 97342.44 | CI23: =CH23 -> 97342.44 | ... CK23: =CJ23 -> 97342.44
A24: =$F$2 -> 0 | B24: StorageOcc | F24: Storage SF Occupancy | I24: =(Inputs!C18-Inputs!C24)/(Inputs!C13-Inputs!C23) -> 0 | J24: =J23/$F$3 -> 0.021821417 | K24: =K23/$F$3 -> 0.043379585 | L24: =L23/$F$3 -> 0.073093854 | M24: =M23/$F$3 -> 0.10328732 | N24: =N23/$F$3 -> 0.14958765 | O24: =O23/$F$3 -> 0.1878091 | P24: =P23/$F$3 -> 0.22122481 | Q24: =Q23/$F$3 -> 0.2464521 | ... BU24: =BU23/$F$3 -> 0.91566667 | BW24: =AVERAGEIF($J$6:$BU$6,BW$9,$J24:$BU24) -> 0.18741743 | BX24: =AVERAGEIF($J$6:$BU$6,BX$9,$J24:$BU24) -> 0.52877606 | BY24: =AVERAGEIF($J$6:$BU$6,BY$9,$J24:$BU24) -> 0.81630358 | BZ24: =AVERAGEIF($J$6:$BU$6,BZ$9,$J24:$BU24) -> 0.92 | CA24: =AVERAGEIF($J$6:$BU$6,CA$9,$J24:$BU24) -> 0.92 | CB24: =CA24 -> 0.92 | CC24: =CB24 -> 0.92 | CD24: =CC24 -> 0.92 | CE24: =CD24 -> 0.92 | CF24: =CE24 -> 0.92 | CG24: =CF24 -> 0.92 | CH24: =CG24 -> 0.92 | CI24: =CH24 -> 0.92 | ... CK24: =CJ24 -> 0.92
A25: =$F$2 -> 0 | B25: ='7 Year Projection-Expanded'!A18 -> SFRent | F25: Total SF Rented | I25: =I23+Inputs!C24-Inputs!C26 -> 0 | J25: =J23+J46 -> 2308.8587 | K25: =K23+K46 -> 4589.8637 | L25: =L23+L46 -> 7733.8414 | M25: =M23+M46 -> 10928.521 | N25: =N23+N46 -> 15827.421 | O25: =O23+O46 -> 19871.517 | P25: =P23+P46 -> 23407.134 | Q25: =Q23+Q46 -> 26076.358 | ... BU25: =BU23+BU46 -> 96883.943 | BW25: =AVERAGEIF($J$6:$BU$6,BW$9,$J25:$BU25) -> 19830.076 | BX25: =AVERAGEIF($J$6:$BU$6,BX$9,$J25:$BU25) -> 55948.208 | BY25: =AVERAGEIF($J$6:$BU$6,BY$9,$J25:$BU25) -> 86370.633 | BZ25: =AVERAGEIF($J$6:$BU$6,BZ$9,$J25:$BU25) -> 97342.44 | CA25: =AVERAGEIF($J$6:$BU$6,CA$9,$J25:$BU25) -> 97342.44 | CB25: =CA25 -> 97342.44 | CC25: =CB25 -> 97342.44 | CD25: =CC25 -> 97342.44 | CE25: =CD25 -> 97342.44 | CF25: =CE25 -> 97342.44 | CG25: =CF25 -> 97342.44 | CH25: =CG25 -> 97342.44 | CI25: =CH25 -> 97342.44 | ... CK25: =CJ25 -> 97342.44
A26: =$F$2 -> 0 | B26: ='7 Year Projection-Expanded'!A19 -> SFOcc% | F26: Total SF Occupancy | I26: =I25/$H$3 -> 0 | J26: =J25/$H$3 -> 0.021821417 | K26: =K25/$H$3 -> 0.043379585 | L26: =L25/$H$3 -> 0.073093854 | M26: =M25/$H$3 -> 0.10328732 | N26: =N25/$H$3 -> 0.14958765 | O26: =O25/$H$3 -> 0.1878091 | P26: =P25/$H$3 -> 0.22122481 | ... BU26: =BU25/$H$3 -> 0.91566667 | BW26: =AVERAGEIF($J$6:$BU$6,BW$9,$J26:$BU26) -> 0.18741743 | BX26: =AVERAGEIF($J$6:$BU$6,BX$9,$J26:$BU26) -> 0.52877606 | BY26: =AVERAGEIF($J$6:$BU$6,BY$9,$J26:$BU26) -> 0.81630358 | BZ26: =AVERAGEIF($J$6:$BU$6,BZ$9,$J26:$BU26) -> 0.92 | CA26: =AVERAGEIF($J$6:$BU$6,CA$9,$J26:$BU26) -> 0.92 | CB26: =CA26 -> 0.92 | CC26: =CB26 -> 0.92 | CD26: =CC26 -> 0.92 | CE26: =CD26 -> 0.92 | CF26: =CE26 -> 0.92 | CG26: =CF26 -> 0.92 | CH26: =CG26 -> 0.92 | CI26: =CH26 -> 0.92 | ... CK26: =CJ26 -> 0.92
A27: =$F$2 -> 0
A28: =$F$2 -> 0 | D28: Rates | BW28: Rates
A29: =$F$2 -> 0 | F29: Growth | J29: =IFERROR(VLOOKUP(J$7,Inputs!$E$19:$J$23,5,FALSE)/12+(VLOOKUP(MONTH(J$9),Modeling!$B$5:$L$16,11,FALSE)),(VLOOKUP(5,Inputs!$E$19:$J$23,5,FALSE)/12+(VLOOKUP(MONTH(J$9),Modeling!$B$5:$L$16,11,FALSE)))) -> 0.0033333333 | K29: =IFERROR(VLOOKUP(K$7,Inputs!$E$19:$J$23,5,FALSE)/12+(VLOOKUP(MONTH(K$9),Modeling!$B$5:$L$16,11,FALSE)),(VLOOKUP(5,Inputs!$E$19:$J$23,5,FALSE)/12+(VLOOKUP(MONTH(K$9),Modeling!$B$5:$L$16,11,FALSE)))) -> 0.0033333333 | L29: =IFERROR(VLOOKUP(L$7,Inputs!$E$19:$J$23,5,FALSE)/12+(VLOOKUP(MONTH(L$9),Modeling!$B$5:$L$16,11,FALSE)),(VLOOKUP(5,Inputs!$E$19:$J$23,5,FALSE)/12+(VLOOKUP(MONTH(L$9),Modeling!$B$5:$L$16,11,FALSE)))) -> 0.013333333 | M29: =IFERROR(VLOOKUP(M$7,Inputs!$E$19:$J$23,5,FALSE)/12+(VLOOKUP(MONTH(M$9),Modeling!$B$5:$L$16,11,FALSE)),(VLOOKUP(5,Inputs!$E$19:$J$23,5,FALSE)/12+(VLOOKUP(MONTH(M$9),Modeling!$B$5:$L$16,11,FALSE)))) -> 0.043333333 | N29: =IFERROR(VLOOKUP(N$7,Inputs!$E$19:$J$23,5,FALSE)/12+(VLOOKUP(MONTH(N$9),Modeling!$B$5:$L$16,11,FALSE)),(VLOOKUP(5,Inputs!$E$19:$J$23,5,FALSE)/12+(VLOOKUP(MONTH(N$9),Modeling!$B$5:$L$16,11,FALSE)))) -> 0.043333333 | O29: =IFERROR(VLOOKUP(O$7,Inputs!$E$19:$J$23,5,FALSE)/12+(VLOOKUP(MONTH(O$9),Modeling!$B$5:$L$16,11,FALSE)),(VLOOKUP(5,Inputs!$E$19:$J$23,5,FALSE)/12+(VLOOKUP(MONTH(O$9),Modeling!$B$5:$L$16,11,FALSE)))) -> 0.028333333 | P29: =IFERROR(VLOOKUP(P$7,Inputs!$E$19:$J$23,5,FALSE)/12+(VLOOKUP(MONTH(P$9),Modeling!$B$5:$L$16,11,FALSE)),(VLOOKUP(5,Inputs!$E$19:$J$23,5,FALSE)/12+(VLOOKUP(MONTH(P$9),Modeling!$B$5:$L$16,11,FALSE)))) -> 0.0033333333 | Q29: =IFERROR(VLOOKUP(Q$7,Inputs!$E$19:$J$23,5,FALSE)/12+(VLOOKUP(MONTH(Q$9),Modeling!$B$5:$L$16,11,FALSE)),(VLOOKUP(5,Inputs!$E$19:$J$23,5,FALSE)/12+(VLOOKUP(MONTH(Q$9),Modeling!$B$5:$L$16,11,FALSE)))) -> -0.056666667 | ... BU29: =IFERROR(VLOOKUP(BU$7,Inputs!$E$19:$J$23,5,FALSE)/12+(VLOOKUP(MONTH(BU$9),Modeling!$B$5:$L$16,11,FALSE)),(VLOOKUP(5,Inputs!$E$19:$J$23,5,FALSE)/12+(VLOOKUP(MONTH(BU$9),Modeling!$B$5:$L$16,11,FALSE)))) -> 0.043333333 | BW29: =SUMIF($J$6:$BU$6,BW$9,$J29:$BU29) -> 0.04 | BX29: =SUMIF($J$6:$BU$6,BX$9,$J29:$BU29) -> 0.04 | BY29: =SUMIF($J$6:$BU$6,BY$9,$J29:$BU29) -> 0.04 | BZ29: =SUMIF($J$6:$BU$6,BZ$9,$J29:$BU29) -> 0.04 | CA29: =SUMIF($J$6:$BU$6,CA$9,$J29:$BU29) -> 0.04 | CB29: =CA29 -> 0.04 | CC29: =CB29 -> 0.04 | CD29: =CC29 -> 0.04 | CE29: =CD29 -> 0.04 | CF29: =CE29 -> 0.04 | CG29: =CF29 -> 0.04 | CH29: =CG29 -> 0.04 | CI29: =CH29 -> 0.04 | ... CK29: =CJ29 -> 0.04
A30: =$F$2 -> 0 | B30: AvgNER | F30: Effective Rate | I30: =Inputs!$J$16*VLOOKUP(MONTH(EOMONTH(Inputs!$C$8,-1)),Modeling!$B$5:$M$16,12,FALSE) -> 17.789291 | J30: =I30*(1+J29) -> 17.848589 | K30: =J30*(1+K29) -> 17.908084 | L30: =K30*(1+L29) -> 18.146859 | M30: =L30*(1+M29) -> 18.933222 | N30: =M30*(1+N29) -> 19.753662 | O30: =N30*(1+O29) -> 20.313349 | P30: =O30*(1+P29) -> 20.38106 | Q30: =P30*(1+Q29) -> 19.226134 | ... BU30: =BT30*(1+BU29) -> 22.637424 | BW30: =AVERAGEIF($J$6:$BU$6,BW$9,$J30:$BU30) -> 18.918678 | BX30: =AVERAGEIF($J$6:$BU$6,BX$9,$J30:$BU30) -> 19.607006 | BY30: =AVERAGEIF($J$6:$BU$6,BY$9,$J30:$BU30) -> 20.320378 | BZ30: =AVERAGEIF($J$6:$BU$6,BZ$9,$J30:$BU30) -> 21.059704 | CA30: =AVERAGEIF($J$6:$BU$6,CA$9,$J30:$BU30) -> 21.82593 | CB30: =CA30*(1+Inputs!$C$34) -> 22.698967 | CC30: =CB30*(1+Inputs!$C$34) -> 23.606926 | CD30: =CC30*(1+Inputs!$C$34) -> 24.551203 | CE30: =CD30*(1+Inputs!$C$34) -> 25.533251 | CF30: =CE30*(1+Inputs!$C$34) -> 26.554581 | CG30: =CF30*(1+Inputs!$C$34) -> 27.616765 | CH30: =CG30*(1+Inputs!$C$34) -> 28.721435 | CI30: =CH30*(1+Inputs!$C$34) -> 29.870293 | ... CK30: =CJ30*(1+Inputs!$C$34) -> 32.307709
A32: =$F$2 -> 0 | B32: AvgFullPriceAsk | F32: Full Price Rental Rate | J32: =Monthly!D14 -> 19.335971 | K32: =Monthly!E14 -> 19.400425 | L32: =Monthly!F14 -> 19.659097 | M32: =Monthly!G14 -> 20.510991 | N32: =Monthly!H14 -> 21.399801 | O32: =Monthly!I14 -> 22.006128 | P32: =Monthly!J14 -> 22.079482 | Q32: =Monthly!K14 -> 20.828311 | ... BU32: =Monthly!BO14 -> 23.558871 | BW32: =AVERAGEIF($J$6:$BU$6,BW$9,$J32:$BU32) -> 20.495235 | BX32: =AVERAGEIF($J$6:$BU$6,BX$9,$J32:$BU32) -> 21.240923 | BY32: =AVERAGEIF($J$6:$BU$6,BY$9,$J32:$BU32) -> 21.716653 | BZ32: =AVERAGEIF($J$6:$BU$6,BZ$9,$J32:$BU32) -> 21.865785 | CA32: =AVERAGEIF($J$6:$BU$6,CA$9,$J32:$BU32) -> 22.661339 | CB32: =CA32*(1+Inputs!$C$34) -> 23.567792 | CC32: =CB32*(1+Inputs!$C$34) -> 24.510504 | CD32: =CC32*(1+Inputs!$C$34) -> 25.490924 | CE32: =CD32*(1+Inputs!$C$34) -> 26.510561 | CF32: =CE32*(1+Inputs!$C$34) -> 27.570984 | CG32: =CF32*(1+Inputs!$C$34) -> 28.673823 | CH32: =CG32*(1+Inputs!$C$34) -> 29.820776 | CI32: =CH32*(1+Inputs!$C$34) -> 31.013607 | ... CK32: =CJ32*(1+Inputs!$C$34) -> 33.544317
A33: =$F$2 -> 0 | B33: AvgRentRate | F33: Rental Rate | J33: =Monthly!D23 -> 18.175813 | K33: =Monthly!E23 -> 18.236399 | L33: =Monthly!F23 -> 18.479551 | M33: =Monthly!G23 -> 19.280332 | N33: =Monthly!H23 -> 20.115813 | O33: =Monthly!I23 -> 20.685761 | P33: =Monthly!J23 -> 20.754713 | Q33: =Monthly!K23 -> 19.578613 | ... BU33: =Monthly!BO23 -> 22.145338 | BW33: =AVERAGEIF($J$6:$BU$6,BW$9,$J33:$BU33) -> 19.265521 | BX33: =AVERAGEIF($J$6:$BU$6,BX$9,$J33:$BU33) -> 19.966468 | BY33: =AVERAGEIF($J$6:$BU$6,BY$9,$J33:$BU33) -> 20.413654 | BZ33: =AVERAGEIF($J$6:$BU$6,BZ$9,$J33:$BU33) -> 20.553838 | CA33: =AVERAGEIF($J$6:$BU$6,CA$9,$J33:$BU33) -> 21.301659 | CB33: =CA33*(1+Inputs!$C$34) -> 22.153725 | CC33: =CB33*(1+Inputs!$C$34) -> 23.039874 | CD33: =CC33*(1+Inputs!$C$34) -> 23.961469 | CE33: =CD33*(1+Inputs!$C$34) -> 24.919928 | CF33: =CE33*(1+Inputs!$C$34) -> 25.916725 | CG33: =CF33*(1+Inputs!$C$34) -> 26.953394 | CH33: =CG33*(1+Inputs!$C$34) -> 28.031529 | CI33: =CH33*(1+Inputs!$C$34) -> 29.152791 | ... CK33: =CJ33*(1+Inputs!$C$34) -> 31.531658
A34: =$F$2 -> 0 | B34: IPRPSF | F34: In-Place Rate | I34: =IFERROR((Inputs!$C$20-Inputs!$C$30)/(Inputs!$C$18-Inputs!$C$24)*12,0) -> 0 | J34: =(J54/J25)*12 -> 18.175813 | K34: =(K54/K25)*12 -> 18.205922 | L34: =(L54/L25)*12 -> 18.324384 | M34: =(M54/M25)*12 -> 18.644272 | N34: =(N54/N25)*12 -> 19.16545 | O34: =(O54/O25)*12 -> 19.760769 | P34: =(P54/P25)*12 -> 20.085302 | Q34: =(Q54/Q25)*12 -> 20.121592 | ... BU34: =(BU54/BU25)*12 -> 24.160574 | BW34: =BW54/BW25 -> 19.859233 | BX34: =BX54/BX25 -> 20.810242 | BY34: =BY54/BY25 -> 21.794342 | BZ34: =BZ54/BZ25 -> 22.648495 | CA34: =CA54/CA25 -> 23.666244 | CB34: =CB54/CB25 -> 24.612894 | CC34: =CC54/CC25 -> 25.59741 | CD34: =CD54/CD25 -> 26.621306 | ... CK34: =CK54/CK25 -> 35.031823
A35: =$F$2 -> 0 | D35: Discounts
A36: =$F$2 -> 0 | B36: Disc % | F36: Discounts (% of Rental Income) | J36: =IF(Inputs!$I$36=0,Monthly!D42,Inputs!$I$36) -> -0.025 | K36: =IF(Inputs!$I$36=0,Monthly!E42,Inputs!$I$36) -> -0.025 | L36: =IF(Inputs!$I$36=0,Monthly!F42,Inputs!$I$36) -> -0.025 | M36: =IF(Inputs!$I$36=0,Monthly!G42,Inputs!$I$36) -> -0.025 | N36: =IF(Inputs!$I$36=0,Monthly!H42,Inputs!$I$36) -> -0.025 | O36: =IF(Inputs!$I$36=0,Monthly!I42,Inputs!$I$36) -> -0.025 | P36: =IF(Inputs!$I$36=0,Monthly!J42,Inputs!$I$36) -> -0.025 | Q36: =IF(Inputs!$I$36=0,Monthly!K42,Inputs!$I$36) -> -0.025 | ... BU36: =IF(Inputs!$I$36=0,Monthly!BO42,Inputs!$I$36) -> -0.025 | BW36: =BW55/BW54 -> -0.025 | BX36: =BX55/BX54 -> -0.025 | BY36: =BY55/BY54 -> -0.025 | BZ36: =BZ55/BZ54 -> -0.025 | CA36: =CA55/CA54 -> -0.025 | CB36: =CB55/CB54 -> -0.025 | CC36: =CC55/CC54 -> -0.025 | CD36: =CD55/CD54 -> -0.025 | ... CK36: =CK55/CK54 -> -0.025
A38: =$F$2 -> 0
A39: =$F$2 -> 0 | D39: Rental Income Calculation | BW39: Rental Income Calc
A40: =$F$2 -> 0 | B40: Move-In Revenue (non-Prorated) | F40: Move-In $ | J40: =Monthly!D22 -> 3497.1153 | K40: =Monthly!E22 -> 3466.4432 | L40: =Monthly!F22 -> 5195.5217 | M40: =Monthly!G22 -> 5936.0469 | N40: =Monthly!H22 -> 9519.1296 | O40: =Monthly!I22 -> 9144.2548 | P40: =Monthly!J22 -> 9051.8399 | Q40: =Monthly!K22 -> 8135.1497 | ... BU40: =Monthly!BO22 -> 7822.7081 | BW40: =SUMIF($J$6:$BU$6,BW$9,$J40:$BU40) -> 83572.084 | BX40: =SUMIF($J$6:$BU$6,BX$9,$J40:$BU40) -> 142797.8 | BY40: =SUMIF($J$6:$BU$6,BY$9,$J40:$BU40) -> 160047.55 | BZ40: =SUMIF($J$6:$BU$6,BZ$9,$J40:$BU40) -> 117889.24 | CA40: =SUMIF($J$6:$BU$6,CA$9,$J40:$BU40) -> 114226.31 | CB40: =SUMIF($J$7:$BP$7,CB$7,$J40:$BP40) -> 0 | CC40: =SUMIF($J$7:$BP$7,CC$7,$J40:$BP40) -> 0 | CD40: =SUMIF($J$7:$BP$7,CD$7,$J40:$BP40) -> 0 | CE40: =SUMIF($J$7:$BP$7,CE$7,$J40:$BP40) -> 0 | CF40: =SUMIF($J$7:$BP$7,CF$7,$J40:$BP40) -> 0 | CG40: =SUMIF($J$7:$BP$7,CG$7,$J40:$BP40) -> 0 | CH40: =SUMIF($J$7:$BP$7,CH$7,$J40:$BP40) -> 0 | CI40: =SUMIF($J$7:$BP$7,CI$7,$J40:$BP40) -> 0 | ... CK40: =SUMIF($J$7:$BP$7,CK$7,$J40:$BP40) -> 0
A41: =$F$2 -> 0 | B41: Move-Out Revenue (non-Prorated) | F41: Move-Out $ | J41: =Monthly!D27 -> 0 | K41: =Monthly!E27 -> 0 | L41: =Monthly!F27 -> -349.25698 | M41: =Monthly!G27 -> -766.34323 | N41: =Monthly!H27 -> -1220.3535 | O41: =Monthly!I27 -> -2035.2426 | P41: =Monthly!J27 -> -2825.4602 | Q41: =Monthly!K27 -> -3931.7866 | ... BU41: =Monthly!BO27 -> -7312.0152 | BW41: =SUMIF($J$6:$BU$6,BW$9,$J41:$BU41) -> -27935.482 | BX41: =SUMIF($J$6:$BU$6,BX$9,$J41:$BU41) -> -83685.289 | BY41: =SUMIF($J$6:$BU$6,BY$9,$J41:$BU41) -> -123309.61 | BZ41: =SUMIF($J$6:$BU$6,BZ$9,$J41:$BU41) -> -129408.19 | CA41: =SUMIF($J$6:$BU$6,CA$9,$J41:$BU41) -> -123401.47 | CB41: =SUMIF($J$7:$BP$7,CB$7,$J41:$BP41) -> 0 | CC41: =SUMIF($J$7:$BP$7,CC$7,$J41:$BP41) -> 0 | CD41: =SUMIF($J$7:$BP$7,CD$7,$J41:$BP41) -> 0 | CE41: =SUMIF($J$7:$BP$7,CE$7,$J41:$BP41) -> 0 | CF41: =SUMIF($J$7:$BP$7,CF$7,$J41:$BP41) -> 0 | CG41: =SUMIF($J$7:$BP$7,CG$7,$J41:$BP41) -> 0 | CH41: =SUMIF($J$7:$BP$7,CH$7,$J41:$BP41) -> 0 | CI41: =SUMIF($J$7:$BP$7,CI$7,$J41:$BP41) -> 0 | ... CK41: =SUMIF($J$7:$BP$7,CK$7,$J41:$BP41) -> 0
A42: =$F$2 -> 0 | B42: Rate Increase Revenue (non-prorated) | F42: TRIs | I42: =Inputs!$I$25 -> 0.12 | J42: =Monthly!D31 -> 0 | K42: =Monthly!E31 -> 0 | L42: =Monthly!F31 -> 0 | M42: =Monthly!G31 -> 0 | N42: =Monthly!H31 -> 0 | O42: =Monthly!I31 -> 335.72307 | P42: =Monthly!J31 -> 228.86099 | Q42: =Monthly!K31 -> 343.17671 | ... BU42: =Monthly!BO31 -> 1279.9978 | BW42: =SUMIF($J$6:$BU$6,BW$9,$J42:$BU42) -> 3023.8625 | BX42: =SUMIF($J$6:$BU$6,BX$9,$J42:$BU42) -> 9393.2651 | BY42: =SUMIF($J$6:$BU$6,BY$9,$J42:$BU42) -> 15022.895 | BZ42: =SUMIF($J$6:$BU$6,BZ$9,$J42:$BU42) -> 17371.69 | CA42: =SUMIF($J$6:$BU$6,CA$9,$J42:$BU42) -> 17385.013 | CB42: =SUMIF($J$7:$BP$7,CB$7,$J42:$BP42) -> 0 | CC42: =SUMIF($J$7:$BP$7,CC$7,$J42:$BP42) -> 0 | CD42: =SUMIF($J$7:$BP$7,CD$7,$J42:$BP42) -> 0 | CE42: =SUMIF($J$7:$BP$7,CE$7,$J42:$BP42) -> 0 | CF42: =SUMIF($J$7:$BP$7,CF$7,$J42:$BP42) -> 0 | CG42: =SUMIF($J$7:$BP$7,CG$7,$J42:$BP42) -> 0 | CH42: =SUMIF($J$7:$BP$7,CH$7,$J42:$BP42) -> 0 | CI42: =SUMIF($J$7:$BP$7,CI$7,$J42:$BP42) -> 0 | ... CK42: =SUMIF($J$7:$BP$7,CK$7,$J42:$BP42) -> 0
A43: =$F$2 -> 0 | F43: Ending Storage Rental Income | I43: =Inputs!$C$20-Inputs!$C$30 -> 0 | J43: =I43+SUM(J40:J42) -> 3497.1153 | K43: =J43+SUM(K40:K42) -> 6963.5585 | L43: =K43+SUM(L40:L42) -> 11809.823 | M43: =L43+SUM(M40:M42) -> 16979.527 | N43: =M43+SUM(N40:N42) -> 25278.303 | O43: =N43+SUM(O40:O42) -> 32723.038 | P43: =O43+SUM(P40:P42) -> 39178.279 | Q43: =P43+SUM(Q40:Q42) -> 43724.819 | ... BU43: =BT43+SUM(BU40:BU42) -> 195064.31 | BW43: =SUMIF($J$7:$BP$7,BW$9,$J43:$BP43) -> 393810.09 | BX43: =SUMIF($J$7:$BP$7,BX$9,$J43:$BP43) -> 1164295.8 | BY43: =SUMIF($J$7:$BP$7,BY$9,$J43:$BP43) -> 1882391.1 | BZ43: =SUMIF($J$7:$BP$7,BZ$9,$J43:$BP43) -> 2204659.7 | CA43: =SUMIF($J$7:$BP$7,CA$9,$J43:$BP43) -> 2110740.3 | CB43: =SUMIF($J$7:$BP$7,CB$7,$J43:$BP43) -> 0 | CC43: =SUMIF($J$7:$BP$7,CC$7,$J43:$BP43) -> 0 | CD43: =SUMIF($J$7:$BP$7,CD$7,$J43:$BP43) -> 0 | CE43: =SUMIF($J$7:$BP$7,CE$7,$J43:$BP43) -> 0 | CF43: =SUMIF($J$7:$BP$7,CF$7,$J43:$BP43) -> 0 | CG43: =SUMIF($J$7:$BP$7,CG$7,$J43:$BP43) -> 0 | CH43: =SUMIF($J$7:$BP$7,CH$7,$J43:$BP43) -> 0 | CI43: =SUMIF($J$7:$BP$7,CI$7,$J43:$BP43) -> 0 | ... CK43: =SUMIF($J$7:$BP$7,CK$7,$J43:$BP43) -> 0
A44: =$F$2 -> 0 | F44: Commercial/Parking Income | H44: =Inputs!$I$28 -> None | I44: =Inputs!$C$28 -> 0 | J44: =IF($H44="None",I44,IF(AND($H$44="Leaseup",J$8<=Inputs!$I31),I44+(Inputs!$I$32-Inputs!$C$30)/Inputs!$I$31,I44*(1+Inputs!$I$29/12))) -> 0 | K44: =IF($H44="None",J44,IF(AND($H$44="Leaseup",K$8<=Inputs!$I31),J44+(Inputs!$I$32-Inputs!$C$30)/Inputs!$I$31,J44*(1+Inputs!$I$29/12))) -> 0 | L44: =IF($H44="None",K44,IF(AND($H$44="Leaseup",L$8<=Inputs!$I31),K44+(Inputs!$I$32-Inputs!$C$30)/Inputs!$I$31,K44*(1+Inputs!$I$29/12))) -> 0 | M44: =IF($H44="None",L44,IF(AND($H$44="Leaseup",M$8<=Inputs!$I31),L44+(Inputs!$I$32-Inputs!$C$30)/Inputs!$I$31,L44*(1+Inputs!$I$29/12))) -> 0 | N44: =IF($H44="None",M44,IF(AND($H$44="Leaseup",N$8<=Inputs!$I31),M44+(Inputs!$I$32-Inputs!$C$30)/Inputs!$I$31,M44*(1+Inputs!$I$29/12))) -> 0 | O44: =IF($H44="None",N44,IF(AND($H$44="Leaseup",O$8<=Inputs!$I31),N44+(Inputs!$I$32-Inputs!$C$30)/Inputs!$I$31,N44*(1+Inputs!$I$29/12))) -> 0 | P44: =IF($H44="None",O44,IF(AND($H$44="Leaseup",P$8<=Inputs!$I31),O44+(Inputs!$I$32-Inputs!$C$30)/Inputs!$I$31,O44*(1+Inputs!$I$29/12))) -> 0 | Q44: =IF($H44="None",P44,IF(AND($H$44="Leaseup",Q$8<=Inputs!$I31),P44+(Inputs!$I$32-Inputs!$C$30)/Inputs!$I$31,P44*(1+Inputs!$I$29/12))) -> 0 | ... BU44: =IF($H44="None",BT44,IF(AND($H$44="Leaseup",BU$8<=Inputs!$I31),BT44+(Inputs!$I$32-Inputs!$C$30)/Inputs!$I$31,BT44*(1+Inputs!$I$29/12))) -> 0 | BW44: =SUMIF($J$6:$BU$6,BW$9,$J44:$BU44) -> 0 | BX44: =SUMIF($J$6:$BU$6,BX$9,$J44:$BU44) -> 0 | BY44: =SUMIF($J$6:$BU$6,BY$9,$J44:$BU44) -> 0 | BZ44: =SUMIF($J$6:$BU$6,BZ$9,$J44:$BU44) -> 0 | CA44: =SUMIF($J$6:$BU$6,CA$9,$J44:$BU44) -> 0 | CB44: =SUMIF($J$7:$BP$7,CB$7,$J44:$BP44) -> 0 | CC44: =SUMIF($J$7:$BP$7,CC$7,$J44:$BP44) -> 0 | CD44: =SUMIF($J$7:$BP$7,CD$7,$J44:$BP44) -> 0 | CE44: =SUMIF($J$7:$BP$7,CE$7,$J44:$BP44) -> 0 | CF44: =SUMIF($J$7:$BP$7,CF$7,$J44:$BP44) -> 0 | CG44: =SUMIF($J$7:$BP$7,CG$7,$J44:$BP44) -> 0 | CH44: =SUMIF($J$7:$BP$7,CH$7,$J44:$BP44) -> 0 | CI44: =SUMIF($J$7:$BP$7,CI$7,$J44:$BP44) -> 0 | ... CK44: =SUMIF($J$7:$BP$7,CK$7,$J44:$BP44) -> 0
A45: =$F$2 -> 0 | F45: Commercial/Parking GPI | I45: =IF(Inputs!$I$28="Leaseup",Inputs!$I$30,Inputs!$C$29) -> 0 | J45: =IF($H44="None",0,IF(AND($H$44="Leaseup",J$8<=Inputs!$I$31),Projection!I45,Projection!I45+Projection!J44-Projection!I44)) -> 0 | K45: =IF($H44="None",0,IF(AND($H$44="Leaseup",K$8<=Inputs!$I$31),Projection!J45,Projection!J45+Projection!K44-Projection!J44)) -> 0 | L45: =IF($H44="None",0,IF(AND($H$44="Leaseup",L$8<=Inputs!$I$31),Projection!K45,Projection!K45+Projection!L44-Projection!K44)) -> 0 | M45: =IF($H44="None",0,IF(AND($H$44="Leaseup",M$8<=Inputs!$I$31),Projection!L45,Projection!L45+Projection!M44-Projection!L44)) -> 0 | N45: =IF($H44="None",0,IF(AND($H$44="Leaseup",N$8<=Inputs!$I$31),Projection!M45,Projection!M45+Projection!N44-Projection!M44)) -> 0 | O45: =IF($H44="None",0,IF(AND($H$44="Leaseup",O$8<=Inputs!$I$31),Projection!N45,Projection!N45+Projection!O44-Projection!N44)) -> 0 | P45: =IF($H44="None",0,IF(AND($H$44="Leaseup",P$8<=Inputs!$I$31),Projection!O45,Projection!O45+Projection!P44-Projection!O44)) -> 0 | Q45: =IF($H44="None",0,IF(AND($H$44="Leaseup",Q$8<=Inputs!$I$31),Projection!P45,Projection!P45+Projection!Q44-Projection!P44)) -> 0 | ... BU45: =IF($H44="None",0,IF(AND($H$44="Leaseup",BU$8<=Inputs!$I$31),Projection!BT45,Projection!BT45+Projection!BU44-Projection!BT44)) -> 0 | BW45: =SUMIF($J$6:$BU$6,BW$9,$J45:$BU45) -> 0 | BX45: =SUMIF($J$6:$BU$6,BX$9,$J45:$BU45) -> 0 | BY45: =SUMIF($J$6:$BU$6,BY$9,$J45:$BU45) -> 0 | BZ45: =SUMIF($J$6:$BU$6,BZ$9,$J45:$BU45) -> 0 | CA45: =SUMIF($J$6:$BU$6,CA$9,$J45:$BU45) -> 0 | CB45: =SUMIF($J$7:$BP$7,CB$7,$J45:$BP45) -> 0 | CC45: =SUMIF($J$7:$BP$7,CC$7,$J45:$BP45) -> 0 | CD45: =SUMIF($J$7:$BP$7,CD$7,$J45:$BP45) -> 0 | CE45: =SUMIF($J$7:$BP$7,CE$7,$J45:$BP45) -> 0 | CF45: =SUMIF($J$7:$BP$7,CF$7,$J45:$BP45) -> 0 | CG45: =SUMIF($J$7:$BP$7,CG$7,$J45:$BP45) -> 0 | CH45: =SUMIF($J$7:$BP$7,CH$7,$J45:$BP45) -> 0 | CI45: =SUMIF($J$7:$BP$7,CI$7,$J45:$BP45) -> 0 | ... CK45: =SUMIF($J$7:$BP$7,CK$7,$J45:$BP45) -> 0
F46: Commercial/Parking Occ SF | I46: =Inputs!$C$24 -> 0 | J46: =IF(AND(Inputs!$I$28="Leaseup",J$8<Inputs!$I$31),Inputs!$C$24+(Inputs!$C$23*Inputs!$I$13-Inputs!$C$24)/Inputs!$I$31*Projection!J$8,Projection!I46) -> 0 | K46: =IF(AND(Inputs!$I$28="Leaseup",K$8<Inputs!$I$31),Inputs!$C$24+(Inputs!$C$23*Inputs!$I$13-Inputs!$C$24)/Inputs!$I$31*Projection!K$8,Projection!J46) -> 0 | L46: =IF(AND(Inputs!$I$28="Leaseup",L$8<Inputs!$I$31),Inputs!$C$24+(Inputs!$C$23*Inputs!$I$13-Inputs!$C$24)/Inputs!$I$31*Projection!L$8,Projection!K46) -> 0 | M46: =IF(AND(Inputs!$I$28="Leaseup",M$8<Inputs!$I$31),Inputs!$C$24+(Inputs!$C$23*Inputs!$I$13-Inputs!$C$24)/Inputs!$I$31*Projection!M$8,Projection!L46) -> 0 | N46: =IF(AND(Inputs!$I$28="Leaseup",N$8<Inputs!$I$31),Inputs!$C$24+(Inputs!$C$23*Inputs!$I$13-Inputs!$C$24)/Inputs!$I$31*Projection!N$8,Projection!M46) -> 0 | O46: =IF(AND(Inputs!$I$28="Leaseup",O$8<Inputs!$I$31),Inputs!$C$24+(Inputs!$C$23*Inputs!$I$13-Inputs!$C$24)/Inputs!$I$31*Projection!O$8,Projection!N46) -> 0 | P46: =IF(AND(Inputs!$I$28="Leaseup",P$8<Inputs!$I$31),Inputs!$C$24+(Inputs!$C$23*Inputs!$I$13-Inputs!$C$24)/Inputs!$I$31*Projection!P$8,Projection!O46) -> 0 | Q46: =IF(AND(Inputs!$I$28="Leaseup",Q$8<Inputs!$I$31),Inputs!$C$24+(Inputs!$C$23*Inputs!$I$13-Inputs!$C$24)/Inputs!$I$31*Projection!Q$8,Projection!P46) -> 0 | ... BU46: =IF(AND(Inputs!$I$28="Leaseup",BU$8<Inputs!$I$31),Inputs!$C$24+(Inputs!$C$23*Inputs!$I$13-Inputs!$C$24)/Inputs!$I$31*Projection!BU$8,Projection!BT46) -> 0 | BW46: =SUMIF($J$6:$BU$6,BW$9,$J46:$BU46) -> 0 | BX46: =SUMIF($J$6:$BU$6,BX$9,$J46:$BU46) -> 0 | BY46: =SUMIF($J$6:$BU$6,BY$9,$J46:$BU46) -> 0 | BZ46: =SUMIF($J$6:$BU$6,BZ$9,$J46:$BU46) -> 0 | CA46: =SUMIF($J$6:$BU$6,CA$9,$J46:$BU46) -> 0 | CB46: =SUMIF($J$7:$BP$7,CB$7,$J46:$BP46) -> 0 | CC46: =SUMIF($J$7:$BP$7,CC$7,$J46:$BP46) -> 0 | CD46: =SUMIF($J$7:$BP$7,CD$7,$J46:$BP46) -> 0 | CE46: =SUMIF($J$7:$BP$7,CE$7,$J46:$BP46) -> 0 | CF46: =SUMIF($J$7:$BP$7,CF$7,$J46:$BP46) -> 0 | CG46: =SUMIF($J$7:$BP$7,CG$7,$J46:$BP46) -> 0 | CH46: =SUMIF($J$7:$BP$7,CH$7,$J46:$BP46) -> 0 | CI46: =SUMIF($J$7:$BP$7,CI$7,$J46:$BP46) -> 0 | ... CK46: =SUMIF($J$7:$BP$7,CK$7,$J46:$BP46) -> 0
A47: =$F$2 -> 0
A48: =$F$2 -> 0 | D48: Insurance Calculation | BW48: Insurance Calc
A49: =$F$2 -> 0 | B49: Insunits | F49: Insured Units | I49: =I$50*I$21 -> 0 | J49: =MIN(J$21*MAX(Inputs!$I$51,Inputs!$C$21),I49+J$19*I50+J$18*Inputs!$J$51) -> 11.194387 | K49: =MIN(K$21*MAX(Inputs!$I$51,Inputs!$C$21),J49+K$19*J50+K$18*Inputs!$J$51) -> 22.253727 | L49: =MIN(L$21*MAX(Inputs!$I$51,Inputs!$C$21),K49+L$19*K50+L$18*Inputs!$J$51) -> 37.497147 | M49: =MIN(M$21*MAX(Inputs!$I$51,Inputs!$C$21),L49+M$19*L50+M$18*Inputs!$J$51) -> 52.986395 | N49: =MIN(N$21*MAX(Inputs!$I$51,Inputs!$C$21),M49+N$19*M50+N$18*Inputs!$J$51) -> 76.738467 | O49: =MIN(O$21*MAX(Inputs!$I$51,Inputs!$C$21),N49+O$19*N50+O$18*Inputs!$J$51) -> 96.346067 | P49: =MIN(P$21*MAX(Inputs!$I$51,Inputs!$C$21),O49+P$19*O50+P$18*Inputs!$J$51) -> 113.48833 | Q49: =MIN(Q$21*MAX(Inputs!$I$51,Inputs!$C$21),P49+Q$19*P50+Q$18*Inputs!$J$51) -> 126.42993 | ... BU49: =MIN(BU$21*MAX(Inputs!$I$51,Inputs!$C$21),BT49+BU$19*BT50+BU$18*Inputs!$J$51) -> 469.737
A50: =$F$2 -> 0 | B50: InsPen | F50: Insurance Penetration | I50: =Inputs!$C$21 -> 0 | J50: =J49/J21 -> 0.75 | K50: =K49/K21 -> 0.75 | L50: =L49/L21 -> 0.75 | M50: =M49/M21 -> 0.75 | N50: =N49/N21 -> 0.75 | O50: =O49/O21 -> 0.75 | P50: =P49/P21 -> 0.75 | Q50: =Q49/Q21 -> 0.75 | ... BU50: =BU49/BU21 -> 0.75 | BW50: =AVERAGEIF($J$6:$BU$6,BW$9,$J50:$BU50) -> 0.75 | BX50: =AVERAGEIF($J$6:$BU$6,BX$9,$J50:$BU50) -> 0.75 | BY50: =AVERAGEIF($J$6:$BU$6,BY$9,$J50:$BU50) -> 0.75 | BZ50: =AVERAGEIF($J$6:$BU$6,BZ$9,$J50:$BU50) -> 0.75 | CA50: =AVERAGEIF($J$6:$BU$6,CA$9,$J50:$BU50) -> 0.75 | CB50: =CA50 -> 0.75 | CC50: =CB50 -> 0.75 | CD50: =CC50 -> 0.75 | CE50: =CD50 -> 0.75 | CF50: =CE50 -> 0.75 | CG50: =CF50 -> 0.75 | CH50: =CG50 -> 0.75 | CI50: =CH50 -> 0.75 | ... CK50: =CJ50 -> 0.75
A51: =$F$2 -> 0
A52: =$F$2 -> 0 | D52: Revenue Budget
A53: =$F$2 -> 0 | F53: Net Rental Income
A54: =$F$2 -> 0 | B54: =F54 -> 4100 | F54: 4100 | G54: Rental Income | J54: =SUM(J43:J44) -> 3497.1153 | K54: =SUM(K43:K44) -> 6963.5585 | L54: =SUM(L43:L44) -> 11809.823 | M54: =SUM(M43:M44) -> 16979.527 | N54: =SUM(N43:N44) -> 25278.303 | O54: =SUM(O43:O44) -> 32723.038 | P54: =SUM(P43:P44) -> 39178.279 | Q54: =SUM(Q43:Q44) -> 43724.819 | ... BU54: =SUM(BU43:BU44) -> 195064.31 | BW54: =SUMIF($J$6:$BU$6,BW$9,$J54:$BU54) -> 393810.09 | BX54: =SUMIF($J$6:$BU$6,BX$9,$J54:$BU54) -> 1164295.8 | BY54: =SUMIF($J$6:$BU$6,BY$9,$J54:$BU54) -> 1882391.1 | BZ54: =SUMIF($J$6:$BU$6,BZ$9,$J54:$BU54) -> 2204659.7 | CA54: =SUMIF($J$6:$BU$6,CA$9,$J54:$BU54) -> 2303730 | CB54: =CA54*(1+Inputs!$C$34) -> 2395879.2 | CC54: =CB54*(1+Inputs!$C$34) -> 2491714.3 | CD54: =CC54*(1+Inputs!$C$34) -> 2591382.9 | CE54: =CD54*(1+Inputs!$C$34) -> 2695038.2 | CF54: =CE54*(1+Inputs!$C$34) -> 2802839.8 | CG54: =CF54*(1+Inputs!$C$34) -> 2914953.3 | CH54: =CG54*(1+Inputs!$C$34) -> 3031551.5 | CI54: =CH54*(1+Inputs!$C$34) -> 3152813.5 | ... CK54: =CJ54*(1+Inputs!$C$34) -> 3410083.1
A55: =$F$2 -> 0 | B55: =F55 -> 4700 | F55: 4700 | G55: Discounts | J55: =J$54*J$36 -> -87.427883 | K55: =K$54*K$36 -> -174.08896 | L55: =L$54*L$36 -> -295.24558 | M55: =M$54*M$36 -> -424.48817 | N55: =N$54*N$36 -> -631.95758 | O55: =O$54*O$36 -> -818.07596 | P55: =P$54*P$36 -> -979.45698 | Q55: =Q$54*Q$36 -> -1093.1205 | ... BU55: =BU$54*BU$36 -> -4876.6077 | BW55: =SUMIF($J$6:$BU$6,BW$9,$J55:$BU55) -> -9845.2523 | BX55: =SUMIF($J$6:$BU$6,BX$9,$J55:$BU55) -> -29107.394 | BY55: =SUMIF($J$6:$BU$6,BY$9,$J55:$BU55) -> -47059.778 | BZ55: =SUMIF($J$6:$BU$6,BZ$9,$J55:$BU55) -> -55116.493 | CA55: =SUMIF($J$6:$BU$6,CA$9,$J55:$BU55) -> -57593.249 | CB55: =CA55*(1+Inputs!$C$34) -> -59896.979 | CC55: =CB55*(1+Inputs!$C$34) -> -62292.858 | CD55: =CC55*(1+Inputs!$C$34) -> -64784.573 | CE55: =CD55*(1+Inputs!$C$34) -> -67375.956 | CF55: =CE55*(1+Inputs!$C$34) -> -70070.994 | CG55: =CF55*(1+Inputs!$C$34) -> -72873.834 | CH55: =CG55*(1+Inputs!$C$34) -> -75788.787 | CI55: =CH55*(1+Inputs!$C$34) -> -78820.339 | ... CK55: =CJ55*(1+Inputs!$C$34) -> -85252.078
A56: =$F$2 -> 0 | B56: =F56 -> 7101 | F56: 7101 | G56: Write-offs | H56: =Inputs!$J$37 -> -0.01 | J56: =$H56*J$54 -> -34.971153 | K56: =$H56*K$54 -> -69.635585 | L56: =$H56*L$54 -> -118.09823 | M56: =$H56*M$54 -> -169.79527 | N56: =$H56*N$54 -> -252.78303 | O56: =$H56*O$54 -> -327.23038 | P56: =$H56*P$54 -> -391.78279 | Q56: =$H56*Q$54 -> -437.24819 | ... BU56: =$H56*BU$54 -> -1950.6431 | BW56: =SUMIF($J$6:$BU$6,BW$9,$J56:$BU56) -> -3938.1009 | BX56: =SUMIF($J$6:$BU$6,BX$9,$J56:$BU56) -> -11642.958 | BY56: =SUMIF($J$6:$BU$6,BY$9,$J56:$BU56) -> -18823.911 | BZ56: =SUMIF($J$6:$BU$6,BZ$9,$J56:$BU56) -> -22046.597 | CA56: =SUMIF($J$6:$BU$6,CA$9,$J56:$BU56) -> -23037.3 | CB56: =CA56*(1+Inputs!$C$34) -> -23958.792 | CC56: =CB56*(1+Inputs!$C$34) -> -24917.143 | CD56: =CC56*(1+Inputs!$C$34) -> -25913.829 | CE56: =CD56*(1+Inputs!$C$34) -> -26950.382 | CF56: =CE56*(1+Inputs!$C$34) -> -28028.398 | CG56: =CF56*(1+Inputs!$C$34) -> -29149.533 | CH56: =CG56*(1+Inputs!$C$34) -> -30315.515 | CI56: =CH56*(1+Inputs!$C$34) -> -31528.135 | ... CK56: =CJ56*(1+Inputs!$C$34) -> -34100.831
A57: =$F$2 -> 0 | B57: NetRentInc | F57: Net Rental Income | J57: =SUM(J54:J56) -> 3374.7163 | K57: =SUM(K54:K56) -> 6719.834 | L57: =SUM(L54:L56) -> 11396.479 | M57: =SUM(M54:M56) -> 16385.244 | N57: =SUM(N54:N56) -> 24393.562 | O57: =SUM(O54:O56) -> 31577.732 | P57: =SUM(P54:P56) -> 37807.039 | Q57: =SUM(Q54:Q56) -> 42194.45 | ... BU57: =SUM(BU54:BU56) -> 188237.06 | BW57: =SUM(BW54:BW56) -> 380026.74 | BX57: =SUM(BX54:BX56) -> 1123545.4 | BY57: =SUM(BY54:BY56) -> 1816507.4 | BZ57: =SUM(BZ54:BZ56) -> 2127496.6 | CA57: =SUM(CA54:CA56) -> 2223099.4 | CB57: =SUM(CB54:CB56) -> 2312023.4 | CC57: =SUM(CC54:CC56) -> 2404504.3 | CD57: =SUM(CD54:CD56) -> 2500684.5 | ... CK57: =SUM(CK54:CK56) -> 3290730.2
A58: =$F$2 -> 0
A59: =$F$2 -> 0 | F59: Other Income
A60: =$F$2 -> 0 | B60: 4281 | F60: 4281 | G60: Admin Fees | H60: =VLOOKUP($F60,Inputs!$E:$J,6,FALSE) -> 15 | J60: =$H60*J$18 -> 223.88774 | K60: =$H60*K$18 -> 221.1868 | L60: =$H60*L$18 -> 327.15379 | M60: =$H60*M$18 -> 358.25894 | N60: =$H60*N$18 -> 550.64775 | O60: =$H60*O$18 -> 514.38824 | P60: =$H60*P$18 -> 507.498 | Q60: =$H60*Q$18 -> 483.50151 | ... BU60: =$H60*BU$18 -> 411.04466 | BW60: =SUMIF($J$6:$BU$6,BW$9,$J60:$BU60) -> 5003.5835 | BX60: =SUMIF($J$6:$BU$6,BX$9,$J60:$BU60) -> 8274.6952 | BY60: =SUMIF($J$6:$BU$6,BY$9,$J60:$BU60) -> 9092.9652 | BZ60: =SUMIF($J$6:$BU$6,BZ$9,$J60:$BU60) -> 6649.4982 | CA60: =SUMIF($J$6:$BU$6,CA$9,$J60:$BU60) -> 6219.2406 | CB60: =CA60*(1+Inputs!$C$34) -> 6468.0102 | CC60: =CB60*(1+Inputs!$C$34) -> 6726.7306 | CD60: =CC60*(1+Inputs!$C$34) -> 6995.7999 | CE60: =CD60*(1+Inputs!$C$34) -> 7275.6319 | CF60: =CE60*(1+Inputs!$C$34) -> 7566.6571 | CG60: =CF60*(1+Inputs!$C$34) -> 7869.3234 | CH60: =CG60*(1+Inputs!$C$34) -> 8184.0963 | CI60: =CH60*(1+Inputs!$C$34) -> 8511.4602 | ... CK60: =CJ60*(1+Inputs!$C$34) -> 9205.9954
A61: =$F$2 -> 0 | B61: =F61 -> 4282 | F61: 4282 | G61: Late Fees | H61: =VLOOKUP($F61,Inputs!$E:$J,6,FALSE) -> 0.001 | J61: =$H61*J$54 -> 3.4971153 | K61: =$H61*K$54 -> 6.9635585 | L61: =$H61*L$54 -> 11.809823 | M61: =$H61*M$54 -> 16.979527 | N61: =$H61*N$54 -> 25.278303 | O61: =$H61*O$54 -> 32.723038 | P61: =$H61*P$54 -> 39.178279 | Q61: =$H61*Q$54 -> 43.724819 | ... BU61: =$H61*BU$54 -> 195.06431 | BW61: =SUMIF($J$6:$BU$6,BW$9,$J61:$BU61) -> 393.81009 | BX61: =SUMIF($J$6:$BU$6,BX$9,$J61:$BU61) -> 1164.2958 | BY61: =SUMIF($J$6:$BU$6,BY$9,$J61:$BU61) -> 1882.3911 | BZ61: =SUMIF($J$6:$BU$6,BZ$9,$J61:$BU61) -> 2204.6597 | CA61: =SUMIF($J$6:$BU$6,CA$9,$J61:$BU61) -> 2303.73 | CB61: =CA61*(1+Inputs!$C$34) -> 2395.8792 | CC61: =CB61*(1+Inputs!$C$34) -> 2491.7143 | CD61: =CC61*(1+Inputs!$C$34) -> 2591.3829 | CE61: =CD61*(1+Inputs!$C$34) -> 2695.0382 | CF61: =CE61*(1+Inputs!$C$34) -> 2802.8398 | CG61: =CF61*(1+Inputs!$C$34) -> 2914.9533 | CH61: =CG61*(1+Inputs!$C$34) -> 3031.5515 | CI61: =CH61*(1+Inputs!$C$34) -> 3152.8135 | ... CK61: =CJ61*(1+Inputs!$C$34) -> 3410.0831
A62: =$F$2 -> 0 | B62: =F62 -> 4283 | F62: 4283 | G62: Other Fee Rev. | H62: =VLOOKUP($F62,Inputs!$E:$J,6,FALSE) -> 0.001 | J62: =$H62*J$54 -> 3.4971153 | K62: =$H62*K$54 -> 6.9635585 | L62: =$H62*L$54 -> 11.809823 | M62: =$H62*M$54 -> 16.979527 | N62: =$H62*N$54 -> 25.278303 | O62: =$H62*O$54 -> 32.723038 | P62: =$H62*P$54 -> 39.178279 | Q62: =$H62*Q$54 -> 43.724819 | ... BU62: =$H62*BU$54 -> 195.06431 | BW62: =SUMIF($J$6:$BU$6,BW$9,$J62:$BU62) -> 393.81009 | BX62: =SUMIF($J$6:$BU$6,BX$9,$J62:$BU62) -> 1164.2958 | BY62: =SUMIF($J$6:$BU$6,BY$9,$J62:$BU62) -> 1882.3911 | BZ62: =SUMIF($J$6:$BU$6,BZ$9,$J62:$BU62) -> 2204.6597 | CA62: =SUMIF($J$6:$BU$6,CA$9,$J62:$BU62) -> 2303.73 | CB62: =CA62*(1+Inputs!$C$34) -> 2395.8792 | CC62: =CB62*(1+Inputs!$C$34) -> 2491.7143 | CD62: =CC62*(1+Inputs!$C$34) -> 2591.3829 | CE62: =CD62*(1+Inputs!$C$34) -> 2695.0382 | CF62: =CE62*(1+Inputs!$C$34) -> 2802.8398 | CG62: =CF62*(1+Inputs!$C$34) -> 2914.9533 | CH62: =CG62*(1+Inputs!$C$34) -> 3031.5515 | CI62: =CH62*(1+Inputs!$C$34) -> 3152.8135 | ... CK62: =CJ62*(1+Inputs!$C$34) -> 3410.0831
A63: =$F$2 -> 0 | B63: =F63 -> 7102 | F63: 7102 | G63: Fee Write Off | H63: =VLOOKUP($F63,Inputs!$E:$J,6,FALSE) -> 0.001 | J63: =$H63*J$54 -> 3.4971153 | K63: =$H63*K$54 -> 6.9635585 | L63: =$H63*L$54 -> 11.809823 | M63: =$H63*M$54 -> 16.979527 | N63: =$H63*N$54 -> 25.278303 | O63: =$H63*O$54 -> 32.723038 | P63: =$H63*P$54 -> 39.178279 | Q63: =$H63*Q$54 -> 43.724819 | ... BU63: =$H63*BU$54 -> 195.06431 | BW63: =SUMIF($J$6:$BU$6,BW$9,$J63:$BU63) -> 393.81009 | BX63: =SUMIF($J$6:$BU$6,BX$9,$J63:$BU63) -> 1164.2958 | BY63: =SUMIF($J$6:$BU$6,BY$9,$J63:$BU63) -> 1882.3911 | BZ63: =SUMIF($J$6:$BU$6,BZ$9,$J63:$BU63) -> 2204.6597 | CA63: =SUMIF($J$6:$BU$6,CA$9,$J63:$BU63) -> 2303.73 | CB63: =CA63*(1+Inputs!$C$34) -> 2395.8792 | CC63: =CB63*(1+Inputs!$C$34) -> 2491.7143 | CD63: =CC63*(1+Inputs!$C$34) -> 2591.3829 | CE63: =CD63*(1+Inputs!$C$34) -> 2695.0382 | CF63: =CE63*(1+Inputs!$C$34) -> 2802.8398 | CG63: =CF63*(1+Inputs!$C$34) -> 2914.9533 | CH63: =CG63*(1+Inputs!$C$34) -> 3031.5515 | CI63: =CH63*(1+Inputs!$C$34) -> 3152.8135 | ... CK63: =CJ63*(1+Inputs!$C$34) -> 3410.0831
A64: =$F$2 -> 0 | B64: =F64 -> 4285 | F64: 4285 | G64: Fees Waived | H64: =VLOOKUP($F64,Inputs!$E:$J,6,FALSE) -> 0.001 | J64: =$H64*J$54 -> 3.4971153 | K64: =$H64*K$54 -> 6.9635585 | L64: =$H64*L$54 -> 11.809823 | M64: =$H64*M$54 -> 16.979527 | N64: =$H64*N$54 -> 25.278303 | O64: =$H64*O$54 -> 32.723038 | P64: =$H64*P$54 -> 39.178279 | Q64: =$H64*Q$54 -> 43.724819 | ... BU64: =$H64*BU$54 -> 195.06431 | BW64: =SUMIF($J$6:$BU$6,BW$9,$J64:$BU64) -> 393.81009 | BX64: =SUMIF($J$6:$BU$6,BX$9,$J64:$BU64) -> 1164.2958 | BY64: =SUMIF($J$6:$BU$6,BY$9,$J64:$BU64) -> 1882.3911 | BZ64: =SUMIF($J$6:$BU$6,BZ$9,$J64:$BU64) -> 2204.6597 | CA64: =SUMIF($J$6:$BU$6,CA$9,$J64:$BU64) -> 2303.73 | CB64: =CA64*(1+Inputs!$C$34) -> 2395.8792 | CC64: =CB64*(1+Inputs!$C$34) -> 2491.7143 | CD64: =CC64*(1+Inputs!$C$34) -> 2591.3829 | CE64: =CD64*(1+Inputs!$C$34) -> 2695.0382 | CF64: =CE64*(1+Inputs!$C$34) -> 2802.8398 | CG64: =CF64*(1+Inputs!$C$34) -> 2914.9533 | CH64: =CG64*(1+Inputs!$C$34) -> 3031.5515 | CI64: =CH64*(1+Inputs!$C$34) -> 3152.8135 | ... CK64: =CJ64*(1+Inputs!$C$34) -> 3410.0831
A65: =$F$2 -> 0 | B65: =F65 -> 4286 | F65: 4286 | G65: Convenience Fee | H65: =VLOOKUP($F65,Inputs!$E:$J,6,FALSE) -> 0.001 | J65: =$H65*J$54 -> 3.4971153 | K65: =$H65*K$54 -> 6.9635585 | L65: =$H65*L$54 -> 11.809823 | M65: =$H65*M$54 -> 16.979527 | N65: =$H65*N$54 -> 25.278303 | O65: =$H65*O$54 -> 32.723038 | P65: =$H65*P$54 -> 39.178279 | Q65: =$H65*Q$54 -> 43.724819 | ... BU65: =$H65*BU$54 -> 195.06431 | BW65: =SUMIF($J$6:$BU$6,BW$9,$J65:$BU65) -> 393.81009 | BX65: =SUMIF($J$6:$BU$6,BX$9,$J65:$BU65) -> 1164.2958 | BY65: =SUMIF($J$6:$BU$6,BY$9,$J65:$BU65) -> 1882.3911 | BZ65: =SUMIF($J$6:$BU$6,BZ$9,$J65:$BU65) -> 2204.6597 | CA65: =SUMIF($J$6:$BU$6,CA$9,$J65:$BU65) -> 2303.73 | CB65: =CA65*(1+Inputs!$C$34) -> 2395.8792 | CC65: =CB65*(1+Inputs!$C$34) -> 2491.7143 | CD65: =CC65*(1+Inputs!$C$34) -> 2591.3829 | CE65: =CD65*(1+Inputs!$C$34) -> 2695.0382 | CF65: =CE65*(1+Inputs!$C$34) -> 2802.8398 | CG65: =CF65*(1+Inputs!$C$34) -> 2914.9533 | CH65: =CG65*(1+Inputs!$C$34) -> 3031.5515 | CI65: =CH65*(1+Inputs!$C$34) -> 3152.8135 | ... CK65: =CJ65*(1+Inputs!$C$34) -> 3410.0831
A66: =$F$2 -> 0 | B66: =F66 -> 4287 | F66: 4287 | G66: Fees Waived - Admin Fee | H66: =VLOOKUP($F66,Inputs!$E:$J,6,FALSE) -> 0.001 | J66: =$H66*J$54 -> 3.4971153 | K66: =$H66*K$54 -> 6.9635585 | L66: =$H66*L$54 -> 11.809823 | M66: =$H66*M$54 -> 16.979527 | N66: =$H66*N$54 -> 25.278303 | O66: =$H66*O$54 -> 32.723038 | P66: =$H66*P$54 -> 39.178279 | Q66: =$H66*Q$54 -> 43.724819 | ... BU66: =$H66*BU$54 -> 195.06431 | BW66: =SUMIF($J$6:$BU$6,BW$9,$J66:$BU66) -> 393.81009 | BX66: =SUMIF($J$6:$BU$6,BX$9,$J66:$BU66) -> 1164.2958 | BY66: =SUMIF($J$6:$BU$6,BY$9,$J66:$BU66) -> 1882.3911 | BZ66: =SUMIF($J$6:$BU$6,BZ$9,$J66:$BU66) -> 2204.6597 | CA66: =SUMIF($J$6:$BU$6,CA$9,$J66:$BU66) -> 2303.73 | CB66: =CA66*(1+Inputs!$C$34) -> 2395.8792 | CC66: =CB66*(1+Inputs!$C$34) -> 2491.7143 | CD66: =CC66*(1+Inputs!$C$34) -> 2591.3829 | CE66: =CD66*(1+Inputs!$C$34) -> 2695.0382 | CF66: =CE66*(1+Inputs!$C$34) -> 2802.8398 | CG66: =CF66*(1+Inputs!$C$34) -> 2914.9533 | CH66: =CG66*(1+Inputs!$C$34) -> 3031.5515 | CI66: =CH66*(1+Inputs!$C$34) -> 3152.8135 | ... CK66: =CJ66*(1+Inputs!$C$34) -> 3410.0831
A67: =$F$2 -> 0 | B67: =F67 -> 4288 | F67: 4288 | G67: Fees Waived - Late Fee | H67: =VLOOKUP($F67,Inputs!$E:$J,6,FALSE) -> 0.001 | J67: =$H67*J$54 -> 3.4971153 | K67: =$H67*K$54 -> 6.9635585 | L67: =$H67*L$54 -> 11.809823 | M67: =$H67*M$54 -> 16.979527 | N67: =$H67*N$54 -> 25.278303 | O67: =$H67*O$54 -> 32.723038 | P67: =$H67*P$54 -> 39.178279 | Q67: =$H67*Q$54 -> 43.724819 | ... BU67: =$H67*BU$54 -> 195.06431 | BW67: =SUMIF($J$6:$BU$6,BW$9,$J67:$BU67) -> 393.81009 | BX67: =SUMIF($J$6:$BU$6,BX$9,$J67:$BU67) -> 1164.2958 | BY67: =SUMIF($J$6:$BU$6,BY$9,$J67:$BU67) -> 1882.3911 | BZ67: =SUMIF($J$6:$BU$6,BZ$9,$J67:$BU67) -> 2204.6597 | CA67: =SUMIF($J$6:$BU$6,CA$9,$J67:$BU67) -> 2303.73 | CB67: =CA67*(1+Inputs!$C$34) -> 2395.8792 | CC67: =CB67*(1+Inputs!$C$34) -> 2491.7143 | CD67: =CC67*(1+Inputs!$C$34) -> 2591.3829 | CE67: =CD67*(1+Inputs!$C$34) -> 2695.0382 | CF67: =CE67*(1+Inputs!$C$34) -> 2802.8398 | CG67: =CF67*(1+Inputs!$C$34) -> 2914.9533 | CH67: =CG67*(1+Inputs!$C$34) -> 3031.5515 | CI67: =CH67*(1+Inputs!$C$34) -> 3152.8135 | ... CK67: =CJ67*(1+Inputs!$C$34) -> 3410.0831
A68: =$F$2 -> 0 | B68: =F68 -> 4255 | F68: 4255 | G68: Credit Card Chargebacks | H68: =VLOOKUP($F68,Inputs!$E:$J,6,FALSE) -> 0.001 | J68: =$H68*J$54 -> 3.4971153 | K68: =$H68*K$54 -> 6.9635585 | L68: =$H68*L$54 -> 11.809823 | M68: =$H68*M$54 -> 16.979527 | N68: =$H68*N$54 -> 25.278303 | O68: =$H68*O$54 -> 32.723038 | P68: =$H68*P$54 -> 39.178279 | Q68: =$H68*Q$54 -> 43.724819 | ... BU68: =$H68*BU$54 -> 195.06431 | BW68: =SUMIF($J$6:$BU$6,BW$9,$J68:$BU68) -> 393.81009 | BX68: =SUMIF($J$6:$BU$6,BX$9,$J68:$BU68) -> 1164.2958 | BY68: =SUMIF($J$6:$BU$6,BY$9,$J68:$BU68) -> 1882.3911 | BZ68: =SUMIF($J$6:$BU$6,BZ$9,$J68:$BU68) -> 2204.6597 | CA68: =SUMIF($J$6:$BU$6,CA$9,$J68:$BU68) -> 2303.73 | CB68: =CA68*(1+Inputs!$C$34) -> 2395.8792 | CC68: =CB68*(1+Inputs!$C$34) -> 2491.7143 | CD68: =CC68*(1+Inputs!$C$34) -> 2591.3829 | CE68: =CD68*(1+Inputs!$C$34) -> 2695.0382 | CF68: =CE68*(1+Inputs!$C$34) -> 2802.8398 | CG68: =CF68*(1+Inputs!$C$34) -> 2914.9533 | CH68: =CG68*(1+Inputs!$C$34) -> 3031.5515 | CI68: =CH68*(1+Inputs!$C$34) -> 3152.8135 | ... CK68: =CJ68*(1+Inputs!$C$34) -> 3410.0831
A69: =$F$2 -> 0 | B69: OtherOpInc | F69: Total Other Income | J69: =SUM(J60:J68) -> 251.86466 | K69: =SUM(K60:K68) -> 276.89527 | L69: =SUM(L60:L68) -> 421.63238 | M69: =SUM(M60:M68) -> 494.09515 | N69: =SUM(N60:N68) -> 752.87417 | O69: =SUM(O60:O68) -> 776.17255 | P69: =SUM(P60:P68) -> 820.92423 | Q69: =SUM(Q60:Q68) -> 833.30006 | ... BU69: =SUM(BU60:BU68) -> 1971.5591 | BW69: =SUM(BW60:BW68) -> 8154.0642 | BX69: =SUM(BX60:BX68) -> 17589.061 | BY69: =SUM(BY60:BY68) -> 24152.094 | BZ69: =SUM(BZ60:BZ68) -> 24286.776 | CA69: =SUM(CA60:CA68) -> 24649.08 | CB69: =SUM(CB60:CB68) -> 25635.044 | CC69: =SUM(CC60:CC68) -> 26660.445 | CD69: =SUM(CD60:CD68) -> 27726.863 | ... CK69: =SUM(CK60:CK68) -> 36486.66
A70: =$F$2 -> 0
A71: =$F$2 -> 0 | F71: Ancillary Income
A72: =$F$2 -> 0 | B72: =F72 -> 4920 | F72: 4920 | G72: Insurance Commission (Managed) | H72: =12*Inputs!$C$41 -> 6 | J72: =$H72*J$49 -> 67.166322 | K72: =$H72*K$49 -> 133.52236 | L72: =$H72*L$49 -> 224.98288 | M72: =$H72*M$49 -> 317.91837 | N72: =$H72*N$49 -> 460.4308 | O72: =$H72*O$49 -> 578.0764 | P72: =$H72*P$49 -> 680.92997 | Q72: =$H72*Q$49 -> 758.57957 | ... BU72: =$H72*BU$49 -> 2818.422 | BW72: =SUMIF($J$6:$BU$6,BW$9,$J72:$BU72) -> 6922.45 | BX72: =SUMIF($J$6:$BU$6,BX$9,$J72:$BU72) -> 19530.872 | BY72: =SUMIF($J$6:$BU$6,BY$9,$J72:$BU72) -> 30150.989 | BZ72: =SUMIF($J$6:$BU$6,BZ$9,$J72:$BU72) -> 33981.12 | CA72: =SUMIF($J$6:$BU$6,CA$9,$J72:$BU72) -> 33981.12 | CB72: =CA72*(1+Inputs!$C$34) -> 35340.365 | CC72: =CB72*(1+Inputs!$C$34) -> 36753.979 | CD72: =CC72*(1+Inputs!$C$34) -> 38224.139 | CE72: =CD72*(1+Inputs!$C$34) -> 39753.104 | CF72: =CE72*(1+Inputs!$C$34) -> 41343.228 | CG72: =CF72*(1+Inputs!$C$34) -> 42996.957 | CH72: =CG72*(1+Inputs!$C$34) -> 44716.836 | CI72: =CH72*(1+Inputs!$C$34) -> 46505.509 | ... CK72: =CJ72*(1+Inputs!$C$34) -> 50300.359
A73: =$F$2 -> 0 | B73: =F73 -> 4940 | F73: 4940 | G73: Penske Truck Rental | H73: =VLOOKUP($F73,Inputs!$E:$J,6,FALSE) -> 0 | J73: =$H73*(1+Inputs!$C$35)^(J$7-1) -> 0 | K73: =$H73*(1+Inputs!$C$35)^(K$7-1) -> 0 | L73: =$H73*(1+Inputs!$C$35)^(L$7-1) -> 0 | M73: =$H73*(1+Inputs!$C$35)^(M$7-1) -> 0 | N73: =$H73*(1+Inputs!$C$35)^(N$7-1) -> 0 | O73: =$H73*(1+Inputs!$C$35)^(O$7-1) -> 0 | P73: =$H73*(1+Inputs!$C$35)^(P$7-1) -> 0 | Q73: =$H73*(1+Inputs!$C$35)^(Q$7-1) -> 0 | ... BU73: =$H73*(1+Inputs!$C$35)^(BU$7-1) -> 0 | BW73: =SUMIF($J$6:$BU$6,BW$9,$J73:$BU73) -> 0 | BX73: =SUMIF($J$6:$BU$6,BX$9,$J73:$BU73) -> 0 | BY73: =SUMIF($J$6:$BU$6,BY$9,$J73:$BU73) -> 0 | BZ73: =SUMIF($J$6:$BU$6,BZ$9,$J73:$BU73) -> 0 | CA73: =SUMIF($J$6:$BU$6,CA$9,$J73:$BU73) -> 0 | CB73: =CA73*(1+Inputs!$C$34) -> 0 | CC73: =CB73*(1+Inputs!$C$34) -> 0 | CD73: =CC73*(1+Inputs!$C$34) -> 0 | CE73: =CD73*(1+Inputs!$C$34) -> 0 | CF73: =CE73*(1+Inputs!$C$34) -> 0 | CG73: =CF73*(1+Inputs!$C$34) -> 0 | CH73: =CG73*(1+Inputs!$C$34) -> 0 | CI73: =CH73*(1+Inputs!$C$34) -> 0 | ... CK73: =CJ73*(1+Inputs!$C$34) -> 0
A74: =$F$2 -> 0 | B74: =F74 -> 4961 | F74: 4961 | G74: Merchandise ($/rental) | H74: =VLOOKUP($F74,Inputs!$E:$J,6,FALSE) -> 2.5 | J74: =$H74*J$18 -> 37.314623 | K74: =$H74*K$18 -> 36.864467 | L74: =$H74*L$18 -> 54.525632 | M74: =$H74*M$18 -> 59.709823 | N74: =$H74*N$18 -> 91.774624 | O74: =$H74*O$18 -> 85.731374 | P74: =$H74*P$18 -> 84.583 | Q74: =$H74*Q$18 -> 80.583585 | ... BU74: =$H74*BU$18 -> 68.507443 | BW74: =SUMIF($J$6:$BU$6,BW$9,$J74:$BU74) -> 833.93058 | BX74: =SUMIF($J$6:$BU$6,BX$9,$J74:$BU74) -> 1379.1159 | BY74: =SUMIF($J$6:$BU$6,BY$9,$J74:$BU74) -> 1515.4942 | BZ74: =SUMIF($J$6:$BU$6,BZ$9,$J74:$BU74) -> 1108.2497 | CA74: =SUMIF($J$6:$BU$6,CA$9,$J74:$BU74) -> 1036.5401 | CB74: =CA74*(1+Inputs!$C$34) -> 1078.0017 | CC74: =CB74*(1+Inputs!$C$34) -> 1121.1218 | CD74: =CC74*(1+Inputs!$C$34) -> 1165.9666 | CE74: =CD74*(1+Inputs!$C$34) -> 1212.6053 | CF74: =CE74*(1+Inputs!$C$34) -> 1261.1095 | CG74: =CF74*(1+Inputs!$C$34) -> 1311.5539 | CH74: =CG74*(1+Inputs!$C$34) -> 1364.0161 | CI74: =CH74*(1+Inputs!$C$34) -> 1418.5767 | ... CK74: =CJ74*(1+Inputs!$C$34) -> 1534.3326
A75: =$F$2 -> 0 | B75: =F75 -> 4962 | F75: 4962 | G75: Site Truck Rental | H75: =VLOOKUP($F75,Inputs!$E:$J,6,FALSE) -> 0 | J75: =$H75*(1+Inputs!$C$35)^(J$7-1) -> 0 | K75: =$H75*(1+Inputs!$C$35)^(K$7-1) -> 0 | L75: =$H75*(1+Inputs!$C$35)^(L$7-1) -> 0 | M75: =$H75*(1+Inputs!$C$35)^(M$7-1) -> 0 | N75: =$H75*(1+Inputs!$C$35)^(N$7-1) -> 0 | O75: =$H75*(1+Inputs!$C$35)^(O$7-1) -> 0 | P75: =$H75*(1+Inputs!$C$35)^(P$7-1) -> 0 | Q75: =$H75*(1+Inputs!$C$35)^(Q$7-1) -> 0 | ... BU75: =$H75*(1+Inputs!$C$35)^(BU$7-1) -> 0 | BW75: =SUMIF($J$6:$BU$6,BW$9,$J75:$BU75) -> 0 | BX75: =SUMIF($J$6:$BU$6,BX$9,$J75:$BU75) -> 0 | BY75: =SUMIF($J$6:$BU$6,BY$9,$J75:$BU75) -> 0 | BZ75: =SUMIF($J$6:$BU$6,BZ$9,$J75:$BU75) -> 0 | CA75: =SUMIF($J$6:$BU$6,CA$9,$J75:$BU75) -> 0 | CB75: =CA75*(1+Inputs!$C$34) -> 0 | CC75: =CB75*(1+Inputs!$C$34) -> 0 | CD75: =CC75*(1+Inputs!$C$34) -> 0 | CE75: =CD75*(1+Inputs!$C$34) -> 0 | CF75: =CE75*(1+Inputs!$C$34) -> 0 | CG75: =CF75*(1+Inputs!$C$34) -> 0 | CH75: =CG75*(1+Inputs!$C$34) -> 0 | CI75: =CH75*(1+Inputs!$C$34) -> 0 | ... CK75: =CJ75*(1+Inputs!$C$34) -> 0
A76: =$F$2 -> 0 | B76: =F76 -> 4999 | F76: 4999 | G76: Miscellaneous | J76: 0 | K76: 0 | L76: 0 | M76: 0 | N76: 0 | O76: 0 | P76: 0 | Q76: 0 | R76: 0 | S76: 0 | T76: 0 | U76: 0 | V76: 0 | W76: 0 | X76: 0 | Y76: 0 | Z76: 0 | AA76: 0 | AB76: 0 | AC76: 0 | AD76: 0 | AE76: 0 | AF76: 0 | AG76: 0 | AH76: 0 | AI76: 0 | AJ76: 0 | AK76: 0 | AL76: 0 | AM76: 0 | AN76: 0 | AO76: 0 | AP76: 0 | AQ76: 0 | AR76: 0 | AS76: 0 | AT76: 0 | AU76: 0 | AV76: 0 | AW76: 0 | AX76: 0 | AY76: 0 | AZ76: 0 | BA76: 0 | BB76: 0 | BC76: 0 | BD76: 0 | BE76: 0 | BF76: 0 | BG76: 0 | BH76: 0 | BI76: 0 | BJ76: 0 | BK76: 0 | BL76: 0 | BM76: 0 | BN76: 0 | BO76: 0 | BP76: 0 | BQ76: 0 | BR76: 0 | BS76: 0 | BT76: 0 | BU76: 0 | BW76: =SUMIF($J$6:$BU$6,BW$9,$J76:$BU76) -> 0 | BX76: =SUMIF($J$6:$BU$6,BX$9,$J76:$BU76) -> 0 | BY76: =SUMIF($J$6:$BU$6,BY$9,$J76:$BU76) -> 0 | BZ76: =SUMIF($J$6:$BU$6,BZ$9,$J76:$BU76) -> 0 | CA76: =SUMIF($J$6:$BU$6,CA$9,$J76:$BU76) -> 0 | CB76: =CA76*(1+Inputs!$C$34) -> 0 | CC76: =CB76*(1+Inputs!$C$34) -> 0 | CD76: =CC76*(1+Inputs!$C$34) -> 0 | CE76: =CD76*(1+Inputs!$C$34) -> 0 | CF76: =CE76*(1+Inputs!$C$34) -> 0 | CG76: =CF76*(1+Inputs!$C$34) -> 0 | CH76: =CG76*(1+Inputs!$C$34) -> 0 | CI76: =CH76*(1+Inputs!$C$34) -> 0 | ... CK76: =CJ76*(1+Inputs!$C$34) -> 0
A77: =$F$2 -> 0 | B77: AncInc | F77: Ancillary Income | J77: =SUM(J72:J76) -> 104.48095 | K77: =SUM(K72:K76) -> 170.38683 | L77: =SUM(L72:L76) -> 279.50851 | M77: =SUM(M72:M76) -> 377.62819 | N77: =SUM(N72:N76) -> 552.20542 | O77: =SUM(O72:O76) -> 663.80778 | P77: =SUM(P72:P76) -> 765.51297 | Q77: =SUM(Q72:Q76) -> 839.16315 | ... BU77: =SUM(BU72:BU76) -> 2886.9294 | BW77: =SUM(BW72:BW76) -> 7756.3806 | BX77: =SUM(BX72:BX76) -> 20909.988 | BY77: =SUM(BY72:BY76) -> 31666.483 | BZ77: =SUM(BZ72:BZ76) -> 35089.37 | CA77: =SUM(CA72:CA76) -> 35017.66 | CB77: =SUM(CB72:CB76) -> 36418.367 | CC77: =SUM(CC72:CC76) -> 37875.101 | CD77: =SUM(CD72:CD76) -> 39390.105 | ... CK77: =SUM(CK72:CK76) -> 51834.691
A78: =$F$2 -> 0
A79: =$F$2 -> 0 | B79: TotAncInc | F79: Total Ancillary Income | J79: =J77+J69 -> 356.34561 | K79: =K77+K69 -> 447.2821 | L79: =L77+L69 -> 701.14089 | M79: =M77+M69 -> 871.72335 | N79: =N77+N69 -> 1305.0796 | O79: =O77+O69 -> 1439.9803 | P79: =P77+P69 -> 1586.4372 | Q79: =Q77+Q69 -> 1672.4632 | ... BU79: =BU77+BU69 -> 4858.4886 | BW79: =BW77+BW69 -> 15910.445 | BX79: =BX77+BX69 -> 38499.05 | BY79: =BY77+BY69 -> 55818.578 | BZ79: =BZ77+BZ69 -> 59376.146 | CA79: =CA77+CA69 -> 59666.74 | CB79: =CB77+CB69 -> 62053.41 | CC79: =CC77+CC69 -> 64535.547 | CD79: =CD77+CD69 -> 67116.968 | ... CK79: =CK77+CK69 -> 88321.352
A80: =$F$2 -> 0 | B80: Income | F80: Total Revenues | J80: =J77+J69+J57 -> 3731.0619 | K80: =K77+K69+K57 -> 7167.1161 | L80: =L77+L69+L57 -> 12097.62 | M80: =M77+M69+M57 -> 17256.967 | N80: =N77+N69+N57 -> 25698.642 | O80: =O77+O69+O57 -> 33017.712 | P80: =P77+P69+P57 -> 39393.477 | Q80: =Q77+Q69+Q57 -> 43866.913 | ... BU80: =BU77+BU69+BU57 -> 193095.55 | BW80: =BW77+BW69+BW57 -> 395937.18 | BX80: =BX77+BX69+BX57 -> 1162044.5 | BY80: =BY77+BY69+BY57 -> 1872326 | BZ80: =BZ77+BZ69+BZ57 -> 2186872.8 | CA80: =CA77+CA69+CA57 -> 2282766.2 | CB80: =CB77+CB69+CB57 -> 2374076.8 | CC80: =CC77+CC69+CC57 -> 2469039.9 | CD80: =CD77+CD69+CD57 -> 2567801.5 | ... CK80: =CK77+CK69+CK57 -> 3379051.6
A81: =$F$2 -> 0
A82: =$F$2 -> 0 | D82: Property operating expenses
A83: =$F$2 -> 0 | F83: Personnel Expense
A84: =$F$2 -> 0 | B84: =F84 -> 6100 | F84: 6100 | G84: Salaries | J84: =Inputs!$U$8*Inputs!$V$8*4.3 -> 4961.5385 | K84: =Inputs!$U$8*Inputs!$V$8*4.3 -> 4961.5385 | L84: =Inputs!$U$8*Inputs!$V$8*4.3 -> 4961.5385 | M84: =Inputs!$U$8*Inputs!$V$8*4.3 -> 4961.5385 | N84: =Inputs!$U$8*Inputs!$V$8*4.3 -> 4961.5385 | O84: =Inputs!$U$8*Inputs!$V$8*4.3 -> 4961.5385 | P84: =Inputs!$U$8*Inputs!$V$8*4.3 -> 4961.5385 | Q84: =Inputs!$U$8*Inputs!$V$8*4.3 -> 4961.5385 | ... U84: =Inputs!$U$8*Inputs!$V$8*4.3 -> 4961.5385 | V84: =J84*(1+Inputs!$C$35) -> 5085.5769 | W84: =K84*(1+Inputs!$C$35) -> 5085.5769 | X84: =L84*(1+Inputs!$C$35) -> 5085.5769 | Y84: =M84*(1+Inputs!$C$35) -> 5085.5769 | Z84: =N84*(1+Inputs!$C$35) -> 5085.5769 | AA84: =O84*(1+Inputs!$C$35) -> 5085.5769 | AB84: =P84*(1+Inputs!$C$35) -> 5085.5769 | AC84: =Q84*(1+Inputs!$C$35) -> 5085.5769 | ... BU84: =BI84*(1+Inputs!$C$35) -> 5613.5254 | BW84: =SUMIF($J$6:$BU$6,BW$9,$J84:$BU84) -> 59538.462 | BX84: =SUMIF($J$6:$BU$6,BX$9,$J84:$BU84) -> 61026.923 | BY84: =SUMIF($J$6:$BU$6,BY$9,$J84:$BU84) -> 62552.596 | BZ84: =SUMIF($J$6:$BU$6,BZ$9,$J84:$BU84) -> 64116.411 | CA84: =SUMIF($J$6:$BU$6,CA$9,$J84:$BU84) -> 65719.321 | CB84: =CA84*(1+Inputs!$C$35) -> 67362.304 | CC84: =CB84*(1+Inputs!$C$35) -> 69046.362 | CD84: =CC84*(1+Inputs!$C$35) -> 70772.521 | CE84: =CD84*(1+Inputs!$C$35) -> 72541.834 | CF84: =CE84*(1+Inputs!$C$35) -> 74355.38 | CG84: =CF84*(1+Inputs!$C$35) -> 76214.264 | CH84: =CG84*(1+Inputs!$C$35) -> 78119.621 | CI84: =CH84*(1+Inputs!$C$35) -> 80072.612 | ... CK84: =CJ84*(1+Inputs!$C$35) -> 84126.287
A85: =$F$2 -> 0 | B85: =F85 -> 6112 | F85: 6112 | G85: Medical Exp. | H85: =Inputs!$Q5*Inputs!$Q4 -> 822 | J85: =$H85 -> 822 | K85: =$H85 -> 822 | L85: =$H85 -> 822 | M85: =$H85 -> 822 | N85: =$H85 -> 822 | O85: =$H85 -> 822 | P85: =$H85 -> 822 | Q85: =$H85 -> 822 | ... U85: =$H85 -> 822 | V85: =J85*(1+Inputs!$C$35) -> 842.55 | W85: =K85*(1+Inputs!$C$35) -> 842.55 | X85: =L85*(1+Inputs!$C$35) -> 842.55 | Y85: =M85*(1+Inputs!$C$35) -> 842.55 | Z85: =N85*(1+Inputs!$C$35) -> 842.55 | AA85: =O85*(1+Inputs!$C$35) -> 842.55 | AB85: =P85*(1+Inputs!$C$35) -> 842.55 | AC85: =Q85*(1+Inputs!$C$35) -> 842.55 | ... BU85: =BI85*(1+Inputs!$C$35) -> 930.01755 | BW85: =SUMIF($J$6:$BU$6,BW$9,$J85:$BU85) -> 9864 | BX85: =SUMIF($J$6:$BU$6,BX$9,$J85:$BU85) -> 10110.6 | BY85: =SUMIF($J$6:$BU$6,BY$9,$J85:$BU85) -> 10363.365 | BZ85: =SUMIF($J$6:$BU$6,BZ$9,$J85:$BU85) -> 10622.449 | CA85: =SUMIF($J$6:$BU$6,CA$9,$J85:$BU85) -> 10888.01 | CB85: =CA85*(1+Inputs!$C$35) -> 11160.211 | CC85: =CB85*(1+Inputs!$C$35) -> 11439.216 | CD85: =CC85*(1+Inputs!$C$35) -> 11725.196 | CE85: =CD85*(1+Inputs!$C$35) -> 12018.326 | CF85: =CE85*(1+Inputs!$C$35) -> 12318.784 | CG85: =CF85*(1+Inputs!$C$35) -> 12626.754 | CH85: =CG85*(1+Inputs!$C$35) -> 12942.423 | CI85: =CH85*(1+Inputs!$C$35) -> 13265.983 | ... CK85: =CJ85*(1+Inputs!$C$35) -> 13937.574
A86: =$F$2 -> 0 | B86: =F86 -> 6118 | F86: 6118 | G86: 401k Expense | H86: 0.01 | J86: =$H86*J$84 -> 49.615385 | K86: =$H86*K$84 -> 49.615385 | L86: =$H86*L$84 -> 49.615385 | M86: =$H86*M$84 -> 49.615385 | N86: =$H86*N$84 -> 49.615385 | O86: =$H86*O$84 -> 49.615385 | P86: =$H86*P$84 -> 49.615385 | Q86: =$H86*Q$84 -> 49.615385 | ... BU86: =$H86*BU$84 -> 56.135254 | BW86: =SUMIF($J$6:$BU$6,BW$9,$J86:$BU86) -> 595.38462 | BX86: =SUMIF($J$6:$BU$6,BX$9,$J86:$BU86) -> 610.26923 | BY86: =SUMIF($J$6:$BU$6,BY$9,$J86:$BU86) -> 625.52596 | BZ86: =SUMIF($J$6:$BU$6,BZ$9,$J86:$BU86) -> 641.16411 | CA86: =SUMIF($J$6:$BU$6,CA$9,$J86:$BU86) -> 657.19321 | CB86: =CA86*(1+Inputs!$C$35) -> 673.62304 | CC86: =CB86*(1+Inputs!$C$35) -> 690.46362 | CD86: =CC86*(1+Inputs!$C$35) -> 707.72521 | CE86: =CD86*(1+Inputs!$C$35) -> 725.41834 | CF86: =CE86*(1+Inputs!$C$35) -> 743.5538 | CG86: =CF86*(1+Inputs!$C$35) -> 762.14264 | CH86: =CG86*(1+Inputs!$C$35) -> 781.19621 | CI86: =CH86*(1+Inputs!$C$35) -> 800.72612 | ... CK86: =CJ86*(1+Inputs!$C$35) -> 841.26287
A87: =$F$2 -> 0 | B87: =F87 -> 6130 | F87: 6130 | G87: Payroll Taxes | H87: =VLOOKUP($F87,Inputs!$L:$Q,6,FALSE) -> 0.01 | J87: =$H87*(J88+J84) -> 50.111538 | K87: =$H87*(K88+K84) -> 50.111538 | L87: =$H87*(L88+L84) -> 50.111538 | M87: =$H87*(M88+M84) -> 50.111538 | N87: =$H87*(N88+N84) -> 50.111538 | O87: =$H87*(O88+O84) -> 50.111538 | P87: =$H87*(P88+P84) -> 50.111538 | Q87: =$H87*(Q88+Q84) -> 50.111538 | ... BU87: =$H87*(BU88+BU84) -> 56.696606 | BW87: =SUMIF($J$6:$BU$6,BW$9,$J87:$BU87) -> 601.33846 | BX87: =SUMIF($J$6:$BU$6,BX$9,$J87:$BU87) -> 616.37192 | BY87: =SUMIF($J$6:$BU$6,BY$9,$J87:$BU87) -> 631.78122 | BZ87: =SUMIF($J$6:$BU$6,BZ$9,$J87:$BU87) -> 647.57575 | CA87: =SUMIF($J$6:$BU$6,CA$9,$J87:$BU87) -> 663.76515 | CB87: =CA87*(1+Inputs!$C$35) -> 680.35927 | CC87: =CB87*(1+Inputs!$C$35) -> 697.36826 | CD87: =CC87*(1+Inputs!$C$35) -> 714.80246 | CE87: =CD87*(1+Inputs!$C$35) -> 732.67252 | CF87: =CE87*(1+Inputs!$C$35) -> 750.98934 | CG87: =CF87*(1+Inputs!$C$35) -> 769.76407 | CH87: =CG87*(1+Inputs!$C$35) -> 789.00817 | CI87: =CH87*(1+Inputs!$C$35) -> 808.73338 | ... CK87: =CJ87*(1+Inputs!$C$35) -> 849.6755
A88: =$F$2 -> 0 | B88: =F88 -> 6135 | F88: 6135 | G88: Bonus | H88: 0.01 | J88: =$H88*J$84 -> 49.615385 | K88: =$H88*K$84 -> 49.615385 | L88: =$H88*L$84 -> 49.615385 | M88: =$H88*M$84 -> 49.615385 | N88: =$H88*N$84 -> 49.615385 | O88: =$H88*O$84 -> 49.615385 | P88: =$H88*P$84 -> 49.615385 | Q88: =$H88*Q$84 -> 49.615385 | ... BU88: =$H88*BU$84 -> 56.135254 | BW88: =SUMIF($J$6:$BU$6,BW$9,$J88:$BU88) -> 595.38462 | BX88: =SUMIF($J$6:$BU$6,BX$9,$J88:$BU88) -> 610.26923 | BY88: =SUMIF($J$6:$BU$6,BY$9,$J88:$BU88) -> 625.52596 | BZ88: =SUMIF($J$6:$BU$6,BZ$9,$J88:$BU88) -> 641.16411 | CA88: =SUMIF($J$6:$BU$6,CA$9,$J88:$BU88) -> 657.19321 | CB88: =CA88*(1+Inputs!$C$35) -> 673.62304 | CC88: =CB88*(1+Inputs!$C$35) -> 690.46362 | CD88: =CC88*(1+Inputs!$C$35) -> 707.72521 | CE88: =CD88*(1+Inputs!$C$35) -> 725.41834 | CF88: =CE88*(1+Inputs!$C$35) -> 743.5538 | CG88: =CF88*(1+Inputs!$C$35) -> 762.14264 | CH88: =CG88*(1+Inputs!$C$35) -> 781.19621 | CI88: =CH88*(1+Inputs!$C$35) -> 800.72612 | ... CK88: =CJ88*(1+Inputs!$C$35) -> 841.26287
A89: =$F$2 -> 0 | B89: =F89 -> 6283 | F89: 6283 | G89: Workers Comp. Premium | H89: =IFERROR(VLOOKUP(Inputs!$C$5,Modeling!$N$4:$O$39,2,FALSE),Inputs!$Q$7) -> 0.01 | J89: =IF($H$89=Inputs!$Q$7,$H89*J$84,$H89*J$84/100) -> 49.615385 | K89: =IF($H$89=Inputs!$Q$7,$H89*K$84,$H89*K$84/100) -> 49.615385 | L89: =IF($H$89=Inputs!$Q$7,$H89*L$84,$H89*L$84/100) -> 49.615385 | M89: =IF($H$89=Inputs!$Q$7,$H89*M$84,$H89*M$84/100) -> 49.615385 | N89: =IF($H$89=Inputs!$Q$7,$H89*N$84,$H89*N$84/100) -> 49.615385 | O89: =IF($H$89=Inputs!$Q$7,$H89*O$84,$H89*O$84/100) -> 49.615385 | P89: =IF($H$89=Inputs!$Q$7,$H89*P$84,$H89*P$84/100) -> 49.615385 | Q89: =IF($H$89=Inputs!$Q$7,$H89*Q$84,$H89*Q$84/100) -> 49.615385 | ... BU89: =IF($H$89=Inputs!$Q$7,$H89*BU$84,$H89*BU$84/100) -> 56.135254 | BW89: =SUMIF($J$6:$BU$6,BW$9,$J89:$BU89) -> 595.38462 | BX89: =SUMIF($J$6:$BU$6,BX$9,$J89:$BU89) -> 610.26923 | BY89: =SUMIF($J$6:$BU$6,BY$9,$J89:$BU89) -> 625.52596 | BZ89: =SUMIF($J$6:$BU$6,BZ$9,$J89:$BU89) -> 641.16411 | CA89: =SUMIF($J$6:$BU$6,CA$9,$J89:$BU89) -> 657.19321 | CB89: =CA89*(1+Inputs!$C$35) -> 673.62304 | CC89: =CB89*(1+Inputs!$C$35) -> 690.46362 | CD89: =CC89*(1+Inputs!$C$35) -> 707.72521 | CE89: =CD89*(1+Inputs!$C$35) -> 725.41834 | CF89: =CE89*(1+Inputs!$C$35) -> 743.5538 | CG89: =CF89*(1+Inputs!$C$35) -> 762.14264 | CH89: =CG89*(1+Inputs!$C$35) -> 781.19621 | CI89: =CH89*(1+Inputs!$C$35) -> 800.72612 | ... CK89: =CJ89*(1+Inputs!$C$35) -> 841.26287
A90: =$F$2 -> 0 | B90: PayExp | F90: Total Personnel Expense | J90: =SUM(J84:J89) -> 5982.4962 | K90: =SUM(K84:K89) -> 5982.4962 | L90: =SUM(L84:L89) -> 5982.4962 | M90: =SUM(M84:M89) -> 5982.4962 | N90: =SUM(N84:N89) -> 5982.4962 | O90: =SUM(O84:O89) -> 5982.4962 | P90: =SUM(P84:P89) -> 5982.4962 | Q90: =SUM(Q84:Q89) -> 5982.4962 | ... BU90: =SUM(BU84:BU89) -> 6768.6453 | BW90: =SUM(BW84:BW89) -> 71789.954 | BX90: =SUM(BX84:BX89) -> 73584.703 | BY90: =SUM(BY84:BY89) -> 75424.32 | BZ90: =SUM(BZ84:BZ89) -> 77309.928 | CA90: =SUM(CA84:CA89) -> 79242.676 | CB90: =SUM(CB84:CB89) -> 81223.743 | CC90: =SUM(CC84:CC89) -> 83254.337 | CD90: =SUM(CD84:CD89) -> 85335.695 | ... CK90: =SUM(CK84:CK89) -> 101437.33
A91: =$F$2 -> 0
A92: =$F$2 -> 0 | F92: Utility Expense
A93: =$F$2 -> 0 | B93: =F93 -> 6150 | F93: 6150 | G93: Rubbish Removal | H93: =VLOOKUP($F93,Inputs!$L:$Q,6,FALSE) -> 0.11 | J93: =($H93*$F$3)/12 -> 969.8975 | K93: =($H93*$F$3)/12 -> 969.8975 | L93: =($H93*$F$3)/12 -> 969.8975 | M93: =($H93*$F$3)/12 -> 969.8975 | N93: =($H93*$F$3)/12 -> 969.8975 | O93: =($H93*$F$3)/12 -> 969.8975 | P93: =($H93*$F$3)/12 -> 969.8975 | Q93: =($H93*$F$3)/12 -> 969.8975 | ... U93: =($H93*$F$3)/12 -> 969.8975 | V93: =J93*(1+Inputs!$C$35) -> 994.14494 | W93: =K93*(1+Inputs!$C$35) -> 994.14494 | X93: =L93*(1+Inputs!$C$35) -> 994.14494 | Y93: =M93*(1+Inputs!$C$35) -> 994.14494 | Z93: =N93*(1+Inputs!$C$35) -> 994.14494 | AA93: =O93*(1+Inputs!$C$35) -> 994.14494 | AB93: =P93*(1+Inputs!$C$35) -> 994.14494 | AC93: =Q93*(1+Inputs!$C$35) -> 994.14494 | ... BU93: =BI93*(1+Inputs!$C$35) -> 1097.35 | BW93: =SUMIF($J$6:$BU$6,BW$9,$J93:$BU93) -> 11638.77 | BX93: =SUMIF($J$6:$BU$6,BX$9,$J93:$BU93) -> 11929.739 | BY93: =SUMIF($J$6:$BU$6,BY$9,$J93:$BU93) -> 12227.983 | BZ93: =SUMIF($J$6:$BU$6,BZ$9,$J93:$BU93) -> 12533.682 | CA93: =SUMIF($J$6:$BU$6,CA$9,$J93:$BU93) -> 12847.024 | CB93: =CA93*(1+Inputs!$C$35) -> 13168.2 | CC93: =CB93*(1+Inputs!$C$35) -> 13497.405 | CD93: =CC93*(1+Inputs!$C$35) -> 13834.84 | CE93: =CD93*(1+Inputs!$C$35) -> 14180.711 | CF93: =CE93*(1+Inputs!$C$35) -> 14535.229 | CG93: =CF93*(1+Inputs!$C$35) -> 14898.61 | CH93: =CG93*(1+Inputs!$C$35) -> 15271.075 | CI93: =CH93*(1+Inputs!$C$35) -> 15652.852 | ... CK93: =CJ93*(1+Inputs!$C$35) -> 16445.277
A94: =$F$2 -> 0 | B94: =F94 -> 6158 | F94: 6158 | G94: Exterminating | H94: =VLOOKUP($F94,Inputs!$L:$Q,6,FALSE) -> 0.05 | J94: =($H94*$F$3)/12 -> 440.8625 | K94: =($H94*$F$3)/12 -> 440.8625 | L94: =($H94*$F$3)/12 -> 440.8625 | M94: =($H94*$F$3)/12 -> 440.8625 | N94: =($H94*$F$3)/12 -> 440.8625 | O94: =($H94*$F$3)/12 -> 440.8625 | P94: =($H94*$F$3)/12 -> 440.8625 | Q94: =($H94*$F$3)/12 -> 440.8625 | ... U94: =($H94*$F$3)/12 -> 440.8625 | V94: =J94*(1+Inputs!$C$35) -> 451.88406 | W94: =K94*(1+Inputs!$C$35) -> 451.88406 | X94: =L94*(1+Inputs!$C$35) -> 451.88406 | Y94: =M94*(1+Inputs!$C$35) -> 451.88406 | Z94: =N94*(1+Inputs!$C$35) -> 451.88406 | AA94: =O94*(1+Inputs!$C$35) -> 451.88406 | AB94: =P94*(1+Inputs!$C$35) -> 451.88406 | AC94: =Q94*(1+Inputs!$C$35) -> 451.88406 | ... BU94: =BI94*(1+Inputs!$C$35) -> 498.79545 | BW94: =SUMIF($J$6:$BU$6,BW$9,$J94:$BU94) -> 5290.35 | BX94: =SUMIF($J$6:$BU$6,BX$9,$J94:$BU94) -> 5422.6087 | BY94: =SUMIF($J$6:$BU$6,BY$9,$J94:$BU94) -> 5558.174 | BZ94: =SUMIF($J$6:$BU$6,BZ$9,$J94:$BU94) -> 5697.1283 | CA94: =SUMIF($J$6:$BU$6,CA$9,$J94:$BU94) -> 5839.5565 | CB94: =CA94*(1+Inputs!$C$35) -> 5985.5454 | CC94: =CB94*(1+Inputs!$C$35) -> 6135.1841 | CD94: =CC94*(1+Inputs!$C$35) -> 6288.5637 | CE94: =CD94*(1+Inputs!$C$35) -> 6445.7778 | CF94: =CE94*(1+Inputs!$C$35) -> 6606.9222 | CG94: =CF94*(1+Inputs!$C$35) -> 6772.0953 | CH94: =CG94*(1+Inputs!$C$35) -> 6941.3977 | CI94: =CH94*(1+Inputs!$C$35) -> 7114.9326 | ... CK94: =CJ94*(1+Inputs!$C$35) -> 7475.1261
A95: =$F$2 -> 0 | B95: =F95 -> 6184 | F95: 6184 | G95: Electric | H95: =VLOOKUP($F95,Inputs!$L:$Q,6,FALSE) -> 0.28 | J95: =($H95*$F$3)*VLOOKUP(MONTH(J$9),Modeling!$B$19:$F$31,2,FALSE) -> 2221.947 | K95: =($H95*$F$3)*VLOOKUP(MONTH(K$9),Modeling!$B$19:$F$31,2,FALSE) -> 2221.947 | L95: =($H95*$F$3)*VLOOKUP(MONTH(L$9),Modeling!$B$19:$F$31,2,FALSE) -> 2221.947 | M95: =($H95*$F$3)*VLOOKUP(MONTH(M$9),Modeling!$B$19:$F$31,2,FALSE) -> 2221.947 | N95: =($H95*$F$3)*VLOOKUP(MONTH(N$9),Modeling!$B$19:$F$31,2,FALSE) -> 2221.947 | O95: =($H95*$F$3)*VLOOKUP(MONTH(O$9),Modeling!$B$19:$F$31,2,FALSE) -> 2370.0768 | P95: =($H95*$F$3)*VLOOKUP(MONTH(P$9),Modeling!$B$19:$F$31,2,FALSE) -> 3110.7258 | Q95: =($H95*$F$3)*VLOOKUP(MONTH(Q$9),Modeling!$B$19:$F$31,2,FALSE) -> 3110.7258 | ... U95: =($H95*$F$3)*VLOOKUP(MONTH(U$9),Modeling!$B$19:$F$31,2,FALSE) -> 2221.947 | V95: =J95*(1+Inputs!$C$35) -> 2277.4957 | W95: =K95*(1+Inputs!$C$35) -> 2277.4957 | X95: =L95*(1+Inputs!$C$35) -> 2277.4957 | Y95: =M95*(1+Inputs!$C$35) -> 2277.4957 | Z95: =N95*(1+Inputs!$C$35) -> 2277.4957 | AA95: =O95*(1+Inputs!$C$35) -> 2429.3287 | AB95: =P95*(1+Inputs!$C$35) -> 3188.4939 | AC95: =Q95*(1+Inputs!$C$35) -> 3188.4939 | ... BU95: =BI95*(1+Inputs!$C$35) -> 2513.9291 | BW95: =SUMIF($J$6:$BU$6,BW$9,$J95:$BU95) -> 29625.96 | BX95: =SUMIF($J$6:$BU$6,BX$9,$J95:$BU95) -> 30366.609 | BY95: =SUMIF($J$6:$BU$6,BY$9,$J95:$BU95) -> 31125.774 | BZ95: =SUMIF($J$6:$BU$6,BZ$9,$J95:$BU95) -> 31903.919 | CA95: =SUMIF($J$6:$BU$6,CA$9,$J95:$BU95) -> 32701.517 | CB95: =CA95*(1+Inputs!$C$35) -> 33519.054 | CC95: =CB95*(1+Inputs!$C$35) -> 34357.031 | CD95: =CC95*(1+Inputs!$C$35) -> 35215.957 | CE95: =CD95*(1+Inputs!$C$35) -> 36096.356 | CF95: =CE95*(1+Inputs!$C$35) -> 36998.764 | CG95: =CF95*(1+Inputs!$C$35) -> 37923.734 | CH95: =CG95*(1+Inputs!$C$35) -> 38871.827 | CI95: =CH95*(1+Inputs!$C$35) -> 39843.623 | ... CK95: =CJ95*(1+Inputs!$C$35) -> 41860.706
A96: =$F$2 -> 0 | B96: =F96 -> 6185 | F96: 6185 | G96: Telephone | H96: =VLOOKUP($F96,Inputs!$L:$Q,6,FALSE) -> 0.05 | J96: =($H96*$F$3)/12 -> 440.8625 | K96: =($H96*$F$3)/12 -> 440.8625 | L96: =($H96*$F$3)/12 -> 440.8625 | M96: =($H96*$F$3)/12 -> 440.8625 | N96: =($H96*$F$3)/12 -> 440.8625 | O96: =($H96*$F$3)/12 -> 440.8625 | P96: =($H96*$F$3)/12 -> 440.8625 | Q96: =($H96*$F$3)/12 -> 440.8625 | ... U96: =($H96*$F$3)/12 -> 440.8625 | V96: =J96*(1+Inputs!$C$35) -> 451.88406 | W96: =K96*(1+Inputs!$C$35) -> 451.88406 | X96: =L96*(1+Inputs!$C$35) -> 451.88406 | Y96: =M96*(1+Inputs!$C$35) -> 451.88406 | Z96: =N96*(1+Inputs!$C$35) -> 451.88406 | AA96: =O96*(1+Inputs!$C$35) -> 451.88406 | AB96: =P96*(1+Inputs!$C$35) -> 451.88406 | AC96: =Q96*(1+Inputs!$C$35) -> 451.88406 | ... BU96: =BI96*(1+Inputs!$C$35) -> 498.79545 | BW96: =SUMIF($J$6:$BU$6,BW$9,$J96:$BU96) -> 5290.35 | BX96: =SUMIF($J$6:$BU$6,BX$9,$J96:$BU96) -> 5422.6087 | BY96: =SUMIF($J$6:$BU$6,BY$9,$J96:$BU96) -> 5558.174 | BZ96: =SUMIF($J$6:$BU$6,BZ$9,$J96:$BU96) -> 5697.1283 | CA96: =SUMIF($J$6:$BU$6,CA$9,$J96:$BU96) -> 5839.5565 | CB96: =CA96*(1+Inputs!$C$35) -> 5985.5454 | CC96: =CB96*(1+Inputs!$C$35) -> 6135.1841 | CD96: =CC96*(1+Inputs!$C$35) -> 6288.5637 | CE96: =CD96*(1+Inputs!$C$35) -> 6445.7778 | CF96: =CE96*(1+Inputs!$C$35) -> 6606.9222 | CG96: =CF96*(1+Inputs!$C$35) -> 6772.0953 | CH96: =CG96*(1+Inputs!$C$35) -> 6941.3977 | CI96: =CH96*(1+Inputs!$C$35) -> 7114.9326 | ... CK96: =CJ96*(1+Inputs!$C$35) -> 7475.1261
A97: =$F$2 -> 0 | B97: =F97 -> 6186 | F97: 6186 | G97: Water/Sewer | H97: =VLOOKUP($F97,Inputs!$L:$Q,6,FALSE) -> 0.12 | J97: =($H97*$F$3)/12 -> 1058.07 | K97: =($H97*$F$3)/12 -> 1058.07 | L97: =($H97*$F$3)/12 -> 1058.07 | M97: =($H97*$F$3)/12 -> 1058.07 | N97: =($H97*$F$3)/12 -> 1058.07 | O97: =($H97*$F$3)/12 -> 1058.07 | P97: =($H97*$F$3)/12 -> 1058.07 | Q97: =($H97*$F$3)/12 -> 1058.07 | ... U97: =($H97*$F$3)/12 -> 1058.07 | V97: =J97*(1+Inputs!$C$35) -> 1084.5217 | W97: =K97*(1+Inputs!$C$35) -> 1084.5217 | X97: =L97*(1+Inputs!$C$35) -> 1084.5217 | Y97: =M97*(1+Inputs!$C$35) -> 1084.5217 | Z97: =N97*(1+Inputs!$C$35) -> 1084.5217 | AA97: =O97*(1+Inputs!$C$35) -> 1084.5217 | AB97: =P97*(1+Inputs!$C$35) -> 1084.5217 | AC97: =Q97*(1+Inputs!$C$35) -> 1084.5217 | ... BU97: =BI97*(1+Inputs!$C$35) -> 1197.1091 | BW97: =SUMIF($J$6:$BU$6,BW$9,$J97:$BU97) -> 12696.84 | BX97: =SUMIF($J$6:$BU$6,BX$9,$J97:$BU97) -> 13014.261 | BY97: =SUMIF($J$6:$BU$6,BY$9,$J97:$BU97) -> 13339.618 | BZ97: =SUMIF($J$6:$BU$6,BZ$9,$J97:$BU97) -> 13673.108 | CA97: =SUMIF($J$6:$BU$6,CA$9,$J97:$BU97) -> 14014.936 | CB97: =CA97*(1+Inputs!$C$35) -> 14365.309 | CC97: =CB97*(1+Inputs!$C$35) -> 14724.442 | CD97: =CC97*(1+Inputs!$C$35) -> 15092.553 | CE97: =CD97*(1+Inputs!$C$35) -> 15469.867 | CF97: =CE97*(1+Inputs!$C$35) -> 15856.613 | CG97: =CF97*(1+Inputs!$C$35) -> 16253.029 | CH97: =CG97*(1+Inputs!$C$35) -> 16659.354 | CI97: =CH97*(1+Inputs!$C$35) -> 17075.838 | ... CK97: =CJ97*(1+Inputs!$C$35) -> 17940.303
A98: =$F$2 -> 0 | B98: =F98 -> 6187 | F98: 6187 | G98: Gas & Utilities | H98: =VLOOKUP($F98,Inputs!$L:$Q,6,FALSE) -> 0.1 | J98: =($H98*$F$3)*VLOOKUP(MONTH(J$9),Modeling!$B$19:$F$31,3,FALSE) -> 2116.14 | K98: =($H98*$F$3)*VLOOKUP(MONTH(K$9),Modeling!$B$19:$F$31,3,FALSE) -> 2116.14 | L98: =($H98*$F$3)*VLOOKUP(MONTH(L$9),Modeling!$B$19:$F$31,3,FALSE) -> 2116.14 | M98: =($H98*$F$3)*VLOOKUP(MONTH(M$9),Modeling!$B$19:$F$31,3,FALSE) -> 1587.105 | N98: =($H98*$F$3)*VLOOKUP(MONTH(N$9),Modeling!$B$19:$F$31,3,FALSE) -> 529.035 | O98: =($H98*$F$3)*VLOOKUP(MONTH(O$9),Modeling!$B$19:$F$31,3,FALSE) -> 0 | P98: =($H98*$F$3)*VLOOKUP(MONTH(P$9),Modeling!$B$19:$F$31,3,FALSE) -> 0 | Q98: =($H98*$F$3)*VLOOKUP(MONTH(Q$9),Modeling!$B$19:$F$31,3,FALSE) -> 0 | ... U98: =($H98*$F$3)*VLOOKUP(MONTH(U$9),Modeling!$B$19:$F$31,3,FALSE) -> 1587.105 | V98: =J98*(1+Inputs!$C$35) -> 2169.0435 | W98: =K98*(1+Inputs!$C$35) -> 2169.0435 | X98: =L98*(1+Inputs!$C$35) -> 2169.0435 | Y98: =M98*(1+Inputs!$C$35) -> 1626.7826 | Z98: =N98*(1+Inputs!$C$35) -> 542.26088 | AA98: =O98*(1+Inputs!$C$35) -> 0 | AB98: =P98*(1+Inputs!$C$35) -> 0 | AC98: =Q98*(1+Inputs!$C$35) -> 0 | ... BU98: =BI98*(1+Inputs!$C$35) -> 1795.6636 | BW98: =SUMIF($J$6:$BU$6,BW$9,$J98:$BU98) -> 10580.7 | BX98: =SUMIF($J$6:$BU$6,BX$9,$J98:$BU98) -> 10845.218 | BY98: =SUMIF($J$6:$BU$6,BY$9,$J98:$BU98) -> 11116.348 | BZ98: =SUMIF($J$6:$BU$6,BZ$9,$J98:$BU98) -> 11394.257 | CA98: =SUMIF($J$6:$BU$6,CA$9,$J98:$BU98) -> 11679.113 | CB98: =CA98*(1+Inputs!$C$35) -> 11971.091 | CC98: =CB98*(1+Inputs!$C$35) -> 12270.368 | CD98: =CC98*(1+Inputs!$C$35) -> 12577.127 | CE98: =CD98*(1+Inputs!$C$35) -> 12891.556 | CF98: =CE98*(1+Inputs!$C$35) -> 13213.844 | CG98: =CF98*(1+Inputs!$C$35) -> 13544.191 | CH98: =CG98*(1+Inputs!$C$35) -> 13882.795 | CI98: =CH98*(1+Inputs!$C$35) -> 14229.865 | ... CK98: =CJ98*(1+Inputs!$C$35) -> 14950.252
A99: =$F$2 -> 0 | B99: =F99 -> 6200 | F99: 6200 | G99: Security Expense | H99: =VLOOKUP($F99,Inputs!$L:$Q,6,FALSE) -> 1e-12 | J99: =($H99*$F$3)/12 -> 8.81725e-09 | K99: =($H99*$F$3)/12 -> 8.81725e-09 | L99: =($H99*$F$3)/12 -> 8.81725e-09 | M99: =($H99*$F$3)/12 -> 8.81725e-09 | N99: =($H99*$F$3)/12 -> 8.81725e-09 | O99: =($H99*$F$3)/12 -> 8.81725e-09 | P99: =($H99*$F$3)/12 -> 8.81725e-09 | Q99: =($H99*$F$3)/12 -> 8.81725e-09 | ... U99: =($H99*$F$3)/12 -> 8.81725e-09 | V99: =J99*(1+Inputs!$C$35) -> 9.0376812e-09 | W99: =K99*(1+Inputs!$C$35) -> 9.0376812e-09 | X99: =L99*(1+Inputs!$C$35) -> 9.0376812e-09 | Y99: =M99*(1+Inputs!$C$35) -> 9.0376812e-09 | Z99: =N99*(1+Inputs!$C$35) -> 9.0376812e-09 | AA99: =O99*(1+Inputs!$C$35) -> 9.0376812e-09 | AB99: =P99*(1+Inputs!$C$35) -> 9.0376812e-09 | AC99: =Q99*(1+Inputs!$C$35) -> 9.0376812e-09 | ... BU99: =BI99*(1+Inputs!$C$35) -> 9.9759091e-09 | BW99: =SUMIF($J$6:$BU$6,BW$9,$J99:$BU99) -> 1.05807e-07 | BX99: =SUMIF($J$6:$BU$6,BX$9,$J99:$BU99) -> 1.0845217e-07 | BY99: =SUMIF($J$6:$BU$6,BY$9,$J99:$BU99) -> 1.1116348e-07 | BZ99: =SUMIF($J$6:$BU$6,BZ$9,$J99:$BU99) -> 1.1394257e-07 | CA99: =SUMIF($J$6:$BU$6,CA$9,$J99:$BU99) -> 1.1679113e-07 | CB99: =CA99*(1+Inputs!$C$35) -> 1.1971091e-07 | CC99: =CB99*(1+Inputs!$C$35) -> 1.2270368e-07 | CD99: =CC99*(1+Inputs!$C$35) -> 1.2577127e-07 | CE99: =CD99*(1+Inputs!$C$35) -> 1.2891556e-07 | CF99: =CE99*(1+Inputs!$C$35) -> 1.3213844e-07 | CG99: =CF99*(1+Inputs!$C$35) -> 1.3544191e-07 | CH99: =CG99*(1+Inputs!$C$35) -> 1.3882795e-07 | CI99: =CH99*(1+Inputs!$C$35) -> 1.4229865e-07 | ... CK99: =CJ99*(1+Inputs!$C$35) -> 1.4950252e-07
A100: =$F$2 -> 0 | B100: =F100 -> 6205 | F100: 6205 | G100: Fire Alarm Monitoring | H100: =VLOOKUP($F100,Inputs!$L:$Q,6,FALSE) -> 0.01 | J100: =($H100*$F$3)/12 -> 88.1725 | K100: =($H100*$F$3)/12 -> 88.1725 | L100: =($H100*$F$3)/12 -> 88.1725 | M100: =($H100*$F$3)/12 -> 88.1725 | N100: =($H100*$F$3)/12 -> 88.1725 | O100: =($H100*$F$3)/12 -> 88.1725 | P100: =($H100*$F$3)/12 -> 88.1725 | Q100: =($H100*$F$3)/12 -> 88.1725 | ... U100: =($H100*$F$3)/12 -> 88.1725 | V100: =J100*(1+Inputs!$C$35) -> 90.376812 | W100: =K100*(1+Inputs!$C$35) -> 90.376812 | X100: =L100*(1+Inputs!$C$35) -> 90.376812 | Y100: =M100*(1+Inputs!$C$35) -> 90.376812 | Z100: =N100*(1+Inputs!$C$35) -> 90.376812 | AA100: =O100*(1+Inputs!$C$35) -> 90.376812 | AB100: =P100*(1+Inputs!$C$35) -> 90.376812 | AC100: =Q100*(1+Inputs!$C$35) -> 90.376812 | ... BU100: =BI100*(1+Inputs!$C$35) -> 99.759091 | BW100: =SUMIF($J$6:$BU$6,BW$9,$J100:$BU100) -> 1058.07 | BX100: =SUMIF($J$6:$BU$6,BX$9,$J100:$BU100) -> 1084.5218 | BY100: =SUMIF($J$6:$BU$6,BY$9,$J100:$BU100) -> 1111.6348 | BZ100: =SUMIF($J$6:$BU$6,BZ$9,$J100:$BU100) -> 1139.4257 | CA100: =SUMIF($J$6:$BU$6,CA$9,$J100:$BU100) -> 1167.9113 | CB100: =CA100*(1+Inputs!$C$35) -> 1197.1091 | CC100: =CB100*(1+Inputs!$C$35) -> 1227.0368 | CD100: =CC100*(1+Inputs!$C$35) -> 1257.7127 | CE100: =CD100*(1+Inputs!$C$35) -> 1289.1556 | CF100: =CE100*(1+Inputs!$C$35) -> 1321.3844 | CG100: =CF100*(1+Inputs!$C$35) -> 1354.4191 | CH100: =CG100*(1+Inputs!$C$35) -> 1388.2795 | CI100: =CH100*(1+Inputs!$C$35) -> 1422.9865 | ... CK100: =CJ100*(1+Inputs!$C$35) -> 1495.0252
A101: =$F$2 -> 0 | B101: TotUtil | F101: Total Utility Expense | J101: =SUM(J93:J100) -> 7335.952 | K101: =SUM(K93:K100) -> 7335.952 | L101: =SUM(L93:L100) -> 7335.952 | M101: =SUM(M93:M100) -> 6806.917 | N101: =SUM(N93:N100) -> 5748.847 | O101: =SUM(O93:O100) -> 5367.9418 | P101: =SUM(P93:P100) -> 6108.5908 | Q101: =SUM(Q93:Q100) -> 6108.5908 | ... BU101: =SUM(BU93:BU100) -> 7701.4018 | BW101: =SUM(BW93:BW100) -> 76181.04 | BX101: =SUM(BX93:BX100) -> 78085.566 | BY101: =SUM(BY93:BY100) -> 80037.705 | BZ101: =SUM(BZ93:BZ100) -> 82038.648 | CA101: =SUM(CA93:CA100) -> 84089.614 | CB101: =SUM(CB93:CB100) -> 86191.854 | CC101: =SUM(CC93:CC100) -> 88346.651 | CD101: =SUM(CD93:CD100) -> 90555.317 | ... CK101: =SUM(CK93:CK100) -> 107641.82
A102: =$F$2 -> 0
A103: =$F$2 -> 0 | F103: Repair & Maintenance Expense
A104: =$F$2 -> 0 | B104: =F104 -> 6189 | F104: 6189 | G104: R&M Roof | H104: =VLOOKUP($F104,Inputs!$L:$Q,6,FALSE) -> 0.00945 | J104: =($H104*$F$3)/12*Inputs!$V$25 -> 24.996904 | K104: =($H104*$F$3)/12*Inputs!$V$25 -> 24.996904 | L104: =($H104*$F$3)/12*Inputs!$V$25 -> 24.996904 | M104: =($H104*$F$3)/12*Inputs!$V$25 -> 24.996904 | N104: =($H104*$F$3)/12*Inputs!$V$25 -> 24.996904 | O104: =($H104*$F$3)/12*Inputs!$V$25 -> 24.996904 | P104: =($H104*$F$3)/12*Inputs!$V$25 -> 24.996904 | Q104: =($H104*$F$3)/12*Inputs!$V$25 -> 24.996904 | ... U104: =($H104*$F$3)/12*Inputs!$V$25 -> 24.996904 | V104: =($H104*$F$3)/12*Inputs!$V$26 -> 49.993807 | W104: =($H104*$F$3)/12*Inputs!$V$26 -> 49.993807 | X104: =($H104*$F$3)/12*Inputs!$V$26 -> 49.993807 | Y104: =($H104*$F$3)/12*Inputs!$V$26 -> 49.993807 | Z104: =($H104*$F$3)/12*Inputs!$V$26 -> 49.993807 | AA104: =($H104*$F$3)/12*Inputs!$V$26 -> 49.993807 | AB104: =($H104*$F$3)/12*Inputs!$V$26 -> 49.993807 | AC104: =($H104*$F$3)/12*Inputs!$V$26 -> 49.993807 | ... AG104: =($H104*$F$3)/12*Inputs!$V$26 -> 49.993807 | AH104: =($H104*$F$3)/12*Inputs!$V$27 -> 83.323012 | AI104: =($H104*$F$3)/12*Inputs!$V$27 -> 83.323012 | AJ104: =($H104*$F$3)/12*Inputs!$V$27 -> 83.323012 | AK104: =($H104*$F$3)/12*Inputs!$V$27 -> 83.323012 | AL104: =($H104*$F$3)/12*Inputs!$V$27 -> 83.323012 | AM104: =($H104*$F$3)/12*Inputs!$V$27 -> 83.323012 | AN104: =($H104*$F$3)/12*Inputs!$V$27 -> 83.323012 | AO104: =($H104*$F$3)/12*Inputs!$V$27 -> 83.323012 | ... AS104: =($H104*$F$3)/12*Inputs!$V$27 -> 83.323012 | AT104: =AH104*(1+Inputs!$C$35) -> 85.406088 | AU104: =AI104*(1+Inputs!$C$35) -> 85.406088 | AV104: =AJ104*(1+Inputs!$C$35) -> 85.406088 | AW104: =AK104*(1+Inputs!$C$35) -> 85.406088 | AX104: =AL104*(1+Inputs!$C$35) -> 85.406088 | AY104: =AM104*(1+Inputs!$C$35) -> 85.406088 | AZ104: =AN104*(1+Inputs!$C$35) -> 85.406088 | BA104: =AO104*(1+Inputs!$C$35) -> 85.406088 | ... BU104: =BI104*(1+Inputs!$C$35) -> 89.729771 | BW104: =SUMIF($J$6:$BU$6,BW$9,$J104:$BU104) -> 299.96284 | BX104: =SUMIF($J$6:$BU$6,BX$9,$J104:$BU104) -> 599.92569 | BY104: =SUMIF($J$6:$BU$6,BY$9,$J104:$BU104) -> 999.87615 | BZ104: =SUMIF($J$6:$BU$6,BZ$9,$J104:$BU104) -> 1024.8731 | CA104: =SUMIF($J$6:$BU$6,CA$9,$J104:$BU104) -> 1050.4949 | CB104: =CA104*(1+Inputs!$C$35) -> 1076.7573 | CC104: =CB104*(1+Inputs!$C$35) -> 1103.6762 | CD104: =CC104*(1+Inputs!$C$35) -> 1131.2681 | CE104: =CD104*(1+Inputs!$C$35) -> 1159.5498 | CF104: =CE104*(1+Inputs!$C$35) -> 1188.5385 | CG104: =CF104*(1+Inputs!$C$35) -> 1218.252 | CH104: =CG104*(1+Inputs!$C$35) -> 1248.7083 | CI104: =CH104*(1+Inputs!$C$35) -> 1279.926 | ... CK104: =CJ104*(1+Inputs!$C$35) -> 1344.7223
...

Sheet 7 Year Projection
J3: =CONCATENATE(Inputs!C3," ",Inputs!C4,", ",Inputs!C5," ",Inputs!C6) -> 250 Dolson Avenue Middletown, New York 10940 | V3: =CONCATENATE(Inputs!C3," ",Inputs!C4,", ",Inputs!C5," ",Inputs!C6) -> 250 Dolson Avenue Middletown, New York 10940
H4: Net Rentable Sq. Feet: | I4: =Projection!F3 -> 105807 | T4: Net Rentable Sq. Feet: | U4: =Projection!H3 -> 105807
H5: Unit Count: | I5: =Projection!F4 -> 684 | T5: Unit Count: | U5: =Projection!H4 -> 684
F8: =EOMONTH(G8,-1) -> 46022 | G8: =EOMONTH(Inputs!$C$9,0) -> 46053 | H8: =EOMONTH(G8,1) -> 46081 | I8: =EOMONTH(H8,1) -> 46112 | J8: =EOMONTH(I8,1) -> 46142 | K8: =EOMONTH(J8,1) -> 46173 | L8: =EOMONTH(K8,1) -> 46203 | M8: =EOMONTH(L8,1) -> 46234 | N8: =EOMONTH(M8,1) -> 46265 | O8: =EOMONTH(N8,1) -> 46295 | ... R8: =EOMONTH(Q8,1) -> 46387 | S8: Year 1 | T8: Year 2 | U8: Year 3 | V8: Year 4 | W8: Year 5 | X8: Year 6 | Y8: Year 7 | Z8: Year 8 | AA8: Year 9 | AB8: Year 10 | AC8: Year 11 | AD8: Year 12 | AE8: Year 13 | AF8: Year 14 | AG8: Year 15
A10: MI | D10: Rentals | G10: {=IFERROR(INDEX(Projection!$B$9:$BE$196,MATCH($A10,Projection!$B$9:$B$196,0),MATCH(G$8,Projection!$B$9:$BE$9,0)),0)} -> 14.925849 | H10: {=IFERROR(INDEX(Projection!$B$9:$BE$196,MATCH($A10,Projection!$B$9:$B$196,0),MATCH(H$8,Projection!$B$9:$BE$9,0)),0)} -> 14.745787 | I10: {=IFERROR(INDEX(Projection!$B$9:$BE$196,MATCH($A10,Projection!$B$9:$B$196,0),MATCH(I$8,Projection!$B$9:$BE$9,0)),0)} -> 21.810253 | J10: {=IFERROR(INDEX(Projection!$B$9:$BE$196,MATCH($A10,Projection!$B$9:$B$196,0),MATCH(J$8,Projection!$B$9:$BE$9,0)),0)} -> 23.883929 | K10: {=IFERROR(INDEX(Projection!$B$9:$BE$196,MATCH($A10,Projection!$B$9:$B$196,0),MATCH(K$8,Projection!$B$9:$BE$9,0)),0)} -> 36.70985 | L10: {=IFERROR(INDEX(Projection!$B$9:$BE$196,MATCH($A10,Projection!$B$9:$B$196,0),MATCH(L$8,Projection!$B$9:$BE$9,0)),0)} -> 34.292549 | M10: {=IFERROR(INDEX(Projection!$B$9:$BE$196,MATCH($A10,Projection!$B$9:$B$196,0),MATCH(M$8,Projection!$B$9:$BE$9,0)),0)} -> 33.8332 | N10: {=IFERROR(INDEX(Projection!$B$9:$BE$196,MATCH($A10,Projection!$B$9:$B$196,0),MATCH(N$8,Projection!$B$9:$BE$9,0)),0)} -> 32.233434 | ... R10: {=IFERROR(INDEX(Projection!$B$9:$BE$196,MATCH($A10,Projection!$B$9:$B$196,0),MATCH(R$8,Projection!$B$9:$BE$9,0)),0)} -> 28.758354 | S10: =SUM(G10:R10) -> 333.57223 | T10: =SUMIF(Projection!$B:$B,$A10,Projection!BX:BX) -> 551.64635 | U10: =SUMIF(Projection!$B:$B,$A10,Projection!BY:BY) -> 606.19768 | V10: =SUMIF(Projection!$B:$B,$A10,Projection!BZ:BZ) -> 443.29988 | W10: =SUMIF(Projection!$B:$B,$A10,Projection!CA:CA) -> 414.61604 | X10: =SUMIF(Projection!$B:$B,$A10,Projection!CB:CB) -> 414.61604 | Y10: =SUMIF(Projection!$B:$B,$A10,Projection!CC:CC) -> 414.61604 | Z10: =SUMIF(Projection!$B:$B,$A10,Projection!CD:CD) -> 414.61604 | AA10: =SUMIF(Projection!$B:$B,$A10,Projection!CE:CE) -> 414.61604 | AB10: =SUMIF(Projection!$B:$B,$A10,Projection!CF:CF) -> 414.61604 | AC10: =SUMIF(Projection!$B:$B,$A10,Projection!CG:CG) -> 414.61604 | AD10: =SUMIF(Projection!$B:$B,$A10,Projection!CH:CH) -> 414.61604 | AE10: =SUMIF(Projection!$B:$B,$A10,Projection!CI:CI) -> 414.61604 | AF10: =SUMIF(Projection!$B:$B,$A10,Projection!CJ:CJ) -> 414.61604 | AG10: =SUMIF(Projection!$B:$B,$A10,Projection!CK:CK) -> 414.61604
A11: MO | D11: Vacates | G11: {=IFERROR(INDEX(Projection!$B$9:$BE$196,MATCH($A11,Projection!$B$9:$B$196,0),MATCH(G$8,Projection!$B$9:$BE$9,0)),0)} -> 0 | H11: {=IFERROR(INDEX(Projection!$B$9:$BE$196,MATCH($A11,Projection!$B$9:$B$196,0),MATCH(H$8,Projection!$B$9:$BE$9,0)),0)} -> 0 | I11: {=IFERROR(INDEX(Projection!$B$9:$BE$196,MATCH($A11,Projection!$B$9:$B$196,0),MATCH(I$8,Projection!$B$9:$BE$9,0)),0)} -> -1.4856926 | J11: {=IFERROR(INDEX(Projection!$B$9:$BE$196,MATCH($A11,Projection!$B$9:$B$196,0),MATCH(J$8,Projection!$B$9:$BE$9,0)),0)} -> -3.2315988 | K11: {=IFERROR(INDEX(Projection!$B$9:$BE$196,MATCH($A11,Projection!$B$9:$B$196,0),MATCH(K$8,Projection!$B$9:$BE$9,0)),0)} -> -5.0404209 | L11: {=IFERROR(INDEX(Projection!$B$9:$BE$196,MATCH($A11,Projection!$B$9:$B$196,0),MATCH(L$8,Projection!$B$9:$BE$9,0)),0)} -> -8.1490822 | M11: {=IFERROR(INDEX(Projection!$B$9:$BE$196,MATCH($A11,Projection!$B$9:$B$196,0),MATCH(M$8,Projection!$B$9:$BE$9,0)),0)} -> -10.976852 | N11: {=IFERROR(INDEX(Projection!$B$9:$BE$196,MATCH($A11,Projection!$B$9:$B$196,0),MATCH(N$8,Projection!$B$9:$BE$9,0)),0)} -> -14.977967 | ... R11: {=IFERROR(INDEX(Projection!$B$9:$BE$196,MATCH($A11,Projection!$B$9:$B$196,0),MATCH(R$8,Projection!$B$9:$BE$9,0)),0)} -> -16.6762 | S11: =SUM(G11:R11) -> -107.85223 | T11: =SUMIF(Projection!$B:$B,$A11,Projection!BX:BX) -> -312.24635 | U11: =SUMIF(Projection!$B:$B,$A11,Projection!BY:BY) -> -442.03768 | V11: =SUMIF(Projection!$B:$B,$A11,Projection!BZ:BZ) -> -451.73588 | W11: =SUMIF(Projection!$B:$B,$A11,Projection!CA:CA) -> -414.61604 | X11: =SUMIF(Projection!$B:$B,$A11,Projection!CB:CB) -> -414.61604 | Y11: =SUMIF(Projection!$B:$B,$A11,Projection!CC:CC) -> -414.61604 | Z11: =SUMIF(Projection!$B:$B,$A11,Projection!CD:CD) -> -414.61604 | AA11: =SUMIF(Projection!$B:$B,$A11,Projection!CE:CE) -> -414.61604 | AB11: =SUMIF(Projection!$B:$B,$A11,Projection!CF:CF) -> -414.61604 | AC11: =SUMIF(Projection!$B:$B,$A11,Projection!CG:CG) -> -414.61604 | AD11: =SUMIF(Projection!$B:$B,$A11,Projection!CH:CH) -> -414.61604 | AE11: =SUMIF(Projection!$B:$B,$A11,Projection!CI:CI) -> -414.61604 | AF11: =SUMIF(Projection!$B:$B,$A11,Projection!CJ:CJ) -> -414.61604 | AG11: =SUMIF(Projection!$B:$B,$A11,Projection!CK:CK) -> -414.61604
A12: Net | D12: Net Rentals | G12: =G10+G11 -> 14.925849 | H12: =H10+H11 -> 14.745787 | I12: =I10+I11 -> 20.32456 | J12: =J10+J11 -> 20.65233 | K12: =K10+K11 -> 31.669429 | L12: =L10+L11 -> 26.143467 | M12: =M10+M11 -> 22.856348 | N12: =N10+N11 -> 17.255467 | ... AG12: =AG10+AG11 -> 0
A13: RentEnd | D13: Rented Units (EoM) | F13: =Inputs!C19 -> 0 | G13: =F13+G12 -> 14.925849 | H13: =G13+H12 -> 29.671636 | I13: =H13+I12 -> 49.996196 | J13: =I13+J12 -> 70.648527 | K13: =J13+K12 -> 102.31796 | L13: =K13+L12 -> 128.46142 | M13: =L13+M12 -> 151.31777 | N13: =M13+N12 -> 168.57324 | ... R13: =Q13+R12 -> 225.72 | S13: =R13 -> 225.72 | T13: =S13+T12 -> 465.12 | U13: =T13+U12 -> 629.28 | V13: =U13+V12 -> 620.844 | W13: =V13+W12 -> 620.844 | X13: =W13+X12 -> 620.844 | Y13: =X13+Y12 -> 620.844 | Z13: =Y13+Z12 -> 620.844 | AA13: =Z13+AA12 -> 620.844 | ... AG13: =AF13+AG12 -> 620.844
C14: Occupancy
A15: SFRent | D15: Sq. Feet Rented | F15: =Projection!I25 -> 0 | G15: {=IFERROR(INDEX(Projection!$B$9:$BE$196,MATCH($A15,Projection!$B$9:$B$196,0),MATCH(G$8,Projection!$B$9:$BE$9,0)),0)} -> 2308.8587 | H15: {=IFERROR(INDEX(Projection!$B$9:$BE$196,MATCH($A15,Projection!$B$9:$B$196,0),MATCH(H$8,Projection!$B$9:$BE$9,0)),0)} -> 4589.8637 | I15: {=IFERROR(INDEX(Projection!$B$9:$BE$196,MATCH($A15,Projection!$B$9:$B$196,0),MATCH(I$8,Projection!$B$9:$BE$9,0)),0)} -> 7733.8414 | J15: {=IFERROR(INDEX(Projection!$B$9:$BE$196,MATCH($A15,Projection!$B$9:$B$196,0),MATCH(J$8,Projection!$B$9:$BE$9,0)),0)} -> 10928.521 | K15: {=IFERROR(INDEX(Projection!$B$9:$BE$196,MATCH($A15,Projection!$B$9:$B$196,0),MATCH(K$8,Projection!$B$9:$BE$9,0)),0)} -> 15827.421 | L15: {=IFERROR(INDEX(Projection!$B$9:$BE$196,MATCH($A15,Projection!$B$9:$B$196,0),MATCH(L$8,Projection!$B$9:$BE$9,0)),0)} -> 19871.517 | M15: {=IFERROR(INDEX(Projection!$B$9:$BE$196,MATCH($A15,Projection!$B$9:$B$196,0),MATCH(M$8,Projection!$B$9:$BE$9,0)),0)} -> 23407.134 | N15: {=IFERROR(INDEX(Projection!$B$9:$BE$196,MATCH($A15,Projection!$B$9:$B$196,0),MATCH(N$8,Projection!$B$9:$BE$9,0)),0)} -> 26076.358 | ... R15: {=IFERROR(INDEX(Projection!$B$9:$BE$196,MATCH($A15,Projection!$B$9:$B$196,0),MATCH(R$8,Projection!$B$9:$BE$9,0)),0)} -> 34916.31 | S15: =SUM(G15:R15)/12 -> 19830.076 | T15: =SUMIF(Projection!$B:$B,$A15,Projection!BX:BX) -> 55948.208 | U15: =SUMIF(Projection!$B:$B,$A15,Projection!BY:BY) -> 86370.633 | V15: =SUMIF(Projection!$B:$B,$A15,Projection!BZ:BZ) -> 97342.44 | W15: =SUMIF(Projection!$B:$B,$A15,Projection!CA:CA) -> 97342.44 | X15: =SUMIF(Projection!$B:$B,$A15,Projection!CB:CB) -> 97342.44 | Y15: =SUMIF(Projection!$B:$B,$A15,Projection!CC:CC) -> 97342.44 | Z15: =SUMIF(Projection!$B:$B,$A15,Projection!CD:CD) -> 97342.44 | AA15: =SUMIF(Projection!$B:$B,$A15,Projection!CE:CE) -> 97342.44 | AB15: =SUMIF(Projection!$B:$B,$A15,Projection!CF:CF) -> 97342.44 | AC15: =SUMIF(Projection!$B:$B,$A15,Projection!CG:CG) -> 97342.44 | AD15: =SUMIF(Projection!$B:$B,$A15,Projection!CH:CH) -> 97342.44 | AE15: =SUMIF(Projection!$B:$B,$A15,Projection!CI:CI) -> 97342.44 | AF15: =SUMIF(Projection!$B:$B,$A15,Projection!CJ:CJ) -> 97342.44 | AG15: =SUMIF(Projection!$B:$B,$A15,Projection!CK:CK) -> 97342.44
A16: SFOcc% | D16: Avg. Square Foot Occupancy | F16: =F15/U4 -> 0 | G16: =G15/$U$4 -> 0.021821417 | H16: =H15/$U$4 -> 0.043379585 | I16: =I15/$U$4 -> 0.073093854 | J16: =J15/$U$4 -> 0.10328732 | K16: =K15/$U$4 -> 0.14958765 | L16: =L15/$U$4 -> 0.1878091 | M16: =M15/$U$4 -> 0.22122481 | N16: =N15/$U$4 -> 0.2464521 | ... AG16: =AG15/$U$4 -> 0.92
A18: AvgRentRate | D18: Avg. Rent Rate on Rentals | G18: {=IFERROR(INDEX(Projection!$B$9:$BE$196,MATCH($A18,Projection!$B$9:$B$196,0),MATCH(G$8,Projection!$B$9:$BE$9,0)),0)} -> 18.175813 | H18: {=IFERROR(INDEX(Projection!$B$9:$BE$196,MATCH($A18,Projection!$B$9:$B$196,0),MATCH(H$8,Projection!$B$9:$BE$9,0)),0)} -> 18.236399 | I18: {=IFERROR(INDEX(Projection!$B$9:$BE$196,MATCH($A18,Projection!$B$9:$B$196,0),MATCH(I$8,Projection!$B$9:$BE$9,0)),0)} -> 18.479551 | J18: {=IFERROR(INDEX(Projection!$B$9:$BE$196,MATCH($A18,Projection!$B$9:$B$196,0),MATCH(J$8,Projection!$B$9:$BE$9,0)),0)} -> 19.280332 | K18: {=IFERROR(INDEX(Projection!$B$9:$BE$196,MATCH($A18,Projection!$B$9:$B$196,0),MATCH(K$8,Projection!$B$9:$BE$9,0)),0)} -> 20.115813 | L18: {=IFERROR(INDEX(Projection!$B$9:$BE$196,MATCH($A18,Projection!$B$9:$B$196,0),MATCH(L$8,Projection!$B$9:$BE$9,0)),0)} -> 20.685761 | M18: {=IFERROR(INDEX(Projection!$B$9:$BE$196,MATCH($A18,Projection!$B$9:$B$196,0),MATCH(M$8,Projection!$B$9:$BE$9,0)),0)} -> 20.754713 | N18: {=IFERROR(INDEX(Projection!$B$9:$BE$196,MATCH($A18,Projection!$B$9:$B$196,0),MATCH(N$8,Projection!$B$9:$BE$9,0)),0)} -> 19.578613 | ... R18: {=IFERROR(INDEX(Projection!$B$9:$BE$196,MATCH($A18,Projection!$B$9:$B$196,0),MATCH(R$8,Projection!$B$9:$BE$9,0)),0)} -> 18.774531 | S18: =AVERAGE(G18:R18) -> 19.265521 | T18: =Projection!BX33 -> 19.966468 | U18: =Projection!BY33 -> 20.413654 | V18: =Projection!BZ33 -> 20.553838 | W18: =Projection!CA33 -> 21.301659 | X18: =Projection!CB33 -> 22.153725 | Y18: =Projection!CC33 -> 23.039874 | Z18: =Projection!CD33 -> 23.961469 | AA18: =Projection!CE33 -> 24.919928 | ... AG18: =Projection!CK33 -> 31.531658
A19: IPRPSF | D19: In-Place Rate | G19: {=IFERROR(INDEX(Projection!$B$9:$BE$196,MATCH($A19,Projection!$B$9:$B$196,0),MATCH(G$8,Projection!$B$9:$BE$9,0)),0)} -> 18.175813 | H19: {=IFERROR(INDEX(Projection!$B$9:$BE$196,MATCH($A19,Projection!$B$9:$B$196,0),MATCH(H$8,Projection!$B$9:$BE$9,0)),0)} -> 18.205922 | I19: {=IFERROR(INDEX(Projection!$B$9:$BE$196,MATCH($A19,Projection!$B$9:$B$196,0),MATCH(I$8,Projection!$B$9:$BE$9,0)),0)} -> 18.324384 | J19: {=IFERROR(INDEX(Projection!$B$9:$BE$196,MATCH($A19,Projection!$B$9:$B$196,0),MATCH(J$8,Projection!$B$9:$BE$9,0)),0)} -> 18.644272 | K19: {=IFERROR(INDEX(Projection!$B$9:$BE$196,MATCH($A19,Projection!$B$9:$B$196,0),MATCH(K$8,Projection!$B$9:$BE$9,0)),0)} -> 19.16545 | L19: {=IFERROR(INDEX(Projection!$B$9:$BE$196,MATCH($A19,Projection!$B$9:$B$196,0),MATCH(L$8,Projection!$B$9:$BE$9,0)),0)} -> 19.760769 | M19: {=IFERROR(INDEX(Projection!$B$9:$BE$196,MATCH($A19,Projection!$B$9:$B$196,0),MATCH(M$8,Projection!$B$9:$BE$9,0)),0)} -> 20.085302 | N19: {=IFERROR(INDEX(Projection!$B$9:$BE$196,MATCH($A19,Projection!$B$9:$B$196,0),MATCH(N$8,Projection!$B$9:$BE$9,0)),0)} -> 20.121592 | ... R19: {=IFERROR(INDEX(Projection!$B$9:$BE$196,MATCH($A19,Projection!$B$9:$B$196,0),MATCH(R$8,Projection!$B$9:$BE$9,0)),0)} -> 20.160365 | S19: =AVERAGE(G19:R19) -> 19.424488 | T19: =Projection!BX34 -> 20.810242 | U19: =Projection!BY34 -> 21.794342 | V19: =Projection!BZ34 -> 22.648495 | W19: =Projection!CA34 -> 23.666244 | X19: =Projection!CB34 -> 24.612894 | Y19: =Projection!CC34 -> 25.59741 | Z19: =Projection!CD34 -> 26.621306 | AA19: =Projection!CE34 -> 27.686159 | ... AG19: =Projection!CK34 -> 35.031823
A21: 4100 | D21: Rental Income | G21: {=IFERROR(INDEX(Projection!$F$9:$BE$173,MATCH('7 Year Projection'!$A21,Projection!$F$9:$F$173,0),MATCH('7 Year Projection'!G$8,Projection!$F$9:$BE$9,0)),0)} -> 3497.1153 | H21: {=IFERROR(INDEX(Projection!$F$9:$BE$173,MATCH('7 Year Projection'!$A21,Projection!$F$9:$F$173,0),MATCH('7 Year Projection'!H$8,Projection!$F$9:$BE$9,0)),0)} -> 6963.5585 | I21: {=IFERROR(INDEX(Projection!$F$9:$BE$173,MATCH('7 Year Projection'!$A21,Projection!$F$9:$F$173,0),MATCH('7 Year Projection'!I$8,Projection!$F$9:$BE$9,0)),0)} -> 11809.823 | J21: {=IFERROR(INDEX(Projection!$F$9:$BE$173,MATCH('7 Year Projection'!$A21,Projection!$F$9:$F$173,0),MATCH('7 Year Projection'!J$8,Projection!$F$9:$BE$9,0)),0)} -> 16979.527 | K21: {=IFERROR(INDEX(Projection!$F$9:$BE$173,MATCH('7 Year Projection'!$A21,Projection!$F$9:$F$173,0),MATCH('7 Year Projection'!K$8,Projection!$F$9:$BE$9,0)),0)} -> 25278.303 | L21: {=IFERROR(INDEX(Projection!$F$9:$BE$173,MATCH('7 Year Projection'!$A21,Projection!$F$9:$F$173,0),MATCH('7 Year Projection'!L$8,Projection!$F$9:$BE$9,0)),0)} -> 32723.038 | M21: {=IFERROR(INDEX(Projection!$F$9:$BE$173,MATCH('7 Year Projection'!$A21,Projection!$F$9:$F$173,0),MATCH('7 Year Projection'!M$8,Projection!$F$9:$BE$9,0)),0)} -> 39178.279 | N21: {=IFERROR(INDEX(Projection!$F$9:$BE$173,MATCH('7 Year Projection'!$A21,Projection!$F$9:$F$173,0),MATCH('7 Year Projection'!N$8,Projection!$F$9:$BE$9,0)),0)} -> 43724.819 | ... R21: {=IFERROR(INDEX(Projection!$F$9:$BE$173,MATCH('7 Year Projection'!$A21,Projection!$F$9:$F$173,0),MATCH('7 Year Projection'!R$8,Projection!$F$9:$BE$9,0)),0)} -> 58660.464 | S21: =SUMIF(Projection!$F:$F,'7 Year Projection'!$A21,Projection!BW:BW) -> 393810.09 | T21: =SUMIF(Projection!$F:$F,'7 Year Projection'!$A21,Projection!BX:BX) -> 1164295.8 | U21: =SUMIF(Projection!$F:$F,'7 Year Projection'!$A21,Projection!BY:BY) -> 1882391.1 | V21: =SUMIF(Projection!$F:$F,'7 Year Projection'!$A21,Projection!BZ:BZ) -> 2204659.7 | W21: =SUMIF(Projection!$F:$F,'7 Year Projection'!$A21,Projection!CA:CA) -> 2303730 | X21: =SUMIF(Projection!$F:$F,'7 Year Projection'!$A21,Projection!CB:CB) -> 2395879.2 | Y21: =SUMIF(Projection!$F:$F,'7 Year Projection'!$A21,Projection!CC:CC) -> 2491714.3 | Z21: =SUMIF(Projection!$F:$F,'7 Year Projection'!$A21,Projection!CD:CD) -> 2591382.9 | AA21: =SUMIF(Projection!$F:$F,'7 Year Projection'!$A21,Projection!CE:CE) -> 2695038.2 | AB21: =SUMIF(Projection!$F:$F,'7 Year Projection'!$A21,Projection!CF:CF) -> 2802839.8 | AC21: =SUMIF(Projection!$F:$F,'7 Year Projection'!$A21,Projection!CG:CG) -> 2914953.3 | AD21: =SUMIF(Projection!$F:$F,'7 Year Projection'!$A21,Projection!CH:CH) -> 3031551.5 | AE21: =SUMIF(Projection!$F:$F,'7 Year Projection'!$A21,Projection!CI:CI) -> 3152813.5 | AF21: =SUMIF(Projection!$F:$F,'7 Year Projection'!$A21,Projection!CJ:CJ) -> 3278926.1 | AG21: =SUMIF(Projection!$F:$F,'7 Year Projection'!$A21,Projection!CK:CK) -> 3410083.1
A22: 4700 | D22: Discounts | G22: {=IFERROR(INDEX(Projection!$F$9:$BE$173,MATCH('7 Year Projection'!$A22,Projection!$F$9:$F$173,0),MATCH('7 Year Projection'!G$8,Projection!$F$9:$BE$9,0)),0)} -> -87.427883 | H22: {=IFERROR(INDEX(Projection!$F$9:$BE$173,MATCH('7 Year Projection'!$A22,Projection!$F$9:$F$173,0),MATCH('7 Year Projection'!H$8,Projection!$F$9:$BE$9,0)),0)} -> -174.08896 | I22: {=IFERROR(INDEX(Projection!$F$9:$BE$173,MATCH('7 Year Projection'!$A22,Projection!$F$9:$F$173,0),MATCH('7 Year Projection'!I$8,Projection!$F$9:$BE$9,0)),0)} -> -295.24558 | J22: {=IFERROR(INDEX(Projection!$F$9:$BE$173,MATCH('7 Year Projection'!$A22,Projection!$F$9:$F$173,0),MATCH('7 Year Projection'!J$8,Projection!$F$9:$BE$9,0)),0)} -> -424.48817 | K22: {=IFERROR(INDEX(Projection!$F$9:$BE$173,MATCH('7 Year Projection'!$A22,Projection!$F$9:$F$173,0),MATCH('7 Year Projection'!K$8,Projection!$F$9:$BE$9,0)),0)} -> -631.95758 | L22: {=IFERROR(INDEX(Projection!$F$9:$BE$173,MATCH('7 Year Projection'!$A22,Projection!$F$9:$F$173,0),MATCH('7 Year Projection'!L$8,Projection!$F$9:$BE$9,0)),0)} -> -818.07596 | M22: {=IFERROR(INDEX(Projection!$F$9:$BE$173,MATCH('7 Year Projection'!$A22,Projection!$F$9:$F$173,0),MATCH('7 Year Projection'!M$8,Projection!$F$9:$BE$9,0)),0)} -> -979.45698 | N22: {=IFERROR(INDEX(Projection!$F$9:$BE$173,MATCH('7 Year Projection'!$A22,Projection!$F$9:$F$173,0),MATCH('7 Year Projection'!N$8,Projection!$F$9:$BE$9,0)),0)} -> -1093.1205 | ... R22: {=IFERROR(INDEX(Projection!$F$9:$BE$173,MATCH('7 Year Projection'!$A22,Projection!$F$9:$F$173,0),MATCH('7 Year Projection'!R$8,Projection!$F$9:$BE$9,0)),0)} -> -1466.5116 | S22: =SUMIF(Projection!$F:$F,'7 Year Projection'!$A22,Projection!BW:BW) -> -9845.2523 | T22: =SUMIF(Projection!$F:$F,'7 Year Projection'!$A22,Projection!BX:BX) -> -29107.394 | U22: =SUMIF(Projection!$F:$F,'7 Year Projection'!$A22,Projection!BY:BY) -> -47059.778 | V22: =SUMIF(Projection!$F:$F,'7 Year Projection'!$A22,Projection!BZ:BZ) -> -55116.493 | W22: =SUMIF(Projection!$F:$F,'7 Year Projection'!$A22,Projection!CA:CA) -> -57593.249 | X22: =SUMIF(Projection!$F:$F,'7 Year Projection'!$A22,Projection!CB:CB) -> -59896.979 | Y22: =SUMIF(Projection!$F:$F,'7 Year Projection'!$A22,Projection!CC:CC) -> -62292.858 | Z22: =SUMIF(Projection!$F:$F,'7 Year Projection'!$A22,Projection!CD:CD) -> -64784.573 | AA22: =SUMIF(Projection!$F:$F,'7 Year Projection'!$A22,Projection!CE:CE) -> -67375.956 | AB22: =SUMIF(Projection!$F:$F,'7 Year Projection'!$A22,Projection!CF:CF) -> -70070.994 | AC22: =SUMIF(Projection!$F:$F,'7 Year Projection'!$A22,Projection!CG:CG) -> -72873.834 | AD22: =SUMIF(Projection!$F:$F,'7 Year Projection'!$A22,Projection!CH:CH) -> -75788.787 | AE22: =SUMIF(Projection!$F:$F,'7 Year Projection'!$A22,Projection!CI:CI) -> -78820.339 | AF22: =SUMIF(Projection!$F:$F,'7 Year Projection'!$A22,Projection!CJ:CJ) -> -81973.152 | AG22: =SUMIF(Projection!$F:$F,'7 Year Projection'!$A22,Projection!CK:CK) -> -85252.078
A23: 7101 | D23: Write Off | G23: {=IFERROR(INDEX(Projection!$F$9:$BE$173,MATCH('7 Year Projection'!$A23,Projection!$F$9:$F$173,0),MATCH('7 Year Projection'!G$8,Projection!$F$9:$BE$9,0)),0)} -> -34.971153 | H23: {=IFERROR(INDEX(Projection!$F$9:$BE$173,MATCH('7 Year Projection'!$A23,Projection!$F$9:$F$173,0),MATCH('7 Year Projection'!H$8,Projection!$F$9:$BE$9,0)),0)} -> -69.635585 | I23: {=IFERROR(INDEX(Projection!$F$9:$BE$173,MATCH('7 Year Projection'!$A23,Projection!$F$9:$F$173,0),MATCH('7 Year Projection'!I$8,Projection!$F$9:$BE$9,0)),0)} -> -118.09823 | J23: {=IFERROR(INDEX(Projection!$F$9:$BE$173,MATCH('7 Year Projection'!$A23,Projection!$F$9:$F$173,0),MATCH('7 Year Projection'!J$8,Projection!$F$9:$BE$9,0)),0)} -> -169.79527 | K23: {=IFERROR(INDEX(Projection!$F$9:$BE$173,MATCH('7 Year Projection'!$A23,Projection!$F$9:$F$173,0),MATCH('7 Year Projection'!K$8,Projection!$F$9:$BE$9,0)),0)} -> -252.78303 | L23: {=IFERROR(INDEX(Projection!$F$9:$BE$173,MATCH('7 Year Projection'!$A23,Projection!$F$9:$F$173,0),MATCH('7 Year Projection'!L$8,Projection!$F$9:$BE$9,0)),0)} -> -327.23038 | M23: {=IFERROR(INDEX(Projection!$F$9:$BE$173,MATCH('7 Year Projection'!$A23,Projection!$F$9:$F$173,0),MATCH('7 Year Projection'!M$8,Projection!$F$9:$BE$9,0)),0)} -> -391.78279 | N23: {=IFERROR(INDEX(Projection!$F$9:$BE$173,MATCH('7 Year Projection'!$A23,Projection!$F$9:$F$173,0),MATCH('7 Year Projection'!N$8,Projection!$F$9:$BE$9,0)),0)} -> -437.24819 | ... R23: {=IFERROR(INDEX(Projection!$F$9:$BE$173,MATCH('7 Year Projection'!$A23,Projection!$F$9:$F$173,0),MATCH('7 Year Projection'!R$8,Projection!$F$9:$BE$9,0)),0)} -> -586.60464 | S23: =SUMIF(Projection!$F:$F,'7 Year Projection'!$A23,Projection!BW:BW) -> -3938.1009 | T23: =SUMIF(Projection!$F:$F,'7 Year Projection'!$A23,Projection!BX:BX) -> -11642.958 | U23: =SUMIF(Projection!$F:$F,'7 Year Projection'!$A23,Projection!BY:BY) -> -18823.911 | V23: =SUMIF(Projection!$F:$F,'7 Year Projection'!$A23,Projection!BZ:BZ) -> -22046.597 | W23: =SUMIF(Projection!$F:$F,'7 Year Projection'!$A23,Projection!CA:CA) -> -23037.3 | X23: =SUMIF(Projection!$F:$F,'7 Year Projection'!$A23,Projection!CB:CB) -> -23958.792 | Y23: =SUMIF(Projection!$F:$F,'7 Year Projection'!$A23,Projection!CC:CC) -> -24917.143 | Z23: =SUMIF(Projection!$F:$F,'7 Year Projection'!$A23,Projection!CD:CD) -> -25913.829 | AA23: =SUMIF(Projection!$F:$F,'7 Year Projection'!$A23,Projection!CE:CE) -> -26950.382 | AB23: =SUMIF(Projection!$F:$F,'7 Year Projection'!$A23,Projection!CF:CF) -> -28028.398 | AC23: =SUMIF(Projection!$F:$F,'7 Year Projection'!$A23,Projection!CG:CG) -> -29149.533 | AD23: =SUMIF(Projection!$F:$F,'7 Year Projection'!$A23,Projection!CH:CH) -> -30315.515 | AE23: =SUMIF(Projection!$F:$F,'7 Year Projection'!$A23,Projection!CI:CI) -> -31528.135 | AF23: =SUMIF(Projection!$F:$F,'7 Year Projection'!$A23,Projection!CJ:CJ) -> -32789.261 | AG23: =SUMIF(Projection!$F:$F,'7 Year Projection'!$A23,Projection!CK:CK) -> -34100.831
A24: NetRentInc | D24: Net Rental Income | G24: =SUM(G21:G23) -> 3374.7163 | H24: =SUM(H21:H23) -> 6719.834 | I24: =SUM(I21:I23) -> 11396.479 | J24: =SUM(J21:J23) -> 16385.244 | K24: =SUM(K21:K23) -> 24393.562 | L24: =SUM(L21:L23) -> 31577.732 | M24: =SUM(M21:M23) -> 37807.039 | N24: =SUM(N21:N23) -> 42194.45 | ... AG24: =SUM(AG21:AG23) -> 3290730.2
A25: Total Ancillary Income | D25: Total Ancillary Income | G25: {=IFERROR(INDEX(Projection!$F$9:$BE$173,MATCH('7 Year Projection'!$A25,Projection!$F$9:$F$173,0),MATCH('7 Year Projection'!G$8,Projection!$F$9:$BE$9,0)),0)} -> 356.34561 | H25: {=IFERROR(INDEX(Projection!$F$9:$BE$173,MATCH('7 Year Projection'!$A25,Projection!$F$9:$F$173,0),MATCH('7 Year Projection'!H$8,Projection!$F$9:$BE$9,0)),0)} -> 447.2821 | I25: {=IFERROR(INDEX(Projection!$F$9:$BE$173,MATCH('7 Year Projection'!$A25,Projection!$F$9:$F$173,0),MATCH('7 Year Projection'!I$8,Projection!$F$9:$BE$9,0)),0)} -> 701.14089 | J25: {=IFERROR(INDEX(Projection!$F$9:$BE$173,MATCH('7 Year Projection'!$A25,Projection!$F$9:$F$173,0),MATCH('7 Year Projection'!J$8,Projection!$F$9:$BE$9,0)),0)} -> 871.72335 | K25: {=IFERROR(INDEX(Projection!$F$9:$BE$173,MATCH('7 Year Projection'!$A25,Projection!$F$9:$F$173,0),MATCH('7 Year Projection'!K$8,Projection!$F$9:$BE$9,0)),0)} -> 1305.0796 | L25: {=IFERROR(INDEX(Projection!$F$9:$BE$173,MATCH('7 Year Projection'!$A25,Projection!$F$9:$F$173,0),MATCH('7 Year Projection'!L$8,Projection!$F$9:$BE$9,0)),0)} -> 1439.9803 | M25: {=IFERROR(INDEX(Projection!$F$9:$BE$173,MATCH('7 Year Projection'!$A25,Projection!$F$9:$F$173,0),MATCH('7 Year Projection'!M$8,Projection!$F$9:$BE$9,0)),0)} -> 1586.4372 | N25: {=IFERROR(INDEX(Projection!$F$9:$BE$173,MATCH('7 Year Projection'!$A25,Projection!$F$9:$F$173,0),MATCH('7 Year Projection'!N$8,Projection!$F$9:$BE$9,0)),0)} -> 1672.4632 | ... R25: {=IFERROR(INDEX(Projection!$F$9:$BE$173,MATCH('7 Year Projection'!$A25,Projection!$F$9:$F$173,0),MATCH('7 Year Projection'!R$8,Projection!$F$9:$BE$9,0)),0)} -> 1988.2949 | S25: =SUMIF(Projection!$F:$F,'7 Year Projection'!$A25,Projection!BW:BW) -> 15910.445 | T25: =SUMIF(Projection!$F:$F,'7 Year Projection'!$A25,Projection!BX:BX) -> 38499.05 | U25: =SUMIF(Projection!$F:$F,'7 Year Projection'!$A25,Projection!BY:BY) -> 55818.578 | V25: =SUMIF(Projection!$F:$F,'7 Year Projection'!$A25,Projection!BZ:BZ) -> 59376.146 | W25: =SUMIF(Projection!$F:$F,'7 Year Projection'!$A25,Projection!CA:CA) -> 59666.74 | X25: =SUMIF(Projection!$F:$F,'7 Year Projection'!$A25,Projection!CB:CB) -> 62053.41 | Y25: =SUMIF(Projection!$F:$F,'7 Year Projection'!$A25,Projection!CC:CC) -> 64535.547 | Z25: =SUMIF(Projection!$F:$F,'7 Year Projection'!$A25,Projection!CD:CD) -> 67116.968 | AA25: =SUMIF(Projection!$F:$F,'7 Year Projection'!$A25,Projection!CE:CE) -> 69801.647 | AB25: =SUMIF(Projection!$F:$F,'7 Year Projection'!$A25,Projection!CF:CF) -> 72593.713 | AC25: =SUMIF(Projection!$F:$F,'7 Year Projection'!$A25,Projection!CG:CG) -> 75497.462 | AD25: =SUMIF(Projection!$F:$F,'7 Year Projection'!$A25,Projection!CH:CH) -> 78517.36
C26: Property Revenue | G26: =SUM(G24:G25) -> 3731.0619 | H26: =SUM(H24:H25) -> 7167.1161 | I26: =SUM(I24:I25) -> 12097.62 | J26: =SUM(J24:J25) -> 17256.967 | K26: =SUM(K24:K25) -> 25698.642 | L26: =SUM(L24:L25) -> 33017.712 | M26: =SUM(M24:M25) -> 39393.477 | N26: =SUM(N24:N25) -> 43866.913 | ... AD26: =SUM(AD24:AD25) -> 3003964.5 | AE26: =SUM(AE24) -> 3042465.1 | AF26: =SUM(AF24) -> 3164163.7 | AG26: =SUM(AG24) -> 3290730.2
A28: Total Personnel Expense | D28: Payroll | G28: {=IFERROR(INDEX(Projection!$F$9:$BE$173,MATCH('7 Year Projection'!$A28,Projection!$F$9:$F$173,0),MATCH('7 Year Projection'!G$8,Projection!$F$9:$BE$9,0)),0)} -> 5982.4962 | H28: {=IFERROR(INDEX(Projection!$F$9:$BE$173,MATCH('7 Year Projection'!$A28,Projection!$F$9:$F$173,0),MATCH('7 Year Projection'!H$8,Projection!$F$9:$BE$9,0)),0)} -> 5982.4962 | I28: {=IFERROR(INDEX(Projection!$F$9:$BE$173,MATCH('7 Year Projection'!$A28,Projection!$F$9:$F$173,0),MATCH('7 Year Projection'!I$8,Projection!$F$9:$BE$9,0)),0)} -> 5982.4962 | J28: {=IFERROR(INDEX(Projection!$F$9:$BE$173,MATCH('7 Year Projection'!$A28,Projection!$F$9:$F$173,0),MATCH('7 Year Projection'!J$8,Projection!$F$9:$BE$9,0)),0)} -> 5982.4962 | K28: {=IFERROR(INDEX(Projection!$F$9:$BE$173,MATCH('7 Year Projection'!$A28,Projection!$F$9:$F$173,0),MATCH('7 Year Projection'!K$8,Projection!$F$9:$BE$9,0)),0)} -> 5982.4962 | L28: {=IFERROR(INDEX(Projection!$F$9:$BE$173,MATCH('7 Year Projection'!$A28,Projection!$F$9:$F$173,0),MATCH('7 Year Projection'!L$8,Projection!$F$9:$BE$9,0)),0)} -> 5982.4962 | M28: {=IFERROR(INDEX(Projection!$F$9:$BE$173,MATCH('7 Year Projection'!$A28,Projection!$F$9:$F$173,0),MATCH('7 Year Projection'!M$8,Projection!$F$9:$BE$9,0)),0)} -> 5982.4962 | N28: {=IFERROR(INDEX(Projection!$F$9:$BE$173,MATCH('7 Year Projection'!$A28,Projection!$F$9:$F$173,0),MATCH('7 Year Projection'!N$8,Projection!$F$9:$BE$9,0)),0)} -> 5982.4962 | ... R28: {=IFERROR(INDEX(Projection!$F$9:$BE$173,MATCH('7 Year Projection'!$A28,Projection!$F$9:$F$173,0),MATCH('7 Year Projection'!R$8,Projection!$F$9:$BE$9,0)),0)} -> 5982.4962 | S28: =SUMIF(Projection!$F:$F,'7 Year Projection'!$A28,Projection!BW:BW) -> 71789.954 | T28: =SUMIF(Projection!$F:$F,'7 Year Projection'!$A28,Projection!BX:BX) -> 73584.703 | U28: =SUMIF(Projection!$F:$F,'7 Year Projection'!$A28,Projection!BY:BY) -> 75424.32 | V28: =SUMIF(Projection!$F:$F,'7 Year Projection'!$A28,Projection!BZ:BZ) -> 77309.928 | W28: =SUMIF(Projection!$F:$F,'7 Year Projection'!$A28,Projection!CA:CA) -> 79242.676 | X28: =SUMIF(Projection!$F:$F,'7 Year Projection'!$A28,Projection!CB:CB) -> 81223.743 | Y28: =SUMIF(Projection!$F:$F,'7 Year Projection'!$A28,Projection!CC:CC) -> 83254.337 | Z28: =SUMIF(Projection!$F:$F,'7 Year Projection'!$A28,Projection!CD:CD) -> 85335.695 | AA28: =SUMIF(Projection!$F:$F,'7 Year Projection'!$A28,Projection!CE:CE) -> 87469.088 | AB28: =SUMIF(Projection!$F:$F,'7 Year Projection'!$A28,Projection!CF:CF) -> 89655.815 | AC28: =SUMIF(Projection!$F:$F,'7 Year Projection'!$A28,Projection!CG:CG) -> 91897.21 | AD28: =SUMIF(Projection!$F:$F,'7 Year Projection'!$A28,Projection!CH:CH) -> 94194.641 | AE28: =SUMIF(Projection!$F:$F,'7 Year Projection'!$A28,Projection!CI:CI) -> 96549.507 | AF28: =SUMIF(Projection!$F:$F,'7 Year Projection'!$A28,Projection!CJ:CJ) -> 98963.244 | AG28: =SUMIF(Projection!$F:$F,'7 Year Projection'!$A28,Projection!CK:CK) -> 101437.33
A29: Total Utility Expense | D29: Utilities | G29: {=IFERROR(INDEX(Projection!$F$9:$BE$173,MATCH('7 Year Projection'!$A29,Projection!$F$9:$F$173,0),MATCH('7 Year Projection'!G$8,Projection!$F$9:$BE$9,0)),0)} -> 7335.952 | H29: {=IFERROR(INDEX(Projection!$F$9:$BE$173,MATCH('7 Year Projection'!$A29,Projection!$F$9:$F$173,0),MATCH('7 Year Projection'!H$8,Projection!$F$9:$BE$9,0)),0)} -> 7335.952 | I29: {=IFERROR(INDEX(Projection!$F$9:$BE$173,MATCH('7 Year Projection'!$A29,Projection!$F$9:$F$173,0),MATCH('7 Year Projection'!I$8,Projection!$F$9:$BE$9,0)),0)} -> 7335.952 | J29: {=IFERROR(INDEX(Projection!$F$9:$BE$173,MATCH('7 Year Projection'!$A29,Projection!$F$9:$F$173,0),MATCH('7 Year Projection'!J$8,Projection!$F$9:$BE$9,0)),0)} -> 6806.917 | K29: {=IFERROR(INDEX(Projection!$F$9:$BE$173,MATCH('7 Year Projection'!$A29,Projection!$F$9:$F$173,0),MATCH('7 Year Projection'!K$8,Projection!$F$9:$BE$9,0)),0)} -> 5748.847 | L29: {=IFERROR(INDEX(Projection!$F$9:$BE$173,MATCH('7 Year Projection'!$A29,Projection!$F$9:$F$173,0),MATCH('7 Year Projection'!L$8,Projection!$F$9:$BE$9,0)),0)} -> 5367.9418 | M29: {=IFERROR(INDEX(Projection!$F$9:$BE$173,MATCH('7 Year Projection'!$A29,Projection!$F$9:$F$173,0),MATCH('7 Year Projection'!M$8,Projection!$F$9:$BE$9,0)),0)} -> 6108.5908 | N29: {=IFERROR(INDEX(Projection!$F$9:$BE$173,MATCH('7 Year Projection'!$A29,Projection!$F$9:$F$173,0),MATCH('7 Year Projection'!N$8,Projection!$F$9:$BE$9,0)),0)} -> 6108.5908 | ... R29: {=IFERROR(INDEX(Projection!$F$9:$BE$173,MATCH('7 Year Projection'!$A29,Projection!$F$9:$F$173,0),MATCH('7 Year Projection'!R$8,Projection!$F$9:$BE$9,0)),0)} -> 6806.917 | S29: =SUMIF(Projection!$F:$F,'7 Year Projection'!$A29,Projection!BW:BW) -> 76181.04 | T29: =SUMIF(Projection!$F:$F,'7 Year Projection'!$A29,Projection!BX:BX) -> 78085.566 | U29: =SUMIF(Projection!$F:$F,'7 Year Projection'!$A29,Projection!BY:BY) -> 80037.705 | V29: =SUMIF(Projection!$F:$F,'7 Year Projection'!$A29,Projection!BZ:BZ) -> 82038.648 | W29: =SUMIF(Projection!$F:$F,'7 Year Projection'!$A29,Projection!CA:CA) -> 84089.614 | X29: =SUMIF(Projection!$F:$F,'7 Year Projection'!$A29,Projection!CB:CB) -> 86191.854 | Y29: =SUMIF(Projection!$F:$F,'7 Year Projection'!$A29,Projection!CC:CC) -> 88346.651 | Z29: =SUMIF(Projection!$F:$F,'7 Year Projection'!$A29,Projection!CD:CD) -> 90555.317 | AA29: =SUMIF(Projection!$F:$F,'7 Year Projection'!$A29,Projection!CE:CE) -> 92819.2 | AB29: =SUMIF(Projection!$F:$F,'7 Year Projection'!$A29,Projection!CF:CF) -> 95139.68 | AC29: =SUMIF(Projection!$F:$F,'7 Year Projection'!$A29,Projection!CG:CG) -> 97518.172 | AD29: =SUMIF(Projection!$F:$F,'7 Year Projection'!$A29,Projection!CH:CH) -> 99956.126 | AE29: =SUMIF(Projection!$F:$F,'7 Year Projection'!$A29,Projection!CI:CI) -> 102455.03 | AF29: =SUMIF(Projection!$F:$F,'7 Year Projection'!$A29,Projection!CJ:CJ) -> 105016.41 | AG29: =SUMIF(Projection!$F:$F,'7 Year Projection'!$A29,Projection!CK:CK) -> 107641.82
A30: Total Other Operating Expense | D30: Operating Expenses | G30: {=IFERROR(INDEX(Projection!$F$9:$BE$173,MATCH('7 Year Projection'!$A30,Projection!$F$9:$F$173,0),MATCH('7 Year Projection'!G$8,Projection!$F$9:$BE$9,0)),0)} -> 773.81442 | H30: {=IFERROR(INDEX(Projection!$F$9:$BE$173,MATCH('7 Year Projection'!$A30,Projection!$F$9:$F$173,0),MATCH('7 Year Projection'!H$8,Projection!$F$9:$BE$9,0)),0)} -> 542.84367 | I30: {=IFERROR(INDEX(Projection!$F$9:$BE$173,MATCH('7 Year Projection'!$A30,Projection!$F$9:$F$173,0),MATCH('7 Year Projection'!I$8,Projection!$F$9:$BE$9,0)),0)} -> 656.24527 | J30: {=IFERROR(INDEX(Projection!$F$9:$BE$173,MATCH('7 Year Projection'!$A30,Projection!$F$9:$F$173,0),MATCH('7 Year Projection'!J$8,Projection!$F$9:$BE$9,0)),0)} -> 774.91024 | K30: {=IFERROR(INDEX(Projection!$F$9:$BE$173,MATCH('7 Year Projection'!$A30,Projection!$F$9:$F$173,0),MATCH('7 Year Projection'!K$8,Projection!$F$9:$BE$9,0)),0)} -> 969.06877 | L30: {=IFERROR(INDEX(Projection!$F$9:$BE$173,MATCH('7 Year Projection'!$A30,Projection!$F$9:$F$173,0),MATCH('7 Year Projection'!L$8,Projection!$F$9:$BE$9,0)),0)} -> 1137.4074 | M30: {=IFERROR(INDEX(Projection!$F$9:$BE$173,MATCH('7 Year Projection'!$A30,Projection!$F$9:$F$173,0),MATCH('7 Year Projection'!M$8,Projection!$F$9:$BE$9,0)),0)} -> 1284.05 | N30: {=IFERROR(INDEX(Projection!$F$9:$BE$173,MATCH('7 Year Projection'!$A30,Projection!$F$9:$F$173,0),MATCH('7 Year Projection'!N$8,Projection!$F$9:$BE$9,0)),0)} -> 1386.939 | ... R30: {=IFERROR(INDEX(Projection!$F$9:$BE$173,MATCH('7 Year Projection'!$A30,Projection!$F$9:$F$173,0),MATCH('7 Year Projection'!R$8,Projection!$F$9:$BE$9,0)),0)} -> 1725.6998 | S30: =SUMIF(Projection!$F:$F,'7 Year Projection'!$A30,Projection!BW:BW) -> 13952.567 | T30: =SUMIF(Projection!$F:$F,'7 Year Projection'!$A30,Projection!BX:BX) -> 32357.985 | U30: =SUMIF(Projection!$F:$F,'7 Year Projection'!$A30,Projection!BY:BY) -> 50326.07 | V30: =SUMIF(Projection!$F:$F,'7 Year Projection'!$A30,Projection!BZ:BZ) -> 59370.694 | W30: =SUMIF(Projection!$F:$F,'7 Year Projection'!$A30,Projection!CA:CA) -> 63285.098 | X30: =SUMIF(Projection!$F:$F,'7 Year Projection'!$A30,Projection!CB:CB) -> 64867.225 | Y30: =SUMIF(Projection!$F:$F,'7 Year Projection'!$A30,Projection!CC:CC) -> 66488.906 | Z30: =SUMIF(Projection!$F:$F,'7 Year Projection'!$A30,Projection!CD:CD) -> 68151.129 | AA30: =SUMIF(Projection!$F:$F,'7 Year Projection'!$A30,Projection!CE:CE) -> 69854.907 | AB30: =SUMIF(Projection!$F:$F,'7 Year Projection'!$A30,Projection!CF:CF) -> 71601.279 | AC30: =SUMIF(Projection!$F:$F,'7 Year Projection'!$A30,Projection!CG:CG) -> 73391.311 | AD30: =SUMIF(Projection!$F:$F,'7 Year Projection'!$A30,Projection!CH:CH) -> 75226.094 | AE30: =SUMIF(Projection!$F:$F,'7 Year Projection'!$A30,Projection!CI:CI) -> 77106.747 | AF30: =SUMIF(Projection!$F:$F,'7 Year Projection'!$A30,Projection!CJ:CJ) -> 79034.415 | AG30: =SUMIF(Projection!$F:$F,'7 Year Projection'!$A30,Projection!CK:CK) -> 81010.276
A31: 6171 | D31: Landscaping | G31: {=IFERROR(INDEX(Projection!$F$9:$BE$173,MATCH('7 Year Projection'!$A31,Projection!$F$9:$F$173,0),MATCH('7 Year Projection'!G$8,Projection!$F$9:$BE$9,0)),0)} -> 2909.6925 | H31: {=IFERROR(INDEX(Projection!$F$9:$BE$173,MATCH('7 Year Projection'!$A31,Projection!$F$9:$F$173,0),MATCH('7 Year Projection'!H$8,Projection!$F$9:$BE$9,0)),0)} -> 4655.508 | I31: {=IFERROR(INDEX(Projection!$F$9:$BE$173,MATCH('7 Year Projection'!$A31,Projection!$F$9:$F$173,0),MATCH('7 Year Projection'!I$8,Projection!$F$9:$BE$9,0)),0)} -> 5872.2885 | J31: {=IFERROR(INDEX(Projection!$F$9:$BE$173,MATCH('7 Year Projection'!$A31,Projection!$F$9:$F$173,0),MATCH('7 Year Projection'!J$8,Projection!$F$9:$BE$9,0)),0)} -> 1481.298 | K31: {=IFERROR(INDEX(Projection!$F$9:$BE$173,MATCH('7 Year Projection'!$A31,Projection!$F$9:$F$173,0),MATCH('7 Year Projection'!K$8,Projection!$F$9:$BE$9,0)),0)} -> 1481.298 | L31: {=IFERROR(INDEX(Projection!$F$9:$BE$173,MATCH('7 Year Projection'!$A31,Projection!$F$9:$F$173,0),MATCH('7 Year Projection'!L$8,Projection!$F$9:$BE$9,0)),0)} -> 1481.298 | M31: {=IFERROR(INDEX(Projection!$F$9:$BE$173,MATCH('7 Year Projection'!$A31,Projection!$F$9:$F$173,0),MATCH('7 Year Projection'!M$8,Projection!$F$9:$BE$9,0)),0)} -> 1481.298 | N31: {=IFERROR(INDEX(Projection!$F$9:$BE$173,MATCH('7 Year Projection'!$A31,Projection!$F$9:$F$173,0),MATCH('7 Year Projection'!N$8,Projection!$F$9:$BE$9,0)),0)} -> 1481.298 | ... R31: {=IFERROR(INDEX(Projection!$F$9:$BE$173,MATCH('7 Year Projection'!$A31,Projection!$F$9:$F$173,0),MATCH('7 Year Projection'!R$8,Projection!$F$9:$BE$9,0)),0)} -> 1163.877 | S31: =SUMIF(Projection!$F:$F,'7 Year Projection'!$A31,Projection!BW:BW) -> 26451.75 | T31: =SUMIF(Projection!$F:$F,'7 Year Projection'!$A31,Projection!BX:BX) -> 27113.044 | U31: =SUMIF(Projection!$F:$F,'7 Year Projection'!$A31,Projection!BY:BY) -> 27790.87 | V31: =SUMIF(Projection!$F:$F,'7 Year Projection'!$A31,Projection!BZ:BZ) -> 28485.642 | W31: =SUMIF(Projection!$F:$F,'7 Year Projection'!$A31,Projection!CA:CA) -> 29197.783 | X31: =SUMIF(Projection!$F:$F,'7 Year Projection'!$A31,Projection!CB:CB) -> 29927.727 | Y31: =SUMIF(Projection!$F:$F,'7 Year Projection'!$A31,Projection!CC:CC) -> 30675.92 | Z31: =SUMIF(Projection!$F:$F,'7 Year Projection'!$A31,Projection!CD:CD) -> 31442.818 | AA31: =SUMIF(Projection!$F:$F,'7 Year Projection'!$A31,Projection!CE:CE) -> 32228.889 | AB31: =SUMIF(Projection!$F:$F,'7 Year Projection'!$A31,Projection!CF:CF) -> 33034.611 | AC31: =SUMIF(Projection!$F:$F,'7 Year Projection'!$A31,Projection!CG:CG) -> 33860.476 | AD31: =SUMIF(Projection!$F:$F,'7 Year Projection'!$A31,Projection!CH:CH) -> 34706.988 | AE31: =SUMIF(Projection!$F:$F,'7 Year Projection'!$A31,Projection!CI:CI) -> 35574.663 | AF31: =SUMIF(Projection!$F:$F,'7 Year Projection'!$A31,Projection!CJ:CJ) -> 36464.03 | AG31: =SUMIF(Projection!$F:$F,'7 Year Projection'!$A31,Projection!CK:CK) -> 37375.63
A32: Total R&M Expense | D32: Repairs & Maintenance | G32: {=IFERROR(INDEX(Projection!$F$9:$BE$173,MATCH('7 Year Projection'!$A32,Projection!$F$9:$F$173,0),MATCH('7 Year Projection'!G$8,Projection!$F$9:$BE$9,0)),0)} -> 555.48675 | H32: {=IFERROR(INDEX(Projection!$F$9:$BE$173,MATCH('7 Year Projection'!$A32,Projection!$F$9:$F$173,0),MATCH('7 Year Projection'!H$8,Projection!$F$9:$BE$9,0)),0)} -> 555.48675 | I32: {=IFERROR(INDEX(Projection!$F$9:$BE$173,MATCH('7 Year Projection'!$A32,Projection!$F$9:$F$173,0),MATCH('7 Year Projection'!I$8,Projection!$F$9:$BE$9,0)),0)} -> 555.48675 | J32: {=IFERROR(INDEX(Projection!$F$9:$BE$173,MATCH('7 Year Projection'!$A32,Projection!$F$9:$F$173,0),MATCH('7 Year Projection'!J$8,Projection!$F$9:$BE$9,0)),0)} -> 555.48675 | K32: {=IFERROR(INDEX(Projection!$F$9:$BE$173,MATCH('7 Year Projection'!$A32,Projection!$F$9:$F$173,0),MATCH('7 Year Projection'!K$8,Projection!$F$9:$BE$9,0)),0)} -> 555.48675 | L32: {=IFERROR(INDEX(Projection!$F$9:$BE$173,MATCH('7 Year Projection'!$A32,Projection!$F$9:$F$173,0),MATCH('7 Year Projection'!L$8,Projection!$F$9:$BE$9,0)),0)} -> 555.48675 | M32: {=IFERROR(INDEX(Projection!$F$9:$BE$173,MATCH('7 Year Projection'!$A32,Projection!$F$9:$F$173,0),MATCH('7 Year Projection'!M$8,Projection!$F$9:$BE$9,0)),0)} -> 555.48675 | N32: {=IFERROR(INDEX(Projection!$F$9:$BE$173,MATCH('7 Year Projection'!$A32,Projection!$F$9:$F$173,0),MATCH('7 Year Projection'!N$8,Projection!$F$9:$BE$9,0)),0)} -> 555.48675 | ... R32: {=IFERROR(INDEX(Projection!$F$9:$BE$173,MATCH('7 Year Projection'!$A32,Projection!$F$9:$F$173,0),MATCH('7 Year Projection'!R$8,Projection!$F$9:$BE$9,0)),0)} -> 555.48675 | S32: =SUMIF(Projection!$F:$F,'7 Year Projection'!$A32,Projection!BW:BW) -> 6665.841 | T32: =SUMIF(Projection!$F:$F,'7 Year Projection'!$A32,Projection!BX:BX) -> 13331.682 | U32: =SUMIF(Projection!$F:$F,'7 Year Projection'!$A32,Projection!BY:BY) -> 22219.47 | V32: =SUMIF(Projection!$F:$F,'7 Year Projection'!$A32,Projection!BZ:BZ) -> 22774.957 | W32: =SUMIF(Projection!$F:$F,'7 Year Projection'!$A32,Projection!CA:CA) -> 23344.331 | X32: =SUMIF(Projection!$F:$F,'7 Year Projection'!$A32,Projection!CB:CB) -> 23927.939 | Y32: =SUMIF(Projection!$F:$F,'7 Year Projection'!$A32,Projection!CC:CC) -> 24526.137 | Z32: =SUMIF(Projection!$F:$F,'7 Year Projection'!$A32,Projection!CD:CD) -> 25139.291 | AA32: =SUMIF(Projection!$F:$F,'7 Year Projection'!$A32,Projection!CE:CE) -> 25767.773 | AB32: =SUMIF(Projection!$F:$F,'7 Year Projection'!$A32,Projection!CF:CF) -> 26411.967 | AC32: =SUMIF(Projection!$F:$F,'7 Year Projection'!$A32,Projection!CG:CG) -> 27072.267 | AD32: =SUMIF(Projection!$F:$F,'7 Year Projection'!$A32,Projection!CH:CH) -> 27749.073 | AE32: =SUMIF(Projection!$F:$F,'7 Year Projection'!$A32,Projection!CI:CI) -> 28442.8 | AF32: =SUMIF(Projection!$F:$F,'7 Year Projection'!$A32,Projection!CJ:CJ) -> 29153.87 | AG32: =SUMIF(Projection!$F:$F,'7 Year Projection'!$A32,Projection!CK:CK) -> 29882.717
A33: Total Marketing Expense | D33: Marketing | G33: {=IFERROR(INDEX(Projection!$F$9:$BE$173,MATCH('7 Year Projection'!$A33,Projection!$F$9:$F$173,0),MATCH('7 Year Projection'!G$8,Projection!$F$9:$BE$9,0)),0)} -> 1000 | H33: {=IFERROR(INDEX(Projection!$F$9:$BE$173,MATCH('7 Year Projection'!$A33,Projection!$F$9:$F$173,0),MATCH('7 Year Projection'!H$8,Projection!$F$9:$BE$9,0)),0)} -> 1000 | I33: {=IFERROR(INDEX(Projection!$F$9:$BE$173,MATCH('7 Year Projection'!$A33,Projection!$F$9:$F$173,0),MATCH('7 Year Projection'!I$8,Projection!$F$9:$BE$9,0)),0)} -> 1000 | J33: {=IFERROR(INDEX(Projection!$F$9:$BE$173,MATCH('7 Year Projection'!$A33,Projection!$F$9:$F$173,0),MATCH('7 Year Projection'!J$8,Projection!$F$9:$BE$9,0)),0)} -> 1000 | K33: {=IFERROR(INDEX(Projection!$F$9:$BE$173,MATCH('7 Year Projection'!$A33,Projection!$F$9:$F$173,0),MATCH('7 Year Projection'!K$8,Projection!$F$9:$BE$9,0)),0)} -> 1000 | L33: {=IFERROR(INDEX(Projection!$F$9:$BE$173,MATCH('7 Year Projection'!$A33,Projection!$F$9:$F$173,0),MATCH('7 Year Projection'!L$8,Projection!$F$9:$BE$9,0)),0)} -> 1000 | M33: {=IFERROR(INDEX(Projection!$F$9:$BE$173,MATCH('7 Year Projection'!$A33,Projection!$F$9:$F$173,0),MATCH('7 Year Projection'!M$8,Projection!$F$9:$BE$9,0)),0)} -> 1000 | N33: {=IFERROR(INDEX(Projection!$F$9:$BE$173,MATCH('7 Year Projection'!$A33,Projection!$F$9:$F$173,0),MATCH('7 Year Projection'!N$8,Projection!$F$9:$BE$9,0)),0)} -> 1000 | ... R33: {=IFERROR(INDEX(Projection!$F$9:$BE$173,MATCH('7 Year Projection'!$A33,Projection!$F$9:$F$173,0),MATCH('7 Year Projection'!R$8,Projection!$F$9:$BE$9,0)),0)} -> 1000 | S33: =SUMIF(Projection!$F:$F,'7 Year Projection'!$A33,Projection!BW:BW) -> 12000 | T33: =SUMIF(Projection!$F:$F,'7 Year Projection'!$A33,Projection!BX:BX) -> 12300 | U33: =SUMIF(Projection!$F:$F,'7 Year Projection'!$A33,Projection!BY:BY) -> 12607.5 | V33: =SUMIF(Projection!$F:$F,'7 Year Projection'!$A33,Projection!BZ:BZ) -> 12922.688 | W33: =SUMIF(Projection!$F:$F,'7 Year Projection'!$A33,Projection!CA:CA) -> 13245.755 | X33: =SUMIF(Projection!$F:$F,'7 Year Projection'!$A33,Projection!CB:CB) -> 13775.585 | Y33: =SUMIF(Projection!$F:$F,'7 Year Projection'!$A33,Projection!CC:CC) -> 14326.608 | Z33: =SUMIF(Projection!$F:$F,'7 Year Projection'!$A33,Projection!CD:CD) -> 14899.673 | AA33: =SUMIF(Projection!$F:$F,'7 Year Projection'!$A33,Projection!CE:CE) -> 15495.66 | AB33: =SUMIF(Projection!$F:$F,'7 Year Projection'!$A33,Projection!CF:CF) -> 16115.486 | AC33: =SUMIF(Projection!$F:$F,'7 Year Projection'!$A33,Projection!CG:CG) -> 16760.105 | AD33: =SUMIF(Projection!$F:$F,'7 Year Projection'!$A33,Projection!CH:CH) -> 17430.51 | AE33: =SUMIF(Projection!$F:$F,'7 Year Projection'!$A33,Projection!CI:CI) -> 18127.73 | AF33: =SUMIF(Projection!$F:$F,'7 Year Projection'!$A33,Projection!CJ:CJ) -> 18852.839 | AG33: =SUMIF(Projection!$F:$F,'7 Year Projection'!$A33,Projection!CK:CK) -> 19606.953
A34: 6270 | D34: Taxes | G34: {=IFERROR(INDEX(Projection!$F$9:$BE$173,MATCH('7 Year Projection'!$A34,Projection!$F$9:$F$173,0),MATCH('7 Year Projection'!G$8,Projection!$F$9:$BE$9,0)),0)} -> 10589.438 | H34: {=IFERROR(INDEX(Projection!$F$9:$BE$173,MATCH('7 Year Projection'!$A34,Projection!$F$9:$F$173,0),MATCH('7 Year Projection'!H$8,Projection!$F$9:$BE$9,0)),0)} -> 10589.438 | I34: {=IFERROR(INDEX(Projection!$F$9:$BE$173,MATCH('7 Year Projection'!$A34,Projection!$F$9:$F$173,0),MATCH('7 Year Projection'!I$8,Projection!$F$9:$BE$9,0)),0)} -> 10589.438 | J34: {=IFERROR(INDEX(Projection!$F$9:$BE$173,MATCH('7 Year Projection'!$A34,Projection!$F$9:$F$173,0),MATCH('7 Year Projection'!J$8,Projection!$F$9:$BE$9,0)),0)} -> 10589.438 | K34: {=IFERROR(INDEX(Projection!$F$9:$BE$173,MATCH('7 Year Projection'!$A34,Projection!$F$9:$F$173,0),MATCH('7 Year Projection'!K$8,Projection!$F$9:$BE$9,0)),0)} -> 10589.438 | L34: {=IFERROR(INDEX(Projection!$F$9:$BE$173,MATCH('7 Year Projection'!$A34,Projection!$F$9:$F$173,0),MATCH('7 Year Projection'!L$8,Projection!$F$9:$BE$9,0)),0)} -> 10589.438 | M34: {=IFERROR(INDEX(Projection!$F$9:$BE$173,MATCH('7 Year Projection'!$A34,Projection!$F$9:$F$173,0),MATCH('7 Year Projection'!M$8,Projection!$F$9:$BE$9,0)),0)} -> 10589.438 | N34: {=IFERROR(INDEX(Projection!$F$9:$BE$173,MATCH('7 Year Projection'!$A34,Projection!$F$9:$F$173,0),MATCH('7 Year Projection'!N$8,Projection!$F$9:$BE$9,0)),0)} -> 10589.438 | ... R34: {=IFERROR(INDEX(Projection!$F$9:$BE$173,MATCH('7 Year Projection'!$A34,Projection!$F$9:$F$173,0),MATCH('7 Year Projection'!R$8,Projection!$F$9:$BE$9,0)),0)} -> 10589.438 | S34: =SUMIF(Projection!$F:$F,'7 Year Projection'!$A34,Projection!BW:BW) -> 127073.25 | T34: =SUMIF(Projection!$F:$F,'7 Year Projection'!$A34,Projection!BX:BX) -> 169431 | U34: =SUMIF(Projection!$F:$F,'7 Year Projection'!$A34,Projection!BY:BY) -> 180858.1 | V34: =SUMIF(Projection!$F:$F,'7 Year Projection'!$A34,Projection!BZ:BZ) -> 203795.44 | W34: =SUMIF(Projection!$F:$F,'7 Year Projection'!$A34,Projection!CA:CA) -> 229641.8 | X34: =SUMIF(Projection!$F:$F,'7 Year Projection'!$A34,Projection!CB:CB) -> 238827.47 | Y34: =SUMIF(Projection!$F:$F,'7 Year Projection'!$A34,Projection!CC:CC) -> 248380.57 | Z34: =SUMIF(Projection!$F:$F,'7 Year Projection'!$A34,Projection!CD:CD) -> 258315.8 | AA34: =SUMIF(Projection!$F:$F,'7 Year Projection'!$A34,Projection!CE:CE) -> 268648.43 | AB34: =SUMIF(Projection!$F:$F,'7 Year Projection'!$A34,Projection!CF:CF) -> 279394.37 | AC34: =SUMIF(Projection!$F:$F,'7 Year Projection'!$A34,Projection!CG:CG) -> 290570.14 | AD34: =SUMIF(Projection!$F:$F,'7 Year Projection'!$A34,Projection!CH:CH) -> 302192.95
A35: 6280 | D35: Insurance | G35: {=IFERROR(INDEX(Projection!$F$9:$BE$173,MATCH('7 Year Projection'!$A35,Projection!$F$9:$F$173,0),MATCH('7 Year Projection'!G$8,Projection!$F$9:$BE$9,0)),0)} -> 2380.6575 | H35: {=IFERROR(INDEX(Projection!$F$9:$BE$173,MATCH('7 Year Projection'!$A35,Projection!$F$9:$F$173,0),MATCH('7 Year Projection'!H$8,Projection!$F$9:$BE$9,0)),0)} -> 2380.6575 | I35: {=IFERROR(INDEX(Projection!$F$9:$BE$173,MATCH('7 Year Projection'!$A35,Projection!$F$9:$F$173,0),MATCH('7 Year Projection'!I$8,Projection!$F$9:$BE$9,0)),0)} -> 2380.6575 | J35: {=IFERROR(INDEX(Projection!$F$9:$BE$173,MATCH('7 Year Projection'!$A35,Projection!$F$9:$F$173,0),MATCH('7 Year Projection'!J$8,Projection!$F$9:$BE$9,0)),0)} -> 2380.6575 | K35: {=IFERROR(INDEX(Projection!$F$9:$BE$173,MATCH('7 Year Projection'!$A35,Projection!$F$9:$F$173,0),MATCH('7 Year Projection'!K$8,Projection!$F$9:$BE$9,0)),0)} -> 2380.6575 | L35: {=IFERROR(INDEX(Projection!$F$9:$BE$173,MATCH('7 Year Projection'!$A35,Projection!$F$9:$F$173,0),MATCH('7 Year Projection'!L$8,Projection!$F$9:$BE$9,0)),0)} -> 2380.6575 | M35: {=IFERROR(INDEX(Projection!$F$9:$BE$173,MATCH('7 Year Projection'!$A35,Projection!$F$9:$F$173,0),MATCH('7 Year Projection'!M$8,Projection!$F$9:$BE$9,0)),0)} -> 2380.6575 | N35: {=IFERROR(INDEX(Projection!$F$9:$BE$173,MATCH('7 Year Projection'!$A35,Projection!$F$9:$F$173,0),MATCH('7 Year Projection'!N$8,Projection!$F$9:$BE$9,0)),0)} -> 2380.6575 | ... R35: {=IFERROR(INDEX(Projection!$F$9:$BE$173,MATCH('7 Year Projection'!$A35,Projection!$F$9:$F$173,0),MATCH('7 Year Projection'!R$8,Projection!$F$9:$BE$9,0)),0)} -> 2380.6575 | S35: =SUMIF(Projection!$F:$F,'7 Year Projection'!$A35,Projection!BW:BW) -> 28567.89 | T35: =SUMIF(Projection!$F:$F,'7 Year Projection'!$A35,Projection!BX:BX) -> 29282.087 | U35: =SUMIF(Projection!$F:$F,'7 Year Projection'!$A35,Projection!BY:BY) -> 30014.139 | V35: =SUMIF(Projection!$F:$F,'7 Year Projection'!$A35,Projection!BZ:BZ) -> 30764.493 | W35: =SUMIF(Projection!$F:$F,'7 Year Projection'!$A35,Projection!CA:CA) -> 31533.605 | X35: =SUMIF(Projection!$F:$F,'7 Year Projection'!$A35,Projection!CB:CB) -> 31848.941 | Y35: =SUMIF(Projection!$F:$F,'7 Year Projection'!$A35,Projection!CC:CC) -> 32167.431 | Z35: =SUMIF(Projection!$F:$F,'7 Year Projection'!$A35,Projection!CD:CD) -> 32489.105 | AA35: =SUMIF(Projection!$F:$F,'7 Year Projection'!$A35,Projection!CE:CE) -> 32813.996 | AB35: =SUMIF(Projection!$F:$F,'7 Year Projection'!$A35,Projection!CF:CF) -> 33142.136 | AC35: =SUMIF(Projection!$F:$F,'7 Year Projection'!$A35,Projection!CG:CG) -> 33473.557 | AD35: =SUMIF(Projection!$F:$F,'7 Year Projection'!$A35,Projection!CH:CH) -> 33808.293
A36: 6801 | D36: Management Fees | F36: =Projection!$H167 -> 0 | G36: {=IFERROR(INDEX(Projection!$F$9:$BE$173,MATCH('7 Year Projection'!$A36,Projection!$F$9:$F$173,0),MATCH('7 Year Projection'!G$8,Projection!$F$9:$BE$9,0)),0)} -> 0 | H36: {=IFERROR(INDEX(Projection!$F$9:$BE$173,MATCH('7 Year Projection'!$A36,Projection!$F$9:$F$173,0),MATCH('7 Year Projection'!H$8,Projection!$F$9:$BE$9,0)),0)} -> 0 | I36: {=IFERROR(INDEX(Projection!$F$9:$BE$173,MATCH('7 Year Projection'!$A36,Projection!$F$9:$F$173,0),MATCH('7 Year Projection'!I$8,Projection!$F$9:$BE$9,0)),0)} -> 0 | J36: {=IFERROR(INDEX(Projection!$F$9:$BE$173,MATCH('7 Year Projection'!$A36,Projection!$F$9:$F$173,0),MATCH('7 Year Projection'!J$8,Projection!$F$9:$BE$9,0)),0)} -> 0 | K36: {=IFERROR(INDEX(Projection!$F$9:$BE$173,MATCH('7 Year Projection'!$A36,Projection!$F$9:$F$173,0),MATCH('7 Year Projection'!K$8,Projection!$F$9:$BE$9,0)),0)} -> 0 | L36: {=IFERROR(INDEX(Projection!$F$9:$BE$173,MATCH('7 Year Projection'!$A36,Projection!$F$9:$F$173,0),MATCH('7 Year Projection'!L$8,Projection!$F$9:$BE$9,0)),0)} -> 0 | M36: {=IFERROR(INDEX(Projection!$F$9:$BE$173,MATCH('7 Year Projection'!$A36,Projection!$F$9:$F$173,0),MATCH('7 Year Projection'!M$8,Projection!$F$9:$BE$9,0)),0)} -> 0 | N36: {=IFERROR(INDEX(Projection!$F$9:$BE$173,MATCH('7 Year Projection'!$A36,Projection!$F$9:$F$173,0),MATCH('7 Year Projection'!N$8,Projection!$F$9:$BE$9,0)),0)} -> 0 | ... R36: {=IFERROR(INDEX(Projection!$F$9:$BE$173,MATCH('7 Year Projection'!$A36,Projection!$F$9:$F$173,0),MATCH('7 Year Projection'!R$8,Projection!$F$9:$BE$9,0)),0)} -> 0 | S36: =SUMIF(Projection!$F:$F,'7 Year Projection'!$A36,Projection!BW:BW) -> 0 | T36: =SUMIF(Projection!$F:$F,'7 Year Projection'!$A36,Projection!BX:BX) -> 0 | U36: =SUMIF(Projection!$F:$F,'7 Year Projection'!$A36,Projection!BY:BY) -> 0 | V36: =SUMIF(Projection!$F:$F,'7 Year Projection'!$A36,Projection!BZ:BZ) -> 0 | W36: =SUMIF(Projection!$F:$F,'7 Year Projection'!$A36,Projection!CA:CA) -> 0 | X36: =SUMIF(Projection!$F:$F,'7 Year Projection'!$A36,Projection!CB:CB) -> 0 | Y36: =SUMIF(Projection!$F:$F,'7 Year Projection'!$A36,Projection!CC:CC) -> 0 | Z36: =SUMIF(Projection!$F:$F,'7 Year Projection'!$A36,Projection!CD:CD) -> 0 | AA36: =SUMIF(Projection!$F:$F,'7 Year Projection'!$A36,Projection!CE:CE) -> 0 | AB36: =SUMIF(Projection!$F:$F,'7 Year Projection'!$A36,Projection!CF:CF) -> 0 | AC36: =SUMIF(Projection!$F:$F,'7 Year Projection'!$A36,Projection!CG:CG) -> 0 | AD36: =SUMIF(Projection!$F:$F,'7 Year Projection'!$A36,Projection!CH:CH) -> 0 | AE36: =SUMIF(Projection!$F:$F,'7 Year Projection'!$A36,Projection!CI:CI) -> 0 | AF36: =SUMIF(Projection!$F:$F,'7 Year Projection'!$A36,Projection!CJ:CJ) -> 0 | AG36: =SUMIF(Projection!$F:$F,'7 Year Projection'!$A36,Projection!CK:CK) -> 0
A37: 7550 | D37: Land Lease | G37: {=IFERROR(INDEX(Projection!$F$9:$BE$173,MATCH('7 Year Projection'!$A37,Projection!$F$9:$F$173,0),MATCH('7 Year Projection'!G$8,Projection!$F$9:$BE$9,0)),0)} -> 0 | H37: {=IFERROR(INDEX(Projection!$F$9:$BE$173,MATCH('7 Year Projection'!$A37,Projection!$F$9:$F$173,0),MATCH('7 Year Projection'!H$8,Projection!$F$9:$BE$9,0)),0)} -> 0 | I37: {=IFERROR(INDEX(Projection!$F$9:$BE$173,MATCH('7 Year Projection'!$A37,Projection!$F$9:$F$173,0),MATCH('7 Year Projection'!I$8,Projection!$F$9:$BE$9,0)),0)} -> 0 | J37: {=IFERROR(INDEX(Projection!$F$9:$BE$173,MATCH('7 Year Projection'!$A37,Projection!$F$9:$F$173,0),MATCH('7 Year Projection'!J$8,Projection!$F$9:$BE$9,0)),0)} -> 0 | K37: {=IFERROR(INDEX(Projection!$F$9:$BE$173,MATCH('7 Year Projection'!$A37,Projection!$F$9:$F$173,0),MATCH('7 Year Projection'!K$8,Projection!$F$9:$BE$9,0)),0)} -> 0 | L37: {=IFERROR(INDEX(Projection!$F$9:$BE$173,MATCH('7 Year Projection'!$A37,Projection!$F$9:$F$173,0),MATCH('7 Year Projection'!L$8,Projection!$F$9:$BE$9,0)),0)} -> 0 | M37: {=IFERROR(INDEX(Projection!$F$9:$BE$173,MATCH('7 Year Projection'!$A37,Projection!$F$9:$F$173,0),MATCH('7 Year Projection'!M$8,Projection!$F$9:$BE$9,0)),0)} -> 0 | N37: {=IFERROR(INDEX(Projection!$F$9:$BE$173,MATCH('7 Year Projection'!$A37,Projection!$F$9:$F$173,0),MATCH('7 Year Projection'!N$8,Projection!$F$9:$BE$9,0)),0)} -> 0 | ... R37: {=IFERROR(INDEX(Projection!$F$9:$BE$173,MATCH('7 Year Projection'!$A37,Projection!$F$9:$F$173,0),MATCH('7 Year Projection'!R$8,Projection!$F$9:$BE$9,0)),0)} -> 0 | S37: =SUMIF(Projection!$F:$F,'7 Year Projection'!$A37,Projection!BW:BW) -> 0 | T37: =SUMIF(Projection!$F:$F,'7 Year Projection'!$A37,Projection!BX:BX) -> 0 | U37: =SUMIF(Projection!$F:$F,'7 Year Projection'!$A37,Projection!BY:BY) -> 0 | V37: =SUMIF(Projection!$F:$F,'7 Year Projection'!$A37,Projection!BZ:BZ) -> 0 | W37: =SUMIF(Projection!$F:$F,'7 Year Projection'!$A37,Projection!CA:CA) -> 0 | X37: =SUMIF(Projection!$F:$F,'7 Year Projection'!$A37,Projection!CB:CB) -> 0 | Y37: =SUMIF(Projection!$F:$F,'7 Year Projection'!$A37,Projection!CC:CC) -> 0 | Z37: =SUMIF(Projection!$F:$F,'7 Year Projection'!$A37,Projection!CD:CD) -> 0 | AA37: =SUMIF(Projection!$F:$F,'7 Year Projection'!$A37,Projection!CE:CE) -> 0 | AB37: =SUMIF(Projection!$F:$F,'7 Year Projection'!$A37,Projection!CF:CF) -> 0 | AC37: =SUMIF(Projection!$F:$F,'7 Year Projection'!$A37,Projection!CG:CG) -> 0 | AD37: =SUMIF(Projection!$F:$F,'7 Year Projection'!$A37,Projection!CH:CH) -> 0
A38: PropertyExp | C38: Property Expenses | G38: =SUM(G28:G37) -> 31527.537 | H38: =SUM(H28:H37) -> 33042.382 | I38: =SUM(I28:I37) -> 34372.564 | J38: =SUM(J28:J37) -> 29571.203 | K38: =SUM(K28:K37) -> 28707.292 | L38: =SUM(L28:L37) -> 28494.725 | M38: =SUM(M28:M37) -> 29382.017 | N38: =SUM(N28:N37) -> 29484.906 | ... AD38: =SUM(AD28:AD37) -> 685264.67 | AE38: =SUM(AE28:AE36) -> 358256.48 | AF38: =SUM(AF28:AF36) -> 367484.8 | AG38: =SUM(AG28:AG36) -> 376954.72
AE39: =AE38/AD38-1 -> -0.47719985 | AF39: =AF38/AE38-1 -> 0.025758998 | AG39: =AG38/AF38-1 -> 0.025769535
A40: PropertyProfit | C40: Property NOI | G40: =G26-G38 -> -27796.475 | H40: =H26-H38 -> -25875.266 | I40: =I26-I38 -> -22274.943 | J40: =J26-J38 -> -12314.236 | K40: =K26-K38 -> -3008.6496 | L40: =L26-L38 -> 4522.9872 | M40: =M26-M38 -> 10011.46 | N40: =N26-N38 -> 14382.008 | ... AG40: =AG26-AG38 -> 2913775.5
A42: Total Debt Service | C42: Total Debt Service | G42: {=IFERROR(INDEX(Projection!$F$9:$BE$179,MATCH('7 Year Projection'!$A42,Projection!$F$9:$F$179,0),MATCH('7 Year Projection'!G$8,Projection!$F$9:$BE$9,0)),0)} -> 71588.876 | H42: {=IFERROR(INDEX(Projection!$F$9:$BE$179,MATCH('7 Year Projection'!$A42,Projection!$F$9:$F$179,0),MATCH('7 Year Projection'!H$8,Projection!$F$9:$BE$9,0)),0)} -> 71588.876 | I42: {=IFERROR(INDEX(Projection!$F$9:$BE$179,MATCH('7 Year Projection'!$A42,Projection!$F$9:$F$179,0),MATCH('7 Year Projection'!I$8,Projection!$F$9:$BE$9,0)),0)} -> 71588.876 | J42: {=IFERROR(INDEX(Projection!$F$9:$BE$179,MATCH('7 Year Projection'!$A42,Projection!$F$9:$F$179,0),MATCH('7 Year Projection'!J$8,Projection!$F$9:$BE$9,0)),0)} -> 71588.876 | K42: {=IFERROR(INDEX(Projection!$F$9:$BE$179,MATCH('7 Year Projection'!$A42,Projection!$F$9:$F$179,0),MATCH('7 Year Projection'!K$8,Projection!$F$9:$BE$9,0)),0)} -> 71588.876 | L42: {=IFERROR(INDEX(Projection!$F$9:$BE$179,MATCH('7 Year Projection'!$A42,Projection!$F$9:$F$179,0),MATCH('7 Year Projection'!L$8,Projection!$F$9:$BE$9,0)),0)} -> 71588.876 | M42: {=IFERROR(INDEX(Projection!$F$9:$BE$179,MATCH('7 Year Projection'!$A42,Projection!$F$9:$F$179,0),MATCH('7 Year Projection'!M$8,Projection!$F$9:$BE$9,0)),0)} -> 71588.876 | N42: {=IFERROR(INDEX(Projection!$F$9:$BE$179,MATCH('7 Year Projection'!$A42,Projection!$F$9:$F$179,0),MATCH('7 Year Projection'!N$8,Projection!$F$9:$BE$9,0)),0)} -> 71588.876 | ... R42: {=IFERROR(INDEX(Projection!$F$9:$BE$179,MATCH('7 Year Projection'!$A42,Projection!$F$9:$F$179,0),MATCH('7 Year Projection'!R$8,Projection!$F$9:$BE$9,0)),0)} -> 71588.876 | S42: =SUMIF(Projection!$F:$F,'7 Year Projection'!$A42,Projection!BW:BW) -> 859066.51 | T42: =SUMIF(Projection!$F:$F,'7 Year Projection'!$A42,Projection!BX:BX) -> 859066.51 | U42: =SUMIF(Projection!$F:$F,'7 Year Projection'!$A42,Projection!BY:BY) -> 859066.51 | V42: =SUMIF(Projection!$F:$F,'7 Year Projection'!$A42,Projection!BZ:BZ) -> 859066.51 | W42: =SUMIF(Projection!$F:$F,'7 Year Projection'!$A42,Projection!CA:CA) -> 859066.51 | X42: =SUMIF(Projection!$F:$F,'7 Year Projection'!$A42,Projection!CB:CB) -> 859066.51 | Y42: =SUMIF(Projection!$F:$F,'7 Year Projection'!$A42,Projection!CC:CC) -> 859066.51 | Z42: =SUMIF(Projection!$F:$F,'7 Year Projection'!$A42,Projection!CD:CD) -> 859066.51 | AA42: =SUMIF(Projection!$F:$F,'7 Year Projection'!$A42,Projection!CE:CE) -> 859066.51 | AB42: =SUMIF(Projection!$F:$F,'7 Year Projection'!$A42,Projection!CF:CF) -> 859066.51 | AC42: =SUMIF(Projection!$F:$F,'7 Year Projection'!$A42,Projection!CG:CG) -> 859066.51 | AD42: =SUMIF(Projection!$F:$F,'7 Year Projection'!$A42,Projection!CH:CH) -> 859066.51 | AE42: =SUMIF(Projection!$F:$F,'7 Year Projection'!$A42,Projection!CI:CI) -> 859066.51 | AF42: =SUMIF(Projection!$F:$F,'7 Year Projection'!$A42,Projection!CJ:CJ) -> 859066.51 | AG42: =SUMIF(Projection!$F:$F,'7 Year Projection'!$A42,Projection!CK:CK) -> 859066.51
A44: Levered Cash Flow | C44: Levered Cash Flow | G44: {=IFERROR(INDEX(Projection!$F$9:$BE$179,MATCH('7 Year Projection'!$A44,Projection!$F$9:$F$179,0),MATCH('7 Year Projection'!G$8,Projection!$F$9:$BE$9,0)),0)} -> -99385.351 | H44: {=IFERROR(INDEX(Projection!$F$9:$BE$179,MATCH('7 Year Projection'!$A44,Projection!$F$9:$F$179,0),MATCH('7 Year Projection'!H$8,Projection!$F$9:$BE$9,0)),0)} -> -97464.142 | I44: {=IFERROR(INDEX(Projection!$F$9:$BE$179,MATCH('7 Year Projection'!$A44,Projection!$F$9:$F$179,0),MATCH('7 Year Projection'!I$8,Projection!$F$9:$BE$9,0)),0)} -> -90901.224 | J44: {=IFERROR(INDEX(Projection!$F$9:$BE$179,MATCH('7 Year Projection'!$A44,Projection!$F$9:$F$179,0),MATCH('7 Year Projection'!J$8,Projection!$F$9:$BE$9,0)),0)} -> -82421.814 | K44: {=IFERROR(INDEX(Projection!$F$9:$BE$179,MATCH('7 Year Projection'!$A44,Projection!$F$9:$F$179,0),MATCH('7 Year Projection'!K$8,Projection!$F$9:$BE$9,0)),0)} -> -73116.228 | L44: {=IFERROR(INDEX(Projection!$F$9:$BE$179,MATCH('7 Year Projection'!$A44,Projection!$F$9:$F$179,0),MATCH('7 Year Projection'!L$8,Projection!$F$9:$BE$9,0)),0)} -> -65584.591 | M44: {=IFERROR(INDEX(Projection!$F$9:$BE$179,MATCH('7 Year Projection'!$A44,Projection!$F$9:$F$179,0),MATCH('7 Year Projection'!M$8,Projection!$F$9:$BE$9,0)),0)} -> -60096.118 | N44: {=IFERROR(INDEX(Projection!$F$9:$BE$179,MATCH('7 Year Projection'!$A44,Projection!$F$9:$F$179,0),MATCH('7 Year Projection'!N$8,Projection!$F$9:$BE$9,0)),0)} -> -55725.57 | ... R44: {=IFERROR(INDEX(Projection!$F$9:$BE$179,MATCH('7 Year Projection'!$A44,Projection!$F$9:$F$179,0),MATCH('7 Year Projection'!R$8,Projection!$F$9:$BE$9,0)),0)} -> -43197.805 | S44: =SUMIF(Projection!$F:$F,'7 Year Projection'!$A44,Projection!BW:BW) -> -810998.64 | T44: =SUMIF(Projection!$F:$F,'7 Year Projection'!$A44,Projection!BX:BX) -> -117324.82 | U44: =SUMIF(Projection!$F:$F,'7 Year Projection'!$A44,Projection!BY:BY) -> 549544.21 | V44: =SUMIF(Projection!$F:$F,'7 Year Projection'!$A44,Projection!BZ:BZ) -> 826295.75 | W44: =SUMIF(Projection!$F:$F,'7 Year Projection'!$A44,Projection!CA:CA) -> 886469.75 | X44: =SUMIF(Projection!$F:$F,'7 Year Projection'!$A44,Projection!CB:CB) -> 961179.34 | Y44: =SUMIF(Projection!$F:$F,'7 Year Projection'!$A44,Projection!CC:CC) -> 1038985.3 | Z44: =SUMIF(Projection!$F:$F,'7 Year Projection'!$A44,Projection!CD:CD) -> 1120014.1 | AA44: =SUMIF(Projection!$F:$F,'7 Year Projection'!$A44,Projection!CE:CE) -> 1204397.3 | AB44: =SUMIF(Projection!$F:$F,'7 Year Projection'!$A44,Projection!CF:CF) -> 1292271.6 | AC44: =SUMIF(Projection!$F:$F,'7 Year Projection'!$A44,Projection!CG:CG) -> 1383779.6 | AD44: =SUMIF(Projection!$F:$F,'7 Year Projection'!$A44,Projection!CH:CH) -> 1479069.3 | AE44: =SUMIF(Projection!$F:$F,'7 Year Projection'!$A44,Projection!CI:CI) -> 1578294.9 | AF44: =SUMIF(Projection!$F:$F,'7 Year Projection'!$A44,Projection!CJ:CJ) -> 1681616.9 | AG44: =SUMIF(Projection!$F:$F,'7 Year Projection'!$A44,Projection!CK:CK) -> 1789202
A46: Beginning Loan Balance | G46: {=IFERROR(INDEX(Projection!$F$9:$BE$179,MATCH('7 Year Projection'!$A46,Projection!$F$9:$F$179,0),MATCH('7 Year Projection'!G$8,Projection!$F$9:$BE$9,0)),0)} -> 9687379 | H46: {=IFERROR(INDEX(Projection!$F$9:$BE$179,MATCH('7 Year Projection'!$A46,Projection!$F$9:$F$179,0),MATCH('7 Year Projection'!H$8,Projection!$F$9:$BE$9,0)),0)} -> 9676336.2 | I46: {=IFERROR(INDEX(Projection!$F$9:$BE$179,MATCH('7 Year Projection'!$A46,Projection!$F$9:$F$179,0),MATCH('7 Year Projection'!I$8,Projection!$F$9:$BE$9,0)),0)} -> 9665224.5 | J46: {=IFERROR(INDEX(Projection!$F$9:$BE$179,MATCH('7 Year Projection'!$A46,Projection!$F$9:$F$179,0),MATCH('7 Year Projection'!J$8,Projection!$F$9:$BE$9,0)),0)} -> 9654043.2 | K46: {=IFERROR(INDEX(Projection!$F$9:$BE$179,MATCH('7 Year Projection'!$A46,Projection!$F$9:$F$179,0),MATCH('7 Year Projection'!K$8,Projection!$F$9:$BE$9,0)),0)} -> 9642792.1 | L46: {=IFERROR(INDEX(Projection!$F$9:$BE$179,MATCH('7 Year Projection'!$A46,Projection!$F$9:$F$179,0),MATCH('7 Year Projection'!L$8,Projection!$F$9:$BE$9,0)),0)} -> 9631470.7 | M46: {=IFERROR(INDEX(Projection!$F$9:$BE$179,MATCH('7 Year Projection'!$A46,Projection!$F$9:$F$179,0),MATCH('7 Year Projection'!M$8,Projection!$F$9:$BE$9,0)),0)} -> 9620078.5 | N46: {=IFERROR(INDEX(Projection!$F$9:$BE$179,MATCH('7 Year Projection'!$A46,Projection!$F$9:$F$179,0),MATCH('7 Year Projection'!N$8,Projection!$F$9:$BE$9,0)),0)} -> 9608615.1 | ... R46: {=IFERROR(INDEX(Projection!$F$9:$BE$179,MATCH('7 Year Projection'!$A46,Projection!$F$9:$F$179,0),MATCH('7 Year Projection'!R$8,Projection!$F$9:$BE$9,0)),0)} -> 9562040.6 | S46: =SUMIF(Projection!$F:$F,'7 Year Projection'!$A46,Projection!BW:BW) -> 9687379 | T46: =SUMIF(Projection!$F:$F,'7 Year Projection'!$A46,Projection!BX:BX) -> 9550214.5 | U46: =SUMIF(Projection!$F:$F,'7 Year Projection'!$A46,Projection!BY:BY) -> 9402401.6 | V46: =SUMIF(Projection!$F:$F,'7 Year Projection'!$A46,Projection!BZ:BZ) -> 9243113.6 | W46: =SUMIF(Projection!$F:$F,'7 Year Projection'!$A46,Projection!CA:CA) -> 9071459.7 | X46: =SUMIF(Projection!$F:$F,'7 Year Projection'!$A46,Projection!CB:CB) -> 8886479.8 | Y46: =SUMIF(Projection!$F:$F,'7 Year Projection'!$A46,Projection!CC:CC) -> 8687139.4 | Z46: =SUMIF(Projection!$F:$F,'7 Year Projection'!$A46,Projection!CD:CD) -> 8472323.7 | AA46: =SUMIF(Projection!$F:$F,'7 Year Projection'!$A46,Projection!CE:CE) -> 8240831.4 | AB46: =SUMIF(Projection!$F:$F,'7 Year Projection'!$A46,Projection!CF:CF) -> 7991367.6 | AC46: =SUMIF(Projection!$F:$F,'7 Year Projection'!$A46,Projection!CG:CG) -> 7722537.4 | AD46: =SUMIF(Projection!$F:$F,'7 Year Projection'!$A46,Projection!CH:CH) -> 7432837.2 | AE46: =SUMIF(Projection!$F:$F,'7 Year Projection'!$A46,Projection!CI:CI) -> 7120646.7 | AF46: =SUMIF(Projection!$F:$F,'7 Year Projection'!$A46,Projection!CJ:CJ) -> 6784220.2 | AG46: =SUMIF(Projection!$F:$F,'7 Year Projection'!$A46,Projection!CK:CK) -> 6421675.9
A47: Interest Payment | G47: {=IFERROR(INDEX(Projection!$F$9:$BE$179,MATCH('7 Year Projection'!$A47,Projection!$F$9:$F$179,0),MATCH('7 Year Projection'!G$8,Projection!$F$9:$BE$9,0)),0)} -> 60546.119 | H47: {=IFERROR(INDEX(Projection!$F$9:$BE$179,MATCH('7 Year Projection'!$A47,Projection!$F$9:$F$179,0),MATCH('7 Year Projection'!H$8,Projection!$F$9:$BE$9,0)),0)} -> 60477.102 | I47: {=IFERROR(INDEX(Projection!$F$9:$BE$179,MATCH('7 Year Projection'!$A47,Projection!$F$9:$F$179,0),MATCH('7 Year Projection'!I$8,Projection!$F$9:$BE$9,0)),0)} -> 60407.653 | J47: {=IFERROR(INDEX(Projection!$F$9:$BE$179,MATCH('7 Year Projection'!$A47,Projection!$F$9:$F$179,0),MATCH('7 Year Projection'!J$8,Projection!$F$9:$BE$9,0)),0)} -> 60337.77 | K47: {=IFERROR(INDEX(Projection!$F$9:$BE$179,MATCH('7 Year Projection'!$A47,Projection!$F$9:$F$179,0),MATCH('7 Year Projection'!K$8,Projection!$F$9:$BE$9,0)),0)} -> 60267.451 | L47: {=IFERROR(INDEX(Projection!$F$9:$BE$179,MATCH('7 Year Projection'!$A47,Projection!$F$9:$F$179,0),MATCH('7 Year Projection'!L$8,Projection!$F$9:$BE$9,0)),0)} -> 60196.692 | M47: {=IFERROR(INDEX(Projection!$F$9:$BE$179,MATCH('7 Year Projection'!$A47,Projection!$F$9:$F$179,0),MATCH('7 Year Projection'!M$8,Projection!$F$9:$BE$9,0)),0)} -> 60125.491 | N47: {=IFERROR(INDEX(Projection!$F$9:$BE$179,MATCH('7 Year Projection'!$A47,Projection!$F$9:$F$179,0),MATCH('7 Year Projection'!N$8,Projection!$F$9:$BE$9,0)),0)} -> 60053.845 | ... R47: {=IFERROR(INDEX(Projection!$F$9:$BE$179,MATCH('7 Year Projection'!$A47,Projection!$F$9:$F$179,0),MATCH('7 Year Projection'!R$8,Projection!$F$9:$BE$9,0)),0)} -> 59762.754 | S47: =SUMIF(Projection!$F:$F,'7 Year Projection'!$A47,Projection!BW:BW) -> 721902.04 | T47: =SUMIF(Projection!$F:$F,'7 Year Projection'!$A47,Projection!BX:BX) -> 711253.61 | U47: =SUMIF(Projection!$F:$F,'7 Year Projection'!$A47,Projection!BY:BY) -> 699778.51 | V47: =SUMIF(Projection!$F:$F,'7 Year Projection'!$A47,Projection!BZ:BZ) -> 687412.56 | W47: =SUMIF(Projection!$F:$F,'7 Year Projection'!$A47,Projection!CA:CA) -> 674086.62 | X47: =SUMIF(Projection!$F:$F,'7 Year Projection'!$A47,Projection!CB:CB) -> 659726.15 | Y47: =SUMIF(Projection!$F:$F,'7 Year Projection'!$A47,Projection!CC:CC) -> 644250.84 | Z47: =SUMIF(Projection!$F:$F,'7 Year Projection'!$A47,Projection!CD:CD) -> 627574.14 | AA47: =SUMIF(Projection!$F:$F,'7 Year Projection'!$A47,Projection!CE:CE) -> 609602.79 | AB47: =SUMIF(Projection!$F:$F,'7 Year Projection'!$A47,Projection!CF:CF) -> 590236.27 | AC47: =SUMIF(Projection!$F:$F,'7 Year Projection'!$A47,Projection!CG:CG) -> 569366.28 | AD47: =SUMIF(Projection!$F:$F,'7 Year Projection'!$A47,Projection!CH:CH) -> 546876.1 | AE47: =SUMIF(Projection!$F:$F,'7 Year Projection'!$A47,Projection!CI:CI) -> 522639.95 | AF47: =SUMIF(Projection!$F:$F,'7 Year Projection'!$A47,Projection!CJ:CJ) -> 496522.28 | AG47: =SUMIF(Projection!$F:$F,'7 Year Projection'!$A47,Projection!CK:CK) -> 468377.03
A48: Principal Payment | G48: {=IFERROR(INDEX(Projection!$F$9:$BE$179,MATCH('7 Year Projection'!$A48,Projection!$F$9:$F$179,0),MATCH('7 Year Projection'!G$8,Projection!$F$9:$BE$9,0)),0)} -> 11042.757 | H48: {=IFERROR(INDEX(Projection!$F$9:$BE$179,MATCH('7 Year Projection'!$A48,Projection!$F$9:$F$179,0),MATCH('7 Year Projection'!H$8,Projection!$F$9:$BE$9,0)),0)} -> 11111.775 | I48: {=IFERROR(INDEX(Projection!$F$9:$BE$179,MATCH('7 Year Projection'!$A48,Projection!$F$9:$F$179,0),MATCH('7 Year Projection'!I$8,Projection!$F$9:$BE$9,0)),0)} -> 11181.223 | J48: {=IFERROR(INDEX(Projection!$F$9:$BE$179,MATCH('7 Year Projection'!$A48,Projection!$F$9:$F$179,0),MATCH('7 Year Projection'!J$8,Projection!$F$9:$BE$9,0)),0)} -> 11251.106 | K48: {=IFERROR(INDEX(Projection!$F$9:$BE$179,MATCH('7 Year Projection'!$A48,Projection!$F$9:$F$179,0),MATCH('7 Year Projection'!K$8,Projection!$F$9:$BE$9,0)),0)} -> 11321.425 | L48: {=IFERROR(INDEX(Projection!$F$9:$BE$179,MATCH('7 Year Projection'!$A48,Projection!$F$9:$F$179,0),MATCH('7 Year Projection'!L$8,Projection!$F$9:$BE$9,0)),0)} -> 11392.184 | M48: {=IFERROR(INDEX(Projection!$F$9:$BE$179,MATCH('7 Year Projection'!$A48,Projection!$F$9:$F$179,0),MATCH('7 Year Projection'!M$8,Projection!$F$9:$BE$9,0)),0)} -> 11463.385 | N48: {=IFERROR(INDEX(Projection!$F$9:$BE$179,MATCH('7 Year Projection'!$A48,Projection!$F$9:$F$179,0),MATCH('7 Year Projection'!N$8,Projection!$F$9:$BE$9,0)),0)} -> 11535.032 | ... R48: {=IFERROR(INDEX(Projection!$F$9:$BE$179,MATCH('7 Year Projection'!$A48,Projection!$F$9:$F$179,0),MATCH('7 Year Projection'!R$8,Projection!$F$9:$BE$9,0)),0)} -> 11826.122 | S48: =SUMIF(Projection!$F:$F,'7 Year Projection'!$A48,Projection!BW:BW) -> 137164.47 | T48: =SUMIF(Projection!$F:$F,'7 Year Projection'!$A48,Projection!BX:BX) -> 147812.91 | U48: =SUMIF(Projection!$F:$F,'7 Year Projection'!$A48,Projection!BY:BY) -> 159288.01 | V48: =SUMIF(Projection!$F:$F,'7 Year Projection'!$A48,Projection!BZ:BZ) -> 171653.95 | W48: =SUMIF(Projection!$F:$F,'7 Year Projection'!$A48,Projection!CA:CA) -> 184979.89 | X48: =SUMIF(Projection!$F:$F,'7 Year Projection'!$A48,Projection!CB:CB) -> 199340.36 | Y48: =SUMIF(Projection!$F:$F,'7 Year Projection'!$A48,Projection!CC:CC) -> 214815.67 | Z48: =SUMIF(Projection!$F:$F,'7 Year Projection'!$A48,Projection!CD:CD) -> 231492.37 | AA48: =SUMIF(Projection!$F:$F,'7 Year Projection'!$A48,Projection!CE:CE) -> 249463.73 | AB48: =SUMIF(Projection!$F:$F,'7 Year Projection'!$A48,Projection!CF:CF) -> 268830.24 | AC48: =SUMIF(Projection!$F:$F,'7 Year Projection'!$A48,Projection!CG:CG) -> 289700.23 | AD48: =SUMIF(Projection!$F:$F,'7 Year Projection'!$A48,Projection!CH:CH) -> 312190.42 | AE48: =SUMIF(Projection!$F:$F,'7 Year Projection'!$A48,Projection!CI:CI) -> 336426.57 | AF48: =SUMIF(Projection!$F:$F,'7 Year Projection'!$A48,Projection!CJ:CJ) -> 362544.24 | AG48: =SUMIF(Projection!$F:$F,'7 Year Projection'!$A48,Projection!CK:CK) -> 390689.49
A49: Ending Loan Balance | G49: {=IFERROR(INDEX(Projection!$F$9:$BE$179,MATCH('7 Year Projection'!$A49,Projection!$F$9:$F$179,0),MATCH('7 Year Projection'!G$8,Projection!$F$9:$BE$9,0)),0)} -> 9676336.2 | H49: {=IFERROR(INDEX(Projection!$F$9:$BE$179,MATCH('7 Year Projection'!$A49,Projection!$F$9:$F$179,0),MATCH('7 Year Projection'!H$8,Projection!$F$9:$BE$9,0)),0)} -> 9665224.5 | I49: {=IFERROR(INDEX(Projection!$F$9:$BE$179,MATCH('7 Year Projection'!$A49,Projection!$F$9:$F$179,0),MATCH('7 Year Projection'!I$8,Projection!$F$9:$BE$9,0)),0)} -> 9654043.2 | J49: {=IFERROR(INDEX(Projection!$F$9:$BE$179,MATCH('7 Year Projection'!$A49,Projection!$F$9:$F$179,0),MATCH('7 Year Projection'!J$8,Projection!$F$9:$BE$9,0)),0)} -> 9642792.1 | K49: {=IFERROR(INDEX(Projection!$F$9:$BE$179,MATCH('7 Year Projection'!$A49,Projection!$F$9:$F$179,0),MATCH('7 Year Projection'!K$8,Projection!$F$9:$BE$9,0)),0)} -> 9631470.7 | L49: {=IFERROR(INDEX(Projection!$F$9:$BE$179,MATCH('7 Year Projection'!$A49,Projection!$F$9:$F$179,0),MATCH('7 Year Projection'!L$8,Projection!$F$9:$BE$9,0)),0)} -> 9620078.5 | M49: {=IFERROR(INDEX(Projection!$F$9:$BE$179,MATCH('7 Year Projection'!$A49,Projection!$F$9:$F$179,0),MATCH('7 Year Projection'!M$8,Projection!$F$9:$BE$9,0)),0)} -> 9608615.1 | N49: {=IFERROR(INDEX(Projection!$F$9:$BE$179,MATCH('7 Year Projection'!$A49,Projection!$F$9:$F$179,0),MATCH('7 Year Projection'!N$8,Projection!$F$9:$BE$9,0)),0)} -> 9597080.1 | ... R49: {=IFERROR(INDEX(Projection!$F$9:$BE$179,MATCH('7 Year Projection'!$A49,Projection!$F$9:$F$179,0),MATCH('7 Year Projection'!R$8,Projection!$F$9:$BE$9,0)),0)} -> 9550214.5 | S49: =SUMIF(Projection!$F:$F,'7 Year Projection'!$A49,Projection!BW:BW) -> 9550214.5 | T49: =SUMIF(Projection!$F:$F,'7 Year Projection'!$A49,Projection!BX:BX) -> 9402401.6 | U49: =SUMIF(Projection!$F:$F,'7 Year Projection'!$A49,Projection!BY:BY) -> 9243113.6 | V49: =SUMIF(Projection!$F:$F,'7 Year Projection'!$A49,Projection!BZ:BZ) -> 9071459.7 | W49: =SUMIF(Projection!$F:$F,'7 Year Projection'!$A49,Projection!CA:CA) -> 8886479.8 | X49: =SUMIF(Projection!$F:$F,'7 Year Projection'!$A49,Projection!CB:CB) -> 8687139.4 | Y49: =SUMIF(Projection!$F:$F,'7 Year Projection'!$A49,Projection!CC:CC) -> 8472323.7 | Z49: =SUMIF(Projection!$F:$F,'7 Year Projection'!$A49,Projection!CD:CD) -> 8240831.4 | AA49: =SUMIF(Projection!$F:$F,'7 Year Projection'!$A49,Projection!CE:CE) -> 7991367.6 | AB49: =SUMIF(Projection!$F:$F,'7 Year Projection'!$A49,Projection!CF:CF) -> 7722537.4 | AC49: =SUMIF(Projection!$F:$F,'7 Year Projection'!$A49,Projection!CG:CG) -> 7432837.2 | AD49: =SUMIF(Projection!$F:$F,'7 Year Projection'!$A49,Projection!CH:CH) -> 7120646.7 | AE49: =SUMIF(Projection!$F:$F,'7 Year Projection'!$A49,Projection!CI:CI) -> 6784220.2 | AF49: =SUMIF(Projection!$F:$F,'7 Year Projection'!$A49,Projection!CJ:CJ) -> 6421675.9 | AG49: =SUMIF(Projection!$F:$F,'7 Year Projection'!$A49,Projection!CK:CK) -> 6030986.5
C50: DSCR | G50: =G40/G42 -> -0.38827925 | H50: =H40/H42 -> -0.36144254 | I50: =I40/I42 -> -0.3111509 | J50: =J40/J42 -> -0.17201326 | K50: =K40/K42 -> -0.042026775 | L50: =L40/L42 -> 0.063180028 | M50: =M40/M42 -> 0.13984658 | N50: =N40/N42 -> 0.20089724 | ... R50: =R40/R42 -> 0.39658495 | S50: =IFERROR(S40/S42,"") -> 0.038710497 | T50: =IFERROR(T40/T42,"") -> 0.84575336 | U50: =IFERROR(U40/U42,"") -> 1.6215832 | V50: =IFERROR(V40/V42,"") -> 1.9432841 | W50: =IFERROR(W40/W42,"") -> 2.0128657 | X50: =IFERROR(X40/X42,"") -> 2.0993559 | Y50: =IFERROR(Y40/Y42,"") -> 2.1894385 | Z50: =IFERROR(Z40/Z42,"") -> 2.2832605 | ... AG50: =IFERROR(AG40/AG42,"") -> 3.3917927
C51: Cap Rate | S51: =S$40/(Inputs!$C$45*(1+Inputs!$C$34)) -> 0.0021455037 | T51: =T$40/(Inputs!$C$45*(1+Inputs!$C$34)) -> 0.04687532 | U51: =U$40/(Inputs!$C$45*(1+Inputs!$C$34)) -> 0.089875176 | V51: =V$40/(Inputs!$C$45*(1+Inputs!$C$34)) -> 0.10770524 | W51: =W$40/(Inputs!$C$45*(1+Inputs!$C$34)) -> 0.11156175 | X51: =X$40/(Inputs!$C$45*(1+Inputs!$C$34)) -> 0.11635541 | Y51: =Y$40/(Inputs!$C$45*(1+Inputs!$C$34)) -> 0.12134818 | Z51: =Z$40/(Inputs!$C$45*(1+Inputs!$C$34)) -> 0.1265482 | ... AG51: =AG$40/(Inputs!$C$45*(1+Inputs!$C$34)) -> 0.18798786
C52: Cash on Cash Return | S52: =(S$44/(Inputs!$C$45-Inputs!$C$46))*100 -> -15.547449 | T52: =(T$44/(Inputs!$C$45-Inputs!$C$46))*100 -> -2.2492044 | U52: =(U$44/(Inputs!$C$45-Inputs!$C$46))*100 -> 10.535173 | V52: =(V$44/(Inputs!$C$45-Inputs!$C$46))*100 -> 15.840706 | W52: =(W$44/(Inputs!$C$45-Inputs!$C$46))*100 -> 16.994287 | X52: =(X$44/(Inputs!$C$45-Inputs!$C$46))*100 -> 18.426525 | Y52: =(Y$44/(Inputs!$C$45-Inputs!$C$46))*100 -> 19.918124 | Z52: =(Z$44/(Inputs!$C$45-Inputs!$C$46))*100 -> 21.471507 | ... AG52: =(AG$44/(Inputs!$C$45-Inputs!$C$46))*100 -> 34.300338
C53: Yield on Cash | S53: =S44/Inputs!$C$55 -> -0.14853377 | T53: =T44/Inputs!$C$55 -> -0.02148795 | U53: =U44/Inputs!$C$55 -> 0.1006486 | V53: =V44/Inputs!$C$55 -> 0.15133543 | W53: =W44/Inputs!$C$55 -> 0.16235625 | X53: =X44/Inputs!$C$55 -> 0.17603925 | Y53: =Y44/Inputs!$C$55 -> 0.19028936 | Z53: =Z44/Inputs!$C$55 -> 0.20512972 | ... AD53: =AD44/Inputs!$C$55 -> 0.27089039

Sheet 7 Year Projection-Expanded
L3: =CONCATENATE(Inputs!C3," ",Inputs!C4,", ",Inputs!C5," ",Inputs!C6) -> 250 Dolson Avenue Middletown, New York 10940
J4: Total Sq. Feet: | K4: =Projection!H3 -> 105807
J5: Total Units: | K5: =Projection!H4 -> 684
A8: GL Acct | I8: =EOMONTH(Inputs!$C$9,0) -> 46053 | J8: =EOMONTH(I8,1) -> 46081 | K8: =EOMONTH(J8,1) -> 46112 | L8: =EOMONTH(K8,1) -> 46142 | M8: =EOMONTH(L8,1) -> 46173 | N8: =EOMONTH(M8,1) -> 46203 | O8: =EOMONTH(N8,1) -> 46234 | P8: =EOMONTH(O8,1) -> 46265 | Q8: =EOMONTH(P8,1) -> 46295 | ... T8: =EOMONTH(S8,1) -> 46387 | V8: Year 1 | W8: Year 2 | X8: Year 3 | Y8: Year 4 | Z8: Year 5 | AA8: Year 6 | AB8: Year 7 | AC8: Year 8 | AD8: Year 9 | AE8: Year 10 | AF8: Year 11 | AG8: Year 12 | AH8: Year 13 | AI8: Year 14 | AJ8: Year 15
C11: Occupancy Statistics
